Workbook
Name Bild: Allgemein!$L$2
Name DAIKIN: Heizungsauswahl[DAIKIN]
Name DAIKIN: Heizungsauswahl[DAIKIN]
Name DAIKIN: Heizungsauswahl[DAIKIN]
Name Heizungshersteller: Heizungsauswahl[Hersteller]
Name Heizungshersteller: Heizungsauswahl[Hersteller]
Name Heizungshersteller: Heizungsauswahl[Hersteller]
Name LG: Heizungsauswahl[LG]
Name LG: Heizungsauswahl[LG]
Name LG: Heizungsauswahl[LG]
Name r_Adresse: Datenaustausch!$D$5:$D$8
Name r_Angaben: Datenaustausch!$C$10:$E$15
Name r_Ausgaben: Datenaustausch!$BV$13:$BW$17
Name r_BEGEM: Datenaustausch!$BI$30:$BM$38
Name r_BEGWG: Datenaustausch!$BI$41:$BM$43
Name r_CO2Flugnach: Datenaustausch!$K$26
Name r_Co2Flugvor: Datenaustausch!$K$25
Name r_CO2Nach: Datenaustausch!$E$26
Name r_CO2Vor: Datenaustausch!$E$25
Name r_CO2Weltnach: Datenaustausch!$J$26
Name r_CO2Weltvor: Datenaustausch!$J$25
Name r_Dach: Datenaustausch!$BR$23:$BS$23
Name r_Effizienshaus: Datenaustausch!$J$32
Name r_EffizienzhausVAR1: Datenaustausch!$AJ$57
Name r_EffizienzhausVAR2: Datenaustausch!$AJ$79
Name r_EffizienzhausVAR3: Datenaustausch!$AJ$98
Name r_Einnahmen: Datenaustausch!$BR$13:$BS$17
Name r_EinsparungenEMPF: Datenaustausch!$AQ$13:$AR$14
Name r_EinsparungenVar1: Datenaustausch!$AC$13:$AD$14
Name r_EinsparungenVar2: Datenaustausch!$AG$13:$AH$14
Name r_EinsparungenVar3: Datenaustausch!$AL$13:$AM$14
Name r_EinsparungTabelleEMPF: Datenaustausch!$AQ$31:$AR$31
Name r_EinsparungTabelleVAR1: Datenaustausch!$AC$31:$AD$31
Name r_EinsparungTabelleVAR2: Datenaustausch!$AG$31:$AH$31
Name r_EinsparungTabelleVAR3: Datenaustausch!$AL$31:$AM$31
Name r_EndenergiebedarfText: Datenaustausch!$BV$6:$BX$8
Name r_Energieeffizienzklasse: Datenaustausch!$AS$85
Name r_EnergielabelVar1: Datenaustausch!$AG$57
Name r_EnergielabelVar2: Datenaustausch!$AG$79
Name r_EnergielabelVar3: Datenaustausch!$AG$98
Name r_Ersparniss: Datenaustausch!$J$31
Name r_Fassade: Datenaustausch!$BR$24:$BS$24
Name r_Fenster: Datenaustausch!$BR$25:$BS$25
Name r_HeizundStromenergie: Datenaustausch!$C$17:$E$22
Name r_HeizundStromkosten: Datenaustausch!$G$17:$I$22
Name r_Heizung: Datenaustausch!$BR$29:$BS$29
Name r_Keller: Datenaustausch!$BR$27:$BS$27
Name r_KostenbilanzEMPF: Datenaustausch!$AQ$46:$AR$46
Name r_KostenbilanzUMSETZ: Datenaustausch!$AQ$33:$AR$33
Name r_KostenbilanzVAR1: Datenaustausch!$AC$33:$AD$33
Name r_KostenbilanzVAR2: Datenaustausch!$AG$33:$AH$33
Name r_KostenbilanzVAR3: Datenaustausch!$AL$33:$AM$33
Name r_KostenEMPF: Datenaustausch!$AQ$17:$AR$20
Name r_KostenTabelleEMPF: Datenaustausch!$AQ$32:$AR$32
Name r_KostenTabelleVAR1: Datenaustausch!$AC$32:$AD$32
Name r_KostenTabelleVAR2: Datenaustausch!$AG$32:$AH$32
Name r_KostenTabelleVAR3: Datenaustausch!$AL$32:$AM$32
Name r_KostenVAR1: Datenaustausch!$AC$17:$AD$20
Name r_KostenVAR2: Datenaustausch!$AG$17:$AH$20
Name r_KostenVAR3: Datenaustausch!$AL$17:$AM$20

Sheet Allgemein
B2: Projektnummer: | D2: Zuständiger Sanierungslotse: | F2: =_xlfn.TEXTJOIN(" - ",TRUE,C2,RIGHT(C4,LEN(C4)-FIND(", ",C4)-1)) -> #VALUE! | L2: Bild von Haus!!! | O2: #VALUE!
B3: Anrede:
B4: Vorname Nachname: | D4: Zuständiger Energieberater:
B5: Straße, Nr. (Objektadresse): | F5: Kurzbeschreibung: | I5: Sanierung EFH
B6: PLZ, Ort: | D6: =IF(AND(C5<>"",C6<>""), HYPERLINK("https://www.google.com/maps/search/"&_xlfn.TEXTBEFORE(C6," ")&"+"&_xlfn.TEXTAFTER(C6," ")&"+"&C5, "Projekt in Maps anzeigen"), "")
B7: Email: | F7: Preis Gesamt: | I7: =J104 -> 0
B8: Telefon: | D8: besondere technische Zuwendung:
B9: Sharepoint | C9: Airteam | D9: Magicplan
E10: Legende: | F10: Energieberater | G10: Kalkulator | H10: Sanierungslotse
B11: Allgemeines Bestand:
B12: Gebäude | F12: Geschosse | J12: Strom und Heizkosten
B13: Gebäudebezeichnung: | D13: Gebäudetyp: | F13: Geschoss | G13: Anzahl | H13: lichte Raumhöhe | I13: Geschosshöhe | J13: Stromkosten
B14: Wohnfläche [m²]: | D14: Baujahr: | J14: Vebrauch Strom [kWh/Jahr]: | M14: Kosten Strom [€/kWh]:
B15: Wohneinheiten: | D15: Denkmalschutz: | J15: Heizkosten
B16: Anzahl der Personen: | D16: Beschreibung Denkmalschutz: | J16: Energieträger: | M16: Abrechnungseinheit:
B17: Kubatur: | J17: =_xlfn.TEXTJOIN(,,"Vebrauch Heizung [",O16,"/Jahr]:") -> Vebrauch Heizung [/Jahr]: | M17: =_xlfn.TEXTJOIN(,,"Kosten Heizung [€/",O16,"]:") -> Kosten Heizung [€/]:
B18: Anbausituation:
B19: Grundfläche des Hauses [m²]: | D19: Haus Länge [m]: | J19: =_xlfn.TEXTJOIN(,,"Heizwert [kWh/",O16,"]:") -> Heizwert [kWh/]: | L19: {=_xlfn.XLOOKUP(L16&O16,Heizung[Heizmedium]&Heizung[Einheit],Heizung[Heizwert '[kWh/Einheit']])} -> 0 | M19: CO2 Emmisionen [g/kWh]: | O19: {=_xlfn.XLOOKUP(Allgemein!L16&Allgemein!O16,Heizung[Heizmedium]&Heizung[Einheit],Heizung[CO2 Emmisionen '[g/kWh']],"",0,1)} -> 0
B20: Zugang zur Baustelle | D20: Haus Breite [m]: | J20: (manuell wenn nicht in Datenbank) | M20: (manuell wenn nicht in Datenbank)
B21: Befahrbarkeit für Fahzeuge < 40t möglich? | D21: Beschreibung Baustellenzufahrt:
B22: Absperrung Zufahrt nötig?:
B23: Zufahrtsbreite von 3,5m gegeben?:
B24: Interesse des Kunden/ Wunsch
B25: Wunsch Kunde | D25: Ist-Aufbau | E25: Ist- U-Wert | F25: Energetische Bewertung | G25: GEG-/ BEG -Norm | I25: Sowieso-Kosten | J25: Begründung | L25: Notizen Datenaufnahme | O25: Besonderheiten Gebäude
B26: Dach: | D26: - | I26: =_xlfn.XLOOKUP(J26,'Datenbank-Preise'!B140:B149,'Datenbank-Preise'!C140:C149,0,0,1)*Dach!E11 -> 0 | J26: -
B27: Fassade: | D27: - | I27: =_xlfn.XLOOKUP(J27,'Datenbank-Preise'!E140:E148,'Datenbank-Preise'!F140:F148,0,0,1)*Fassade!$P$523 -> 0 | J27: -
B28: Fenster: | D28: - | I28: =_xlfn.XLOOKUP(J28,'Datenbank-Preise'!H140:H148,'Datenbank-Preise'!I140:I148,0,0,1)*Fenster!J12+IF(AND(Fenster!J15>=1,J28<>"-",J28<>""),Fenster!J15*'Datenbank-Preise'!O140,0) -> 0 | J28: -
B29: Boden (unterer Gebäudeabschluss): | D29: - | I29: 0 | J29: -
B30: Keller: | D30: - | I30: =_xlfn.XLOOKUP(Allgemein!J30,'Datenbank-Preise'!Q140:Q142,'Datenbank-Preise'!R140:R142,0,0,1)*'Boden u. Keller'!E14+_xlfn.XLOOKUP(Allgemein!J30,'Datenbank-Preise'!Q140:Q142,'Datenbank-Preise'!S140:S142,0,0,1)*'Boden u. Keller'!E15 -> 0 | J30: -
B31: Heizung: | D31: - | I31: =_xlfn.XLOOKUP(J31,'Datenbank-Preise'!K140:K148,'Datenbank-Preise'!L140:L148,0,0,1) -> 0 | J31: -
B32: Photovoltaik: | I32: =SUM(I26:I31) -> 0 | J32: Summe
B33: Sonstiges
B34: Interesse / Anmerkungen | C34: Internes Gespräch + Fragen fürs Erstgespräch | D34: Ergebnisse Erstgespräch | G34: Ergebnisse Zweitgespräch | K34: Änderungsprotokollierung
B36: Ausgangszustand
B37: Ausgangswerte für Wirtschaftlichkeitsberechnung
B38: Primärenergiebedarf: | D38: kWh/m²a | E38: Endenergiebedarf Gerechnet: | H38: kWh/m²a | I38: Heizwärmemenge: | K38: =G40*C40 -> #DIV/0! | L38: kWh/a | M38: Vebrauch Strom [kWh/Jahr]: | O38: =L14 -> 0 | P38: kWh/a
B39: Heizwärmebedarf Nach Berechnung: | D39: kWh/m²a | E39: Endenergiebedarf Nach Verbrauch: | G39: =L19*L17/C40 -> #DIV/0! | H39: kWh/m²a | I39: Heizpreis pro kWh: | K39: =O17/L19 -> #DIV/0! | L39: /kWh | M39: Kosten Strom [€/kWh]: | O39: =O14 -> 0 | P39: /kWh
B40: Gebäudenutzfläche [Grundlage iSFP, Energieausweis]: | D40: m² | E40: Endenergiebedarf Annahme (Wirtschaftlichkeit): | G40: =G39 -> #DIV/0! | H40: kWh/m²a | I40: Heizkosten pro Jahr: | K40: =K38*K39 -> #DIV/0! | L40: /a | M40: Stromkosten [€/Jahr]: | O40: =L14*O14 -> 0 | P40: /a
B41: Varianten | F41: U-Wert Tabelle nach BEG
B42: iSFP | K42: BEG WG + Kredite:
C43: Kurzbeschreibung Maßnahmen Standard | E43: Maßnahmen Erweiterung | F43: U-Wert Nach | G43: Preisschätzung ST. | H43: Satz | I43: Förderbare Kosten | J43: Direkt Summe | K43: Kredit: | L43: BEG WG | M43: Ergänzungskredit | N43: Zusatz Darlehen | O43: Gesamt
B44: Dach: | C44: - | D44: - | G44: =IF(C44="-",0,'Datenbank-Preise'!$P$13) -> 0 | H44: 0.2 | J44: =H44*I44 -> 0 | K44: Maßnahmen?: | L44: - | M44: - | N44: -
B45: Fassade: | C45: - | D45: - | G45: ='Datenbank-Preise'!$O$27 -> 0 | H45: 0.2 | J45: =H45*I45 -> 0 | O45: =L46+M46+N46 -> 0
B46: Fenster: | C46: - | G46: =IF(C46="-",0,'Datenbank-Preise'!O40) -> 0 | H46: 0.2 | J46: =H46*I46 -> 0 | K46: Kreditsumme: | L46: 0 | M46: 0 | N46: 0
B47: Boden (unterer Gebäudeabschluss): | C47: - | D47: - | G47: ='Datenbank-Preise'!M56 -> 0 | H47: 0.2 | J47: =H47*I47 -> 0 | K47: Tilgungszuschuss: | L47: 0 | M47: 0 | N47: 0
B48: Keller: | C48: - | D48: - | G48: ='Datenbank-Preise'!N84 -> 0 | H48: 0.2 | J48: =H48*I48 -> 0 | K48: Zinssatz: | L48: 0 | M48: 0 | N48: 0
B49: Summe Gebäudehülle: | C49: =_xlfn.TEXTJOIN(" + ",,IF(C44="-","","Dach"),IF(C45="-","","Fassade"),IF(C46="-","","Fenster"),IF(C47="-","","Boden (unterer Gebäudeabschluss)"),IF(C48="-","","Keller")) | G49: =SUM(G44:G48) -> 0 | H49: =SUM(H44:H48)/COUNT(H44:H48) -> 0.2 | I49: =SUM(I44:I48) -> 0 | J49: =SUM(J44:J48) -> 0 | K49: Laufzeit: | L49: 0 | M49: 0 | N49: 0
B50: Heizung/ Wärmeübertragung: | G50: ='Datenbank-Preise'!$O$116 -> 0 | H50: 0.5 | J50: =H50*I50 -> 0 | K50: Tilgungsfreie Anlaufzeit: | L50: 0 | M50: 0 | N50: 0
B51: kWp / Speicher | C51: - | D51: - | G51: ='Datenbank-Preise'!Z111 -> 0 | H51: Weiter Förderbar: | I51: =G49-I49 -> 0 | K51: AnfänglicheTilgung: | L51: 0 | M51: 0 | N51: 0
B52: Sonstiges: | C52: - | D52: =IF(C52="Dezentrale Lüftungsanlage","Anzahl: "&Sonstiges!I12,"") | G52: =IF(C52="Dezentrale Lüftungsanlage",'Datenbank-Preise'!G237,0) -> 0 | H52: Kosten zu finanzieren: | I52: =G53-J54 -> 0 | K52: Jahre bis Volltilgung: | L52: =_xlfn.XLOOKUP(0,Datenbank!D38:AH38,Datenbank!D25:AH25) -> 1 | M52: =_xlfn.XLOOKUP(0,Datenbank!D55:AH55,Datenbank!D25:AH25) -> 1 | N52: =_xlfn.XLOOKUP(0,Datenbank!D72:AH72,Datenbank!D25:AH25) -> 1
B53: WB-Berechnung, Wert: | C53: Nein | D53: 0.1 | F53: =Datenbank!AN104 -> #DIV/0! | G53: =SUM(G49:G52) -> 0 | K53: Monatliche Belastung: | L53: =(L51+L48)*L46/12 -> 0 | M53: =(M51+M48)*M46/12 -> 0 | N53: =(N51+N48)*N46/12 -> 0 | O53: =L53+M53+N53 -> 0
B54: Primär-E / End-E / Heizwärmebedarf realistisch | F54: Einsparung | G54: Kosten | I54: Direkt Summe: | J54: =SUM(J49:J50) -> 0 | K54: Tilgungszuschuss: | L54: =L47*L46 -> 0 | M54: =M47*M46 -> 0 | N54: Förderung: | O54: =SUM(J54,L54,M54) -> 0
B55: Heizlast kW | H55: Anmerkungen:
B56: Wird ein Effizienzhausstandard erreicht? | C56: Nicht ausgefüllt | D56: - | E56: -
B58: Variante 1 | K58: BEG WG + Kredite:
C59: Kurzbeschreibung Maßnahmen Standard | E59: Maßnahmen Erweiterung | F59: U-Wert Nach | G59: Preisschätzung ST. | H59: Satz | I59: Förderbare Kosten | J59: Direkt Summe | K59: Kredit: | L59: BEG WG | M59: Ergänzungskredit | N59: Zusatz Darlehen | O59: Gesamt
B60: Dach: | C60: - | D60: - | G60: =IF(C60="-",0,'Datenbank-Preise'!$R$13) -> 0 | H60: 0.2 | J60: =H60*I60 -> 0 | K60: Maßnahmen?: | L60: - | M60: - | N60: -
B61: Fassade: | C61: - | D61: - | G61: ='Datenbank-Preise'!$Q$27 -> 0 | H61: 0.2 | J61: =H61*I61 -> 0 | O61: =L62+M62+N62 -> 0
B62: Fenster: | C62: - | G62: =IF(C62="-",0,'Datenbank-Preise'!Q40) -> 0 | H62: 0.2 | J62: =H62*I62 -> 0 | K62: Kreditsumme: | L62: 0 | M62: 0 | N62: 0
B63: Boden (unterer Gebäudeabschluss): | C63: - | D63: - | G63: ='Datenbank-Preise'!O56 -> 0 | H63: 0.2 | J63: =H63*I63 -> 0 | K63: Tilgungszuschuss: | L63: 0 | M63: 0 | N63: 0
B64: Keller: | C64: - | D64: - | G64: ='Datenbank-Preise'!P84 -> 0 | H64: 0.2 | J64: =H64*I64 -> 0 | K64: Zinssatz: | L64: 0 | M64: 0 | N64: 0
B65: Summe Gebäudehülle: | C65: =_xlfn.TEXTJOIN(" + ",,IF(C60="-","","Dach"),IF(C61="-","","Fassade"),IF(C62="-","","Fenster"),IF(C63="-","","Boden (unterer Gebäudeabschluss)"),IF(C64="-","","Keller")) | G65: =SUM(G60:G64) -> 0 | H65: =SUM(H60:H64)/COUNT(H60:H64) -> 0.2 | I65: =SUM(I60:I64) -> 0 | J65: =SUM(J60:J64) -> 0 | K65: Laufzeit: | L65: 0 | M65: 0 | N65: 0
B66: Heizung/ Wärmeübertragung: | G66: ='Datenbank-Preise'!$Q$116 -> 0 | H66: 0.5 | J66: =H66*I66 -> 0 | K66: Tilgungsfreie Anlaufzeit: | L66: 0 | M66: 0 | N66: 0
B67: kWp / Speicher / Autarkiegrad: | C67: - | D67: - | G67: ='Datenbank-Preise'!AB111 -> 0 | H67: Weiter Förderbar: | I67: =G65-I65 -> 0 | K67: AnfänglicheTilgung: | L67: 0 | M67: 0 | N67: 0
B68: Sonstiges: | C68: - | D68: =IF(C68="Dezentrale Lüftungsanlage","Anzahl: "&Sonstiges!J12,"") | G68: =IF(C68="Dezentrale Lüftungsanlage",'Datenbank-Preise'!I237,0) -> 0 | H68: Kosten zu finanzieren: | I68: =G69-J70 -> 0 | K68: Jahre bis Volltilgung: | L68: =_xlfn.XLOOKUP(0,Datenbank!D147:AH147,Datenbank!D134:AH134) -> 1 | M68: =_xlfn.XLOOKUP(0,Datenbank!D164:AH164,Datenbank!D134:AH134) -> 1 | N68: =_xlfn.XLOOKUP(0,Datenbank!D181:AH181,Datenbank!D134:AH134) -> 1
B69: WB-Berechnung, Wert: | C69: Nein | D69: 0.1 | F69: =Datenbank!AN214 -> #DIV/0! | G69: =SUM(G65:G68) -> 0 | K69: Monatliche Belastung: | L69: =(L67+L64)*L62/12 -> 0 | M69: =(M67+M64)*M62/12 -> 0 | N69: =(N67+N64)*N62/12 -> 0 | O69: =L69+M69+N69 -> 0
B70: Primär-E / End-E / Heizwärmebedarf realistisch | F70: Einsparung | G70: Kosten | I70: Direkt Summe: | J70: =SUM(J65:J66) -> 0 | K70: Tilgungszuschuss: | L70: =L63*L62 -> 0 | M70: =M63*M62 -> 0 | N70: Förderung: | O70: =SUM(J70,L70,M70) -> 0
B71: Heizlast kW | H71: Anmerkungen:
B72: Wird ein Effizienzhausstandard erreicht? | C72: Nicht ausgefüllt | D72: - | E72: -
B74: Variante 2 | K74: BEG WG + Kredite:
C75: Kurzbeschreibung Maßnahmen Standard | E75: Maßnahmen Erweiterung | F75: U-Wert Nach | G75: Preisschätzung ST. | H75: Satz | I75: Förderbare Kosten | J75: Direkt Summe | K75: Kredit: | L75: BEG WG | M75: Ergänzungskredit | N75: Zusatz Darlehen | O75: Gesamt
B76: Dach: | C76: - | D76: - | G76: =IF(C76="-",0,'Datenbank-Preise'!$T$13) -> 0 | H76: 0.2 | J76: =H76*I76 -> 0 | K76: Maßnahmen?: | L76: - | M76: - | N76: -
B77: Fassade: | C77: - | D77: - | G77: ='Datenbank-Preise'!$S$27 -> 0 | H77: 0.2 | J77: =H77*I77 -> 0 | O77: =L78+M78+N78 -> 0
B78: Fenster: | C78: - | G78: =IF(C78="-",0,'Datenbank-Preise'!S40) -> 0 | H78: 0.2 | J78: =H78*I78 -> 0 | K78: Kreditsumme: | L78: 0 | M78: 0 | N78: 0
B79: Boden (unterer Gebäudeabschluss): | C79: - | D79: - | G79: ='Datenbank-Preise'!Q56 -> 0 | H79: 0.2 | J79: =H79*I79 -> 0 | K79: Tilgungszuschuss: | L79: 0 | M79: 0 | N79: 0
B80: Keller: | C80: - | D80: - | G80: ='Datenbank-Preise'!R84 -> 0 | H80: 0.2 | J80: =H80*I80 -> 0 | K80: Zinssatz: | L80: 0 | M80: 0 | N80: 0
B81: Summe Gebäudehülle: | C81: =_xlfn.TEXTJOIN(" + ",,IF(C76="-","","Dach"),IF(C77="-","","Fassade"),IF(C78="-","","Fenster"),IF(C79="-","","Boden (unterer Gebäudeabschluss)"),IF(C80="-","","Keller")) | G81: =SUM(G76:G80) -> 0 | H81: =SUM(H76:H80)/COUNT(H76:H80) -> 0.2 | I81: =SUM(I76:I80) -> 0 | J81: =SUM(J76:J80) -> 0 | K81: Laufzeit: | L81: 0 | M81: 0 | N81: 0
B82: Heizung/ Wärmeübertragung: | G82: ='Datenbank-Preise'!$S$116 -> 0 | H82: 0.5 | J82: =H82*I82 -> 0 | K82: Tilgungsfreie Anlaufzeit: | L82: 0 | M82: 0 | N82: 0
B83: kWp / Speicher / Autarkiegrad: | C83: - | D83: - | G83: ='Datenbank-Preise'!AD111 -> 0 | H83: Weiter Förderbar: | I83: =G81-I81 -> 0 | K83: AnfänglicheTilgung: | L83: 0 | M83: 0 | N83: 0
B84: Sonstiges: | C84: - | D84: =IF(C84="Dezentrale Lüftungsanlage","Anzahl: "&Sonstiges!K12,"") | G84: =IF(C84="Dezentrale Lüftungsanlage",'Datenbank-Preise'!K237,0) -> 0 | H84: Kosten zu finanzieren: | I84: =G85-J86 -> 0 | K84: Jahre bis Volltilgung: | L84: =_xlfn.XLOOKUP(0,Datenbank!D264:AH264,Datenbank!D251:AH251) -> 1 | M84: =_xlfn.XLOOKUP(0,Datenbank!D281:AH281,Datenbank!D268:AH268) -> 1 | N84: =_xlfn.XLOOKUP(0,Datenbank!D298:AH298,Datenbank!D285:AH285) -> 1
B85: WB-Berechnung, Wert: | C85: Nein | D85: 0.1 | F85: =Datenbank!AN331 -> #DIV/0! | G85: =SUM(G81:G84) -> 0 | K85: Monatliche Belastung: | L85: =(L83+L80)*L78/12 -> 0 | M85: =(M83+M80)*M78/12 -> 0 | N85: =(N83+N80)*N78/12 -> 0 | O85: =L85+M85+N85 -> 0
B86: Primär-E / End-E / Heizwärmebedarf realistisch | F86: Einsparung | G86: Kosten | I86: Direkt Summe: | J86: =SUM(J81:J82) -> 0 | K86: Tilgungszuschuss: | L86: =L79*L78 -> 0 | M86: =M79*M78 -> 0 | N86: Förderung: | O86: =SUM(J86,L86,M86) -> 0
B87: Heizlast kW | H87: Anmerkungen:
B88: Wird ein Effizienzhausstandard erreicht? | C88: Nicht ausgefüllt | D88: - | E88: -
B91: Welche Variante wird verfolgt? | C91: nicht festgelegt
B92: Maßnahmenliste | L92: auf Standardpreis
B93: Maßnahmenpaket | C93: Kurzbeschreibung Maßnahmen Standard | E93: Maßnahmen Erweiterung | F93: Preis Standard | G93: Zusatz-Leistung | I93: Preis Zusatz | J93: Preis Gesamt | K93: Sowieso-Kosten | L93: Wertsteigerung
B94: Dach: | C94: ='Datenbank-Preise'!B266 -> 0 | D94: ='Datenbank-Preise'!B273 -> 0 | E94: ='Datenbank-Preise'!B280 | F94: =IF($C$91="iSFP",G44,IF($C$91="Variante 1",G60,IF($C$91="Variante 2",G76,0))) -> 0 | I94: 0 | J94: =F94+I94 -> 0 | K94: =Datenaustausch!X69 -> 0 | L94: =IF($L$92="auf Standardpreis",F94*0.8,J94*0.8) -> 0
B95: Fassade: | C95: ='Datenbank-Preise'!C266 -> 0 | D95: ='Datenbank-Preise'!C273 -> 0 | E95: ='Datenbank-Preise'!C280 | F95: =IF($C$91="iSFP",G45,IF($C$91="Variante 1",G61,IF($C$91="Variante 2",G77,0))) -> 0 | I95: 0 | J95: =F95+I95 -> 0 | K95: =Datenaustausch!X70 -> 0 | L95: =IF($L$92="auf Standardpreis",F95*0.8,J95*0.8) -> 0
B96: Fenster: | C96: ='Datenbank-Preise'!D266 -> 0 | D96: ='Datenbank-Preise'!D273 | E96: ='Datenbank-Preise'!D280 | F96: =IF($C$91="iSFP",G46,IF($C$91="Variante 1",G62,IF($C$91="Variante 2",G78,0))) -> 0 | I96: 0 | J96: =F96+I96 -> 0 | K96: =Datenaustausch!X71 -> 0 | L96: =IF($L$92="auf Standardpreis",F96*0.8,J96*0.8) -> 0
B97: Boden (unterer Gebäudeabschluss): | C97: ='Datenbank-Preise'!E266 -> 0 | D97: ='Datenbank-Preise'!E273 -> 0 | E97: ='Datenbank-Preise'!E280 | F97: =IF($C$91="iSFP",G47,IF($C$91="Variante 1",G63,IF($C$91="Variante 2",G79,0))) -> 0 | I97: 0 | J97: =F97+I97 -> 0 | K97: 0 | L97: =IF($L$92="auf Standardpreis",F97*0.8,J97*0.8) -> 0
B98: Keller: | C98: ='Datenbank-Preise'!F266 -> 0 | D98: ='Datenbank-Preise'!F273 -> 0 | E98: ='Datenbank-Preise'!F280 | F98: =IF($C$91="iSFP",G48,IF($C$91="Variante 1",G64,IF($C$91="Variante 2",G80,0))) -> 0 | I98: 0 | J98: =F98+I98 -> 0 | K98: =Datenaustausch!X72 -> 0 | L98: =IF($L$92="auf Standardpreis",F98*0.8,J98*0.8) -> 0
B99: Summe Gebäudehülle: | C99: =IF($C$91="nicht festgelegt","nicht festgelegt",_xlfn.TEXTJOIN(" + ",,IF(C94="-","","Dach"),IF(C95="-","","Fassade"),IF(C96="-","","Fenster"),IF(C97="-","","Boden (unterer Gebäudeabschluss)"),IF(C98="-","","Keller"))) -> nicht festgelegt | F99: =SUM(F94:F98) -> 0 | I99: =SUM(I94:I98) -> 0 | J99: =F99+I99 -> 0 | K99: =SUM(K94:K98) -> 0 | L99: =IF($L$92="auf Standardpreis",F99*0.8,J99*0.8) -> 0
B100: Heizung: | C100: ='Datenbank-Preise'!G266 -> 0 | D100: ='Datenbank-Preise'!G273 -> 0 | E100: ='Datenbank-Preise'!G280 | F100: =IF($C$91="iSFP",G50,IF($C$91="Variante 1",G66,IF($C$91="Variante 2",G82,0))) -> 0 | I100: 0 | J100: =F100+I100 -> 0 | K100: =Datenaustausch!X73 -> 0 | L100: =IF($L$92="auf Standardpreis",F100*0.8,J100*0.8) -> 0
B101: Photovoltaik: | C101: ='Datenbank-Preise'!H266 -> 0 | D101: ='Datenbank-Preise'!H273 -> 0 | E101: ='Datenbank-Preise'!H280 | F101: =IF($C$91="iSFP",G51,IF($C$91="Variante 1",G67,IF($C$91="Variante 2",G83,0))) -> 0 | I101: 0 | J101: =F101+I101 -> 0 | L101: =IF($L$92="auf Standardpreis",F101*0.8,J101*0.8) -> 0
B102: Sonstiges: | C102: ='Datenbank-Preise'!I266 -> 0 | D102: ='Datenbank-Preise'!I273 -> 0 | E102: ='Datenbank-Preise'!I280 | F102: =IF($C$91="iSFP",G52,IF($C$91="Variante 1",G68,IF($C$91="Variante 2",G84,0))) -> 0 | I102: 0 | J102: =F102+I102 -> 0 | K102: 0 | L102: =IF($L$92="auf Standardpreis",F102*0.8,J102*0.8) -> 0
A103: 0 | B103: BRALE Energy | F103: 0 | J103: =F103 -> 0
B104: Summe: | F104: =SUM(F99:F103) -> 0 | I104: =SUM(I99:I102) -> 0 | J104: =SUM(J99:J103) -> 0 | K104: =SUM(K99:K102) -> 0 | L104: =SUM(L99:L102) -> 0
B106: Allgemeine Umsetzungshinweise | D106: Förderung | F106: Einzelmaßnahme BEG EM: | J106: BEG WG + Kredite:
D107: Maßnahmenpaket | E107: Preis Gesamt | F107: U-Wert Nach | G107: Satz | H107: Förderbare Kosten | I107: Direkt Summe | J107: Kredit: | K107: BEG WG | L107: Ergänzungskredit | M107: Zusatz Darlehen | N107: Gesamt | O107: =Datenaustausch!AS85
...

Sheet Datenbank-Preise
B2: Dach
B4: Position Dach | C4: Dacheindeckung: | D4: Dämmung Dachschrägen: | E4: Dämmung obere Geschossdecke: | F4: Trockenbau innen: | G4: Dachstuhl Neu komplett: | L4: Pro Position | M4: Einheit | N4: Preis Brutto | O4: Menge | P4: iSFP | Q4: Menge | R4: Variante 1 | S4: Menge | T4: Variante 2
B5: - | C5: Nein | D5: Nein | E5: Nein | F5: Nein | G5: Nein | L5: Dacheindeckung: | M5: m² | N5: 270 | O5: =Dach!I12 -> 0 | P5: =IF(Dach!I11="Nein",0,N5*O5) -> 0 | Q5: =Dach!J12 -> 0 | R5: =IF(Dach!J11="Nein",0,Q5*'Datenbank-Preise'!$N$5) -> 0 | S5: =Dach!K12 -> 0 | T5: =IF(Dach!K11="Nein",0,S5*'Datenbank-Preise'!$N$5) -> 0
B6: Dacheindeckung + Dämmung Schrägen (außen) | C6: Ja | D6: Ja | E6: Nein | F6: Nein | G6: Nein | L6: Dämmung Dachschrägen: | M6: m² | N6: 100 | O6: =Dach!I16 -> 0 | P6: =IF(Dach!I14="Nein",0,O6*N6) -> 0 | Q6: =Dach!J16 -> 0 | R6: =IF(Dach!J14="Nein",0,Q6*'Datenbank-Preise'!$N6) -> 0 | S6: =Dach!K16 -> 0 | T6: =IF(Dach!K14="Nein",0,S6*'Datenbank-Preise'!$N6) -> 0
B7: Dacheindeckung + Dämmung Schrägen (außen) + Dämmung obere Geschossdecke | C7: Ja | D7: Ja | E7: Ja | F7: Nein | G7: Nein | L7: Trockenbau innen | M7: m² | N7: 90 | O7: =Dach!I20 -> 0 | P7: =IF(Dach!I19="Nein",0,O7*'Datenbank-Preise'!$N7) -> 0 | Q7: =Dach!J20 -> 0 | R7: =IF(Dach!J19="Nein",0,Q7*'Datenbank-Preise'!$N7) -> 0 | S7: =Dach!K20 -> 0 | T7: =IF(Dach!K19="Nein",0,S7*'Datenbank-Preise'!$N7) -> 0
B8: Dämmung Schrägen mit Trockenbau (innen) + Dämmung obere Geschossdecke | C8: Nein | D8: Ja | E8: Ja | F8: Ja | G8: Nein | L8: Dämmung obere Geschossdecke | M8: m² | N8: 110 | O8: =Dach!I23 -> 0 | P8: =IF(Dach!I22="Nein",0,O8*'Datenbank-Preise'!$N8) -> 0 | Q8: =Dach!J23 -> 0 | R8: =IF(Dach!J22="Nein",0,Q8*'Datenbank-Preise'!$N8) -> 0 | S8: =Dach!K23 -> 0 | T8: =IF(Dach!K22="Nein",0,S8*'Datenbank-Preise'!$N8) -> 0
B9: Dämmung Schrägen mit Trockenbau (innen) | C9: Nein | D9: Ja | E9: Nein | F9: Ja | G9: Nein | L9: Dachstuhl Neu komplett | M9: m² | N9: 200 | O9: =Dach!I27 -> 0 | P9: =IF(Dach!I26="Nein",0,O9*'Datenbank-Preise'!$N9) -> 0 | Q9: =Dach!J27 -> 0 | R9: =IF(Dach!J26="Nein",0,Q9*'Datenbank-Preise'!$N9) -> 0 | S9: =Dach!K27 -> 0 | T9: =IF(Dach!K26="Nein",0,S9*'Datenbank-Preise'!$N9) -> 0
B10: Dämmung obere Geschossdecke | C10: Nein | D10: Nein | E10: Ja | F10: Nein | G10: Nein | L10: Gauben bei neuer Dachdeckung | M10: Stk. | N10: 5500 | O10: =Dach!I31 -> 0 | P10: =IF(Dach!I11="Nein",0,O10*'Datenbank-Preise'!$N10) -> 0 | Q10: =Dach!J31 -> 0 | R10: =IF(Dach!J11="Nein",0,Q10*'Datenbank-Preise'!$N10) -> 0 | S10: =Dach!K31 -> 0 | T10: =IF(Dach!K11="Nein",0,S10*'Datenbank-Preise'!$N10) -> 0
B11: Dacheindeckung + Dämmung Schrägen mit Trockenbau (innen) + Dämmung obere Geschossdecke | C11: Ja | D11: Ja | E11: Ja | F11: Ja | G11: Nein | L11: Dachflächenfenster | M11: Stk. | N11: 3800 | O11: =(Dach!I35+Dach!I36) -> 0 | P11: =O11*'Datenbank-Preise'!$N11 -> 0 | Q11: =(Dach!J35+Dach!J36) -> 0 | R11: =Q11*'Datenbank-Preise'!$N11 -> 0 | S11: =(Dach!K35+Dach!K36) -> 0 | T11: =S11*'Datenbank-Preise'!$N11 -> 0
B12: Dacheindeckung + Dämmung Schrägen mit Trockenbau (innen) | C12: Ja | D12: Ja | E12: Nein | F12: Ja | G12: Nein
B13: Dachstuhl neu | C13: Ja | D13: Ja | E13: Nein | F13: Ja | G13: Ja | P13: =SUBTOTAL(109,'Datenbank-Preise'!$P$5:$P$12) -> 0 | R13: =SUBTOTAL(109,'Datenbank-Preise'!$R$5:$R$12) -> 0 | T13: =SUBTOTAL(109,'Datenbank-Preise'!$T$5:$T$12) -> 0
B14: Dacheindeckung + Dämmung obere Geschossdecke | C14: Ja | D14: Nein | E14: Ja | F14: Nein | G14: Nein
B15: Sonstiges | C15: Nein | D15: Nein | E15: Nein | F15: Nein | G15: Nein
B16: =Allgemein!C44 -> -
B17: =Allgemein!C60 -> -
B18: =Allgemein!C76 -> -
B22: Fassade
B24: Position Fassade | C24: WDVS: | D24: Einblasdämmung: | I24: Pro Position | J24: Einheit | K24: Preis Brutto | M24: Preisschätzung | N24: Menge | O24: iSFP | P24: Menge | Q24: Variante 1 | R24: Menge | S24: Variante 2
B25: WDVS Dämmung der Außenfassade mit Strukturputz | C25: Ja | D25: Nein | M25: WDVS | N25: =Fassade!V527 -> 0 | O25: =N25*_xlfn.XLOOKUP(Allgemein!D45,Tabelle43[Fassade],Tabelle43[Preis]) -> 0 | P25: =Fassade!W527 -> 0 | Q25: =P25*_xlfn.XLOOKUP(Allgemein!D61,Tabelle43[Fassade],Tabelle43[Preis]) -> 0 | R25: =Fassade!X527 -> 0 | S25: =R25*_xlfn.XLOOKUP(Allgemein!D77,Tabelle43[Fassade],Tabelle43[Preis]) -> 0
B26: WDVS Dämmung der Außenfassade mit Strukturputz + Einblasdämmung | C26: Ja | D26: Ja | I26: Einblasdämmung | J26: m² | K26: 100 | M26: Einblasdämmung | N26: =Fassade!V524 -> 0 | O26: =N26*'Datenbank-Preise'!$K26 -> 0 | P26: =Fassade!W524 -> 0 | Q26: =P26*'Datenbank-Preise'!$K26 -> 0 | R26: =Fassade!X524 -> 0 | S26: =R26*'Datenbank-Preise'!$K26 -> 0
B27: Einblasdämmung | C27: Nein | D27: Ja | M27: Ergebnis | O27: =SUBTOTAL(109,'Datenbank-Preise'!$O$25:$O$26) -> 0 | Q27: =SUBTOTAL(109,'Datenbank-Preise'!$Q$25:$Q$26) -> 0 | S27: =SUBTOTAL(109,'Datenbank-Preise'!$S$25:$S$26) -> 0
B28: - | C28: Nein | D28: Nein
B29: =Allgemein!C45 -> -
B30: =Allgemein!C61 -> -
B31: =Allgemein!C77 -> -
B35: Fenster
B37: Position Fenster | C37: Fensteraustausch: | D37: Türaustausch: | I37: Pro Position | J37: Einheit | K37: Preis Brutto | M37: Preisschätzung | N37: Menge | O37: iSFP | P37: Menge | Q37: Variante 1 | R37: Menge | S37: Variante 2
B38: - | C38: Nein | D38: Nein | I38: Fensteraustausch: | J38: m² | K38: 1350 | M38: Fensteraustausch | N38: =Fenster!M13 -> 0 | O38: =IF(N38="",0,'Datenbank-Preise'!$K38*N38) -> 0 | P38: =Fenster!N13 -> 0 | Q38: =IF(P38="",0,'Datenbank-Preise'!$K38*P38) -> 0 | R38: =Fenster!O13 -> 0 | S38: =IF(R38="",0,'Datenbank-Preise'!$K38*R38) -> 0
B39: Fenster + Terrassentüren inkl. Demontage, Entsorgung und Rollläden + Türaustausch | C39: Ja | D39: Ja | I39: Türaustausch: | J39: Stk. | K39: 4000 | M39: Türaustausch | N39: =Fenster!R13 -> 0 | O39: =IF(N39="",0,'Datenbank-Preise'!$K39*N39) -> 0 | P39: =Fenster!S13 -> 0 | Q39: =IF(P39="",0,'Datenbank-Preise'!$K39*P39) -> 0 | R39: =Fenster!T13 -> 0 | S39: =IF(R39="",0,'Datenbank-Preise'!$K39*R39) -> 0
B40: Türaustausch ohne Fenstersanierung | C40: Nein | D40: Ja | M40: Summe | O40: =SUM(O38:O39) -> 0 | Q40: =SUM(Q38:Q39) -> 0 | S40: =SUM(S38:S39) -> 0
B41: Fenster + Terrassentüren inkl. Demontage, Entsorgung und Rollläden | C41: Ja | D41: Nein
B42: =Allgemein!C46 -> -
B43: =Allgemein!C62 -> -
B44: =Allgemein!C78 -> -
B49: Boden (unterer Gebäudeabschluss)
B51: Position Keller | C51: Kellerdeckendämmung: | D51: Dämmung des Fußbodens: | E51: Einblasdämmung:
B52: - | C52: Nein | D52: Nein | E52: Nein | G52: Pro Position | H52: Einheit | I52: Preis Brutto | K52: Preisschätzung | L52: Menge | M52: iSFP | N52: Menge | O52: Variante 1 | P52: Menge | Q52: Variante 2
B53: Dämmung der Kellerdecke | C53: Ja | D53: Nein | E53: Nein | G53: Dämmung Kellerdecke | K53: Dämmung Kellerdecke | L53: ='Boden u. Keller'!G12 -> 0 | M53: =L53*_xlfn.XLOOKUP(Allgemein!D47,MiWo42[Keller und FB],MiWo42[Preis]) -> 0 | N53: ='Boden u. Keller'!H12 -> 0 | O53: =N53*_xlfn.XLOOKUP(Allgemein!D63,MiWo42[Keller und FB],MiWo42[Preis]) -> 0 | P53: ='Boden u. Keller'!I12 -> 0 | Q53: =P53*_xlfn.XLOOKUP(Allgemein!D79,MiWo42[Keller und FB],MiWo42[Preis]) -> 0
B54: Dämmung des Fußbodens | C54: Nein | D54: Ja | E54: Nein | G54: Dämmung Fußboden | H54: m² | I54: 245 | K54: Dämmung Fußboden | L54: ='Boden u. Keller'!G15 -> 0 | M54: =L54*'Datenbank-Preise'!$I$54 -> 0 | N54: ='Boden u. Keller'!H15 -> 0 | O54: =N54*'Datenbank-Preise'!$I$54 -> 0 | P54: ='Boden u. Keller'!I15 -> 0 | Q54: =P54*'Datenbank-Preise'!$I$54 -> 0
B55: Dämmung der Kellerdecke und des Fußbodens | C55: Ja | D55: Ja | E55: Nein | G55: Kellerdämmung (inkl. Abdichten) | H55: m² | I55: 300
B56: Einblasdämmung | C56: Nein | D56: Nein | E56: Ja | G56: Horizontalsperre | H56: m | I56: 750 | K56: Summe | M56: =SUM(M53:M55) -> 0 | O56: =SUM(O53:O55) -> 0 | Q56: =SUM(Q53:Q55) -> 0
B57: Dämmung der Kellerdecke + Einblasdämmung | C57: Ja | D57: Nein | E57: Ja | G57: Ausschachten | H57: m² | I57: 100
B58: Dämmung des Fußbodens + Einblasdämmung | C58: Nein | D58: Ja | E58: Ja | G58: Summe
B59: Dämmung der Kellerdecke und des Fußbodens + Einblasdämmung | C59: Ja | D59: Ja | E59: Ja
B60: =Allgemein!C47 -> -
B61: =Allgemein!C63 -> -
B62: =Allgemein!C79 -> -
B70: Keller
B73: Position Keller | C73: Kellerinnendämmung: | D73: Kelleraußendämmung: | E73: Ausschachten: | F73: Horizontalsperre
B74: - | C74: Nein | D74: Nein | E74: Nein | F74: Nein
B75: Kellerinnendämmung | C75: Ja | D75: Nein | E75: Nein | F75: Nein
B76: Kellerinnendämmung (inkl. Abdichten) + Horizontalsperre | C76: Ja | D76: Nein | E76: Nein | F76: Ja
B77: Kelleraußendämmung (inkl. Abdichten) | C77: Nein | D77: Ja | E77: Nein | F77: Nein | H77: Pro Position | I77: Einheit | J77: Preis Brutto | L77: Preisschätzung | M77: Menge | N77: iSFP | O77: Menge | P77: Variante 1 | Q77: Menge | R77: Variante 2
B78: Kelleraußendämmung (inkl. Abdichten) + Horizontalsperre | C78: Nein | D78: Ja | E78: Nein | F78: Ja | H78: Dämmung Kellerdecke | L78: Kellerinnendämmung | M78: ='Boden u. Keller'!G24 -> 0 | N78: =M78*$J$80 -> 0 | O78: ='Boden u. Keller'!H24 -> 0 | P78: =O78*$J$80 -> 0 | Q78: ='Boden u. Keller'!I24 -> 0 | R78: =Q78*$J$80 -> 0
B79: Kelleraußendämmung (inkl. Abdichten) + Horizontalsperre + Ausschachten | C79: Nein | D79: Ja | E79: Ja | F79: Ja | H79: Dämmung Fußboden | I79: m² | J79: 245 | L79: Kelleraußendämmung | M79: ='Boden u. Keller'!G21 -> 0 | N79: =M79*'Datenbank-Preise'!$J$80 -> 0 | O79: ='Boden u. Keller'!H21 -> 0 | P79: =O79*'Datenbank-Preise'!$J$80 -> 0 | Q79: ='Boden u. Keller'!I21 -> 0 | R79: =Q79*'Datenbank-Preise'!$J$80 -> 0
B80: =Allgemein!C48 -> - | H80: Kellerdämmung (inkl. Abdichten) | I80: m² | J80: 300 | L80: Horizontalsperre | M80: ='Boden u. Keller'!G30 -> 0 | N80: =M80*'Datenbank-Preise'!$J$81 -> 0 | O80: ='Boden u. Keller'!H30 -> 0 | P80: =O80*'Datenbank-Preise'!$J$81 -> 0 | Q80: ='Boden u. Keller'!I30 -> 0 | R80: =Q80*'Datenbank-Preise'!$J$81 -> 0
B81: =Allgemein!C64 -> - | H81: Horizontalsperre | I81: m | J81: 750 | L81: Ausschachten | M81: ='Boden u. Keller'!G27 -> 0 | N81: =M81*'Datenbank-Preise'!$J$82 -> 0 | O81: ='Boden u. Keller'!H27 -> 0 | P81: =O81*'Datenbank-Preise'!$J$82 -> 0 | Q81: ='Boden u. Keller'!I27 -> 0 | R81: =Q81*'Datenbank-Preise'!$J$82 -> 0
B82: =Allgemein!C80 -> - | H82: Ausschachten | I82: m² | J82: 100
H83: Summe
L84: Summe | N84: =SUM(N78:N83) -> 0 | P84: =SUM(P78:P83) -> 0 | R84: =SUM(R78:R83) -> 0
B106: Heizung
M107: Preisschätzung | N107: Menge | O107: iSFP | P107: Menge | Q107: Variante 1 | R107: Menge | S107: Variante 2
M108: Wärmepumpe: | N108: - | O108: =IF(Wärmepumpe!I16="Ja",IF(Allgemein!$C$55>10,'Datenbank-Preise'!$K$111,K110),0) -> 0 | P108: - | Q108: =IF(Wärmepumpe!J16="Ja",IF(Allgemein!$C$71>10,'Datenbank-Preise'!$K$111,K110),0) -> 0 | R108: - | S108: =IF(Wärmepumpe!K16="Ja",IF(Allgemein!$C$87>10,'Datenbank-Preise'!$K$111,K110),0) -> 0 | X108: Preisschätzung PV | Y108: Menge | Z108: iSFP | AA108: Menge | AB108: Variante 1 | AC108: Menge | AD108: Variante 2
B109: Position Heizung | C109: Wärmepumpe: | D109: Ausbau Bestandsheizung: | E109: Neuer Trinkwasserspeicher: | F109: Pufferspeicher/hydr. Weiche: | I109: Pro Position | J109: Einheit | K109: Preis Brutto | M109: Ausbau Bestandsheizung: | N109: - | O109: =IF(Wärmepumpe!I21="Ja",'Datenbank-Preise'!$K$112,0) -> 0 | P109: - | Q109: =IF(Wärmepumpe!J21="Ja",'Datenbank-Preise'!$K$112,0) -> 0 | R109: - | S109: =IF(Wärmepumpe!K21="Ja",'Datenbank-Preise'!$K$112,0) -> 0 | X109: kWp | Y109: =Allgemein!C51 -> - | Z109: =_xlfn.XLOOKUP(Y109,PVGröße[kWp],PVGröße[Preis],,0,1) -> - | AA109: =Allgemein!C67 -> - | AB109: =_xlfn.XLOOKUP(AA109,PVGröße[kWp],PVGröße[Preis],,0,1) -> - | AC109: =Allgemein!C83 -> - | AD109: =_xlfn.XLOOKUP(AC109,PVGröße[kWp],PVGröße[Preis],,0,1) -> -
B110: Einbau Luftwärmepumpe + Ausbau Bestandsheizung + Trinkwasserspeicher | C110: Ja | D110: Ja | E110: Ja | F110: Nein | I110: Wärmepumpe bis 10 kW | J110: Stück | K110: 32000 | M110: Pufferspeicher/hydr. Weiche: | O110: 0 | Q110: 0 | S110: 0 | X110: kWh | Y110: =Allgemein!D51 -> - | Z110: =_xlfn.XLOOKUP(Y110,Tabelle35[Speicher],Tabelle35[Preis],0,1) -> 0 | AA110: =Allgemein!D67 -> - | AB110: =_xlfn.XLOOKUP(AA110,Tabelle35[Speicher],Tabelle35[Preis],0,1) -> 0 | AC110: =Allgemein!D83 -> - | AD110: =_xlfn.XLOOKUP(AC110,Tabelle35[Speicher],Tabelle35[Preis],0,1) -> 0
B111: Einbau Luftwärmepumpe + Ausbau Bestandsheizung | C111: Ja | D111: Ja | E111: Nein | F111: Nein | I111: Wärmepumpe ab 10 kW | J111: Stück | K111: 36000 | M111: Wärmepumpenheizkörper: | N111: =SUM(Wärmepumpe!C26:C27) -> 0 | O111: =IF(Wärmepumpe!I27="Ja",'Datenbank-Preise'!$K$114*N111,0) -> 0 | P111: =SUM(Wärmepumpe!C26:C27) -> 0 | Q111: =IF(Wärmepumpe!J27="Ja",'Datenbank-Preise'!$K$114*P111,0) -> 0 | R111: =SUM(Wärmepumpe!C26:C27) -> 0 | S111: =IF(Wärmepumpe!K27="Ja",'Datenbank-Preise'!$K$114*R111,0) -> 0 | X111: Summe | Z111: =SUM(Z109:Z110) -> 0 | AB111: =SUM(AB109:AB110) -> 0 | AD111: =SUM(AD109:AD110) -> 0
B112: Einbau Luftwärmepumpe als Hybridsystem + Trinkwasserspeicher | C112: Ja | D112: Nein | E112: Ja | F112: Nein | I112: Ausbau Bestandsheizung | J112: Stück | K112: 1000 | M112: Flächenheizung: | N112: =Allgemein!C40 -> 0 | O112: =IF(Wärmepumpe!I30="Ja",'Datenbank-Preise'!$K$115*N112,0) -> 0 | P112: =Allgemein!C40 -> 0 | Q112: =IF(Wärmepumpe!J30="Ja",'Datenbank-Preise'!$K$115*P112,0) -> 0 | R112: =Allgemein!C40 -> 0 | S112: =IF(Wärmepumpe!K30="Ja",'Datenbank-Preise'!$K$115*R112,0) -> 0
B113: Einbau Luftwärmepumpe als Hybridsystem | C113: Ja | D113: Nein | E113: Nein | F113: Nein | I113: Trinkwasserspeicher | J113: Stück | K113: 1000 | M113: Neuer Trinkwasserspeicher: | N113: - | O113: =IF(Wärmepumpe!I35="Ja",'Datenbank-Preise'!$K$113,0) -> 0 | P113: - | Q113: =IF(Wärmepumpe!J35="Ja",'Datenbank-Preise'!$K$112,0) -> 0 | R113: - | S113: =IF(Wärmepumpe!K35="Ja",'Datenbank-Preise'!$K$112,0) -> 0
B114: Ausbau Bestandsheizung + Einbau Luftwärmepumpe + Trinkwasserspeicher + Pufferspeicher/hydr. Weiche | C114: Ja | D114: Ja | E114: Ja | F114: Ja | I114: Wärmepumpenheizkörper | J114: Stück | K114: 2200
B115: Ausbau Bestandsheizung + Einbau Luftwärmepumpe + Pufferspeicher/hydr. Weiche | C115: Ja | D115: Ja | E115: Nein | F115: Ja | I115: Flächenheizung | J115: m² | K115: 170 | M115: Kompaktheizkörper | N115: =SUM(Wärmepumpe!C26:C27) -> 0 | O115: =IF(Wärmepumpe!I24="Ja",'Datenbank-Preise'!$K$116*N115,0) -> 0 | P115: =SUM(Wärmepumpe!C26:C27) -> 0 | Q115: =IF(Wärmepumpe!J24="Ja",'Datenbank-Preise'!$K$116*P115,0) -> 0 | R115: =SUM(Wärmepumpe!C26:C27) -> 0 | S115: =IF(Wärmepumpe!K24="Ja",'Datenbank-Preise'!$K$116*R115,0) -> 0
B116: Einbau Luftwärmepumpe als Hybridsystem + Trinkwasserspeicher + Pufferspeicher/hydr. Weiche | C116: Ja | D116: Nein | E116: Ja | F116: Ja | I116: Kompaktheizkörper | J116: Stück | K116: 1500 | M116: Summe | O116: =SUBTOTAL(109,'Datenbank-Preise'!$O$108:$O$115) -> 0 | Q116: =SUBTOTAL(109,'Datenbank-Preise'!$Q$108:$Q$115) -> 0 | S116: =SUBTOTAL(109,'Datenbank-Preise'!$S$108:$S$115) -> 0
B117: Einbau Luftwärmepumpe als Hybridsystem + Pufferspeicher/hydr. Weiche | C117: Ja | D117: Nein | E117: Nein | F117: Ja
B118: Heizungsanlage unverändert | C118: Nein | D118: Nein | E118: Nein | F118: Nein
B119: Sonstiges | C119: Nein | D119: Nein | E119: Nein | F119: Nein
B120: =Allgemein!C50 -> 0
B121: =Allgemein!C66 -> 0
B122: =Allgemein!C82 -> 0
B128: Position Wärmeabgabe | C128: Wärmepumpenheizkörper: | D128: Flächenheizung: | E128: neue Standardheizkörper:
B129: Austausch zu effizienten Wärmepumpenheizkörper | C129: Ja | D129: Nein | E129: Nein
B130: Einbau neuer Kompaktheizkörper | C130: Nein | D130: Nein | E130: Ja
B131: Einbau Flächenheizung | C131: Nein | D131: Ja | E131: Nein
B132: Wärmeübertragung unverändert | C132: Nein | D132: Nein | E132: Nein
B133: =Allgemein!D50 -> 0
B134: =Allgemein!D66 -> 0
B135: =Allgemein!D82 -> 0
B138: Sowieso-Kosten
B139: Dach | C139: Einzelpreis (pro m²) | E139: Fassade | F139: Einzelpreis (pro m²) | H139: Fenster | I139: Einzelpreis (pro m²) | K139: Heizung auswechseln | L139: Einzelpreis | N139: Tür | O139: Einzelpreis (pro Stück) | Q139: Keller | R139: Horizontalsperre [pro m] | S139: Abdichten+Ausschachten [m²] | T139: Summe
B140: Dachdeckung mit Unterspannbahn erneuern | C140: 270 | E140: Fassade Streichen und Putz ausbessern | F140: 108 | H140: =_xlfn.TEXTJOIN(" ",,"Fenster",IF(Fenster!J15>=1,"und Tür",""),"einfach auswechseln (zweifach-verglast)") -> Fenster einfach auswechseln (zweifach-verglast) | I140: 1000 | K140: Heizungsaustausch | L140: 15000 | N140: Tür auswechseln | O140: 3000 | Q140: Keller abdichten und trockenlegen | R140: 750 | S140: 300
B141: - | C141: 0 | E141: - | F141: 0 | H141: - | I141: 0 | K141: Heizung komplett neu | L141: 40000 | N141: - | O141: 0 | Q141: - | R141: 0 | S141: 0
B142: Dach vereinzelt ausbessern | C142: 50 | E142: Klinker ausbessern | F142: 100 | H142: =Allgemein!J28 -> - | K142: - | L142: 0 | Q142: =Allgemein!J30 -> - | R142: 0 | S142: 0
B143: =Allgemein!J26 -> - | E143: =Allgemein!J27 -> - | K143: =Allgemein!J31 -> -
B156: Preislisten
B165: Dach | D165: Keller | G165: Fassade | J165: PV | R165: Fenster | X165: Heizung | AJ165: Elektro
B167: Dach | D167: Keller und FB | E167: Preis | G167: Fassade | H167: Preis | J167: PV Module | K167: Spalte1 | L167: kWp | M167: Preis | O167: Speicher | P167: Preis | R167: Fensterart | T167: Dachflächenfenster | V167: Türart | X167: Trinkwasserspeicher | AA167: Pufferspeicher | AC167: Hersteller | AD167: Viessman | AE167: Vaillant | AF167: DAIKIN | AG167: Samsung | AH167: LG | AJ167: Umsetzungspositionen Elektro
B168: - | D168: - | G168: - | H168: 0 | J168: - | K168: - | L168: - | M168: - | O168: - | P168: 0 | R168: Wärmeschutzfenster (Uw 0,86) | T168: RotoQ Schwingfenster Q4 Kunststoff 2C (Uw 1,1) | V168: Wärmeschutztür (Uw <<1,3) | X168: Viessmann CVAB 300l | AA168: Viessmann Puffer | AC168: Viessmann | AD168: Vitocal 250-A AWO-M-E-AC(-AF) 251.A04 | AE168: Wärmepumpe Vaillant | AF168: Wärmepumpe DAIKIN | AG168: Wärmepumpe Samsung | AH168: Wärmepumpe LG | AJ168: Installation SPD
B169: 4 cm MiWo WLG 035 | D169: 4 cm MiWo WLG 035 | E169: 100 | G169: 8 cm MiWo WLG 035 | H169: 225 | J169: 12 | K169: =ROUND(PVGröße[[#This Row],[PV Module]]*Allgemein!$I$121/1000,2) -> 5.28 | L169: =_xlfn.TEXTJOIN(,,PVGröße[[#This Row],[Spalte1]]," kWp") -> 5,28 kWp | M169: 12500 | O169: 5 kWh | P169: 4000 | T169: RotoQ Schwingfenster Q4 Kunststoff 2P (Uw 1,1) | X169: Viessmann CVWC 250l | AA169: Vaillant Puffer | AC169: Vaillant | AD169: Vitocal 250-A AWO-M-E-AC(-AF) 251.A06 | AJ169: Installation SLS
B170: 5 cm MiWo WLG 035 | D170: 5 cm MiWo WLG 035 | E170: 100 | G170: 10 cm MiWo WLG 035 | H170: 230 | J170: 13 | K170: =ROUND(PVGröße[[#This Row],[PV Module]]*Allgemein!$I$121/1000,2) -> 5.72 | L170: =_xlfn.TEXTJOIN(,,PVGröße[[#This Row],[Spalte1]]," kWp") -> 5,72 kWp | M170: 12800 | O170: 10 kWh | P170: 6500 | T170: RotoQ Schwingfenster Q4 Kunststoff 3C (Uw 0,9) | X170: - | AA170: Hydr. Weiche | AC170: DAIKIN | AD170: Vitocal 250-A AWO-M-E-AC(-AF) 251.A08 | AJ170: Neuer Zählerschrank mit 1 Zählerplatz
B171: 6 cm MiWo WLG 035 | D171: 6 cm MiWo WLG 035 | E171: 100 | G171: 12 cm MiWo WLG 035 | H171: 235 | J171: 14 | K171: =ROUND(PVGröße[[#This Row],[PV Module]]*Allgemein!$I$121/1000,2) -> 6.16 | L171: =_xlfn.TEXTJOIN(,,PVGröße[[#This Row],[Spalte1]]," kWp") -> 6,16 kWp | M171: 13100 | O171: 15 kWh | P171: 9000 | T171: RotoQ Schwingfenster Q4 Kunststoff 3P (Uw 0,77) | AC171: Samsung | AD171: Vitocal 250-A AWO-M-E-AC(-AF) 251.A10 | AJ171: Neuer Zählerschrank mit 2 Zählerplätzen
B172: 7 cm MiWo WLG 035 | D172: 7 cm MiWo WLG 035 | E172: 100 | G172: 14 cm MiWo WLG 035 | H172: 240 | J172: 15 | K172: =ROUND(PVGröße[[#This Row],[PV Module]]*Allgemein!$I$121/1000,2) -> 6.6 | L172: =_xlfn.TEXTJOIN(,,PVGröße[[#This Row],[Spalte1]]," kWp") -> 6,6 kWp | M172: 13400 | O172: 20 kWh | P172: 12500 | T172: RotoQ Schwingfenster Q4 Kunststoff 3A (Uw 0,78) | AC172: LG | AD172: Vitocal 252-A AWOT-M-E-AC-(AF) 251.A04 2C | AJ172: Neuer Zählerschrank mit 3 Zählerplätzen
B173: 8 cm MiWo WLG 035 | D173: 8 cm MiWo WLG 035 | E173: 100 | G173: 16 cm MiWo WLG 035 | H173: 245 | J173: 16 | K173: =ROUND(PVGröße[[#This Row],[PV Module]]*Allgemein!$I$121/1000,2) -> 7.04 | L173: =_xlfn.TEXTJOIN(,,PVGröße[[#This Row],[Spalte1]]," kWp") -> 7,04 kWp | M173: 13700 | O173: 7 kWh | P173: 5200 | AD173: Vitocal 252-A AWOT-M-E-AC-(AF) 251.A06 2C | AJ173: Montage Poti
...

Sheet Datenaustausch
B1: Allgemeine Angaben | AF1: Präsentation Erstgespräch | BH1: Präsentation Zweitgespräch
C4: =Allgemein!B2 -> Projektnummer: | D4: =Allgemein!C2 -> 0
C5: =Allgemein!B3 -> Anrede: | D5: =Allgemein!C3 -> 0
C6: =Allgemein!B4 -> Vorname Nachname: | D6: =Allgemein!C4 -> 0 | BR6: Primärenergiebedarf | BV6: Endenergiebedarf
C7: =Allgemein!B5 -> Straße, Nr. (Objektadresse): | D7: =Allgemein!C5 -> 0 | BR7: Vor Sanierung: | BS7: =Allgemein!C38 -> 0 | BT7: kWh/m²a | BV7: Vor Sanierung: | BW7: =Allgemein!G38 -> 0 | BX7: kWh/m²a
C8: =Allgemein!B6 -> PLZ, Ort: | D8: =Allgemein!C6 -> 0 | BR8: Nach Sanierung: | BS8: =Allgemein!C122 -> 0 | BT8: kWh/m²a | BV8: Nach Sanierung: | BW8: =Allgemein!C123 -> 0 | BX8: kWh/m²a
AQ9: Empfehlungsvariante | BJ9: Energetische Maßnahmen | BK9: Kosten
C10: Angaben | AC10: iSFP | AG10: Variante 1 | AL10: Variante 2 | BI10: Dach: | BJ10: =_xlfn.TEXTJOIN(" ",,Allgemein!C94,Allgemein!D94,IF(Allgemein!E94="",,"+"),Allgemein!E94) -> 0 0 | BK10: =Allgemein!E108 -> 0
C11: Beheizte Wohnfläche: | D11: =Allgemein!C14 -> 0 | E11: m² | BI11: Fassade: | BJ11: =_xlfn.TEXTJOIN(" ",,Allgemein!C95,Allgemein!D95,IF(Allgemein!E95="",,"+"),Allgemein!E95) -> 0 0 | BK11: =Allgemein!E109 -> 0
C12: Gebäudenutzfläche | D12: =Allgemein!C40 -> 0 | E12: m² | V12: Ausgangszustand - Sowieso-Kosten | BI12: Fenster: | BJ12: =_xlfn.TEXTJOIN(" ",,Allgemein!C96,Allgemein!D96,IF(Allgemein!E96="",,"+"),Allgemein!E96) -> 0 | BK12: =Allgemein!E110 -> 0 | BR12: Wirtschaftlichkeit
C13: Baujahr: | D13: =Allgemein!E14 -> 0 | AC13: Einsparung durch energetische Sanierung | AG13: Einsparung durch energetische Sanierung | AL13: Einsparung durch energetische Sanierung | AQ13: Einsparung durch energetische Sanierung | BI13: Boden / Keller: | BJ13: =_xlfn.TEXTJOIN(" ",,Allgemein!C97,Allgemein!D97,IF(Allgemein!E97="",,"+"),Allgemein!E97," / ",Allgemein!C98,Allgemein!D98,IF(Allgemein!E98="",,"+"),Allgemein!E98) -> 0 0 / 0 0 | BK13: =Allgemein!E112+Allgemein!E111 -> 0 | BR13: Einnahmen | BV13: Ausgaben
C14: Endenergiebedarf: | D14: =Allgemein!G38 -> 0 | E14: kWh/m²a | AC14: Einsparung der Strom- und Heizkosten über 30 Jahre: | AD14: =Datenbank!AN104 -> #DIV/0! | AG14: Einsparung der Strom- und Heizkosten über 30 Jahre: | AH14: =Datenbank!AN214 -> #DIV/0! | AL14: Einsparung der Strom- und Heizkosten über 30 Jahre: | AM14: =Datenbank!AN331 -> #DIV/0! | AQ14: Einsparung der Strom- und Heizkosten über 30 Jahre: | AR14: =Datenbank!AN446 -> #DIV/0! | BI14: Heizung: | BJ14: =_xlfn.TEXTJOIN(" ",,Allgemein!C100,IF(Allgemein!D100="",,"+"),Allgemein!D100,IF(Allgemein!E100="",,"+"),Allgemein!E100) -> 0 + 0 | BK14: =Allgemein!E114 -> 0 | BR14: Einsparung: | BS14: WENN(Allgemein!G94="";"";"/ ") | BV14: Kosten: | BW14: =Allgemein!L122 -> 0
C15: Primärenergiebedarf: | D15: =Allgemein!C38 -> 0 | E15: kWh/m²a | W15: Maßnahmen | X15: Sowieso-Kosten | Y15: Begründung | AD15: =SUM(AD14) -> #DIV/0! | AH15: =SUM(AH14) -> #DIV/0! | AM15: =SUM(AM14) -> #DIV/0! | AR15: =SUM(AR14) -> #DIV/0! | BI15: PV / Elektro: | BJ15: =_xlfn.TEXTJOIN(" ",TRUE,Allgemein!C101,"PV-Anlage","mit",Allgemein!D101,"Speichersystem",IF(Allgemein!E101="",,"+"),Allgemein!E101) -> 0 PV-Anlage mit 0 Speichersystem | BK15: =Allgemein!E115 -> 0 | BR15: geschätzte Wertsteigerung: | BS15: =Allgemein!L123 -> 0 | BV15: geschätzte Sowieso-Kosten: | BW15: =X74 -> 0
W16: Dach: | X16: =Allgemein!I26 -> 0 | Y16: =Allgemein!J26 -> - | BI16: Sonstiges: | BJ16: =_xlfn.TEXTJOIN(" ",,IF(Allgemein!C102="Dezentrale Lüftungsanlage",_xlfn.TEXTJOIN(" ",TRUE,Allgemein!C102,"("&Allgemein!D102,")"),Allgemein!C102),IF(Allgemein!E102="",,"+"),Allgemein!E102) -> 0 | BK16: =Allgemein!E116 -> 0 | BR16: Förderung: | BS16: =Allgemein!P123 -> 0 | BV16: Kreditkosten: | BW16: =Allgemein!N122 -> 0
C17: Heiz- und Stromenergie | G17: Heiz- und Stromkosten | W17: Fassade: | X17: =Allgemein!I27 -> 0 | Y17: =Allgemein!J27 -> - | AC17: Kosten der energetischen Sanierung | AG17: Kosten der energetischen Sanierung | AL17: Kosten der energetischen Sanierung | AQ17: Kosten der energetischen Sanierung | BI17: BRALE Energy: | BJ17: Begleitung durch Energieberater, Begleitung und Koordination durch Bauleiter, Schnittstellenversprechen, Förderservice, Festpreisgarantie, Bauzeitgarantie, Gewährleistung aus einer Hand | BK17: =Allgemein!E117 -> 0 | BS17: =SUM(BS14:BS16) -> 0 | BW17: =SUM(BW14,BW16) -> 0
C18: Haupt-Energieträger: | D18: =Allgemein!L16 -> 0 | G18: Stromkosten pro kWh: | H18: =Allgemein!O14 -> 0 | I18: € | W18: Fenster: | X18: =Allgemein!I28 -> 0 | Y18: =Allgemein!J28 -> - | AC18: Geschätzte energetische Sanierungskosten: | AD18: =Allgemein!G53 -> 0 | AG18: Geschätzte energetische Sanierungskosten: | AH18: =Allgemein!G69 -> 0 | AL18: Geschätzte energetische Sanierungskosten: | AM18: =Allgemein!G85 -> 0 | AQ18: Geschätzte energetische Sanierungskosten: | AR18: =Allgemein!E118 -> 0 | BI18: Gesamt: | BK18: =Allgemein!E118 -> 0
C19: angegebener Heizverbrauch: | D19: =Allgemein!L17 -> 0 | E19: =_xlfn.TEXTJOIN(,,Allgemein!O16,"/a") -> /a | G19: Stromkosten: | H19: =Allgemein!O40 -> 0 | I19: €/a | W19: Keller: | X19: =Allgemein!I30 -> 0 | Y19: =Allgemein!J30 -> - | AC19: Abzgl. geschätzte Förderung: | AD19: =-Allgemein!O54 -> 0 | AG19: Abzgl. geschätzte Förderung: | AH19: =-Allgemein!O70 -> 0 | AL19: Abzgl. geschätzte Förderung: | AM19: =-Allgemein!O86 -> 0 | AQ19: Abzgl. geschätzte Förderung: | AR19: =-Allgemein!N118 -> 0
C20: angenommener Heizverbrauch: | D20: =Allgemein!K38 -> #DIV/0! | E20: kWh/a | G20: Heizpreis pro kWh: | H20: =Allgemein!K39 -> #DIV/0! | I20: € | W20: Heizung: | X20: =Allgemein!I31 -> 0 | Y20: =Allgemein!J31 -> - | AD20: =SUM(AD18:AD19) -> 0 | AH20: =SUM(AH18:AH19) -> 0 | AM20: =SUM(AM18:AM19) -> 0 | AR20: =SUM(AR18:AR19) -> 0
C21: Endenergiebedarf nach Heizverbrauch: | D21: =ROUNDUP(Allgemein!G40,0) -> #DIV/0! | E21: kWh/m²a | G21: Heizkosten: | H21: =Allgemein!K40 -> #DIV/0! | I21: €/a | W21: Gesamt: | X21: =SUM(X16:X20) -> 0
C22: Stromverbrauch: | D22: =Allgemein!L14 -> 0 | E22: kWh/a | G22: Betriebskosten: | H22: =Allgemein!K40+Allgemein!O40 -> #DIV/0! | I22: €/a | AC22: Tatsächliche Kosten der energetischen Sanierung | AG22: Tatsächliche Kosten der energetischen Sanierung | AL22: Tatsächliche Kosten der energetischen Sanierung | AQ22: Tatsächliche Mehrkosten der energetischen Sanierung
AC23: Kosten der energetischen Sanierung: | AD23: =AD20 -> 0 | AG23: Kosten der energetischen Sanierung: | AH23: =AH20 -> 0 | AL23: Kosten der energetischen Sanierung: | AM23: =AM20 -> 0 | AQ23: Kosten der energetischen Sanierung: | AR23: =AR20 -> 0 | BR23: Zusammenfassend: | BS23: =BJ10 -> 0 0
I24: CO2 Auto km (120 g pro km) | J24: Um die Welt fahren | K24: Flug Berlin Nach Mallorca | AC24: Abzgl. der Sowieso-Kosten | AD24: =-X34 -> 0 | AG24: Abzgl. der Sowieso-Kosten | AH24: =-X46 -> 0 | AL24: Abzgl. der Sowieso-Kosten | AM24: =-X60 -> 0 | AQ24: Abzgl. der Sowieso-Kosten | AR24: =-Allgemein!P122 -> 0 | BR24: Zusammenfassend: | BS24: =BJ11 -> 0 0
C25: CO2-Verbrauch in 30 Jahre (Vor -Sanierung): | E25: =_xlfn.TEXTJOIN(,,H25," t") -> 0 t | H25: =ROUNDUP(Allgemein!L17*30*Allgemein!L19*Allgemein!O19/(1000*1000),0) -> 0 | I25: =H25*1000/0.12 -> 0 | J25: =_xlfn.TEXTJOIN("",,ROUNDUP(I25/40075,0)," x") -> 0 x | K25: =_xlfn.TEXTJOIN("",,ROUNDUP(H25/0.364,0), " x") -> 0 x | V25: iSFP - Sowieso-Kosten | AD25: =SUM(AD23:AD24) -> 0 | AH25: =SUM(AH23:AH24) -> 0 | AM25: =SUM(AM23:AM24) -> 0 | AR25: =SUM(AR23:AR24) -> 0 | BR25: Zusammenfassend: | BS25: =BJ12 -> 0
C26: CO2-Einsparung in 30 Jahre (Nach -Sanierung): | E26: =_xlfn.TEXTJOIN(,,H26," t") -> 0 t | H26: =ROUNDUP(IF(Allgemein!C132="JA",H25,H25-Allgemein!O19*Allgemein!C124*Allgemein!C14*30/(1000*1000)),0) -> 0 | I26: =H26*1000/0.12 -> 0 | J26: =_xlfn.TEXTJOIN(" ",,ROUNDUP(I26/40075,0),"x") -> 0 x | K26: =_xlfn.TEXTJOIN(" ",,ROUNDUP(H26/0.364,0),"x") -> 0 x | BR26: Zusammenfassend: | BS26: =_xlfn.TEXTJOIN(" ",,Allgemein!C97,Allgemein!D97,IF(Allgemein!E97="",,"+"),Allgemein!E97) -> 0 0
AC27: Einnahmen | AD27: Ausgaben | AG27: Einnahmen | AH27: Ausgaben | AL27: Einnahmen | AM27: Ausgaben | AQ27: Einsparung | AR27: Kosten | BR27: Zusammenfassend: | BS27: =_xlfn.TEXTJOIN(" ",,Allgemein!C98,Allgemein!D98,IF(Allgemein!E98="",,"+"),Allgemein!E98) -> 0 0
C28: Endenergiebedarf vor Sanierung | W28: Maßnahmen | X28: Sowieso-Kosten | Y28: Begründung | AB28: Kosten | AD28: =AD25 -> 0 | AF28: Kosten | AH28: =AH25 -> 0 | AK28: Kosten | AM28: =AM25 -> 0 | AP28: Kosten | AR28: =AR25 -> 0 | BR28: Zusammenfassend: | BS28: =Allgemein!C99 -> nicht festgelegt
D29: Vor Sanierung | E29: =IF(Allgemein!G38>250,250,Allgemein!G38) -> 0 | F29: 0 | W29: Dach: | X29: =IF(OR(Allgemein!C44="-",Allgemein!C44=""),0,Allgemein!$I$26) -> 0 | Y29: =IF(OR(Allgemein!C44="-",Allgemein!C44=""),"",Allgemein!$J$26) | AB29: Einsparung | AC29: =Datenbank!AN104 -> #DIV/0! | AF29: Einsparung | AG29: =Datenbank!AN214 -> #DIV/0! | AK29: Einsparung | AL29: =Datenbank!AN331 -> #DIV/0! | AP29: Einsparung | AQ29: =Datenbank!AN446 -> #DIV/0! | BR29: Zusammenfassend: | BS29: =BJ14 -> 0 + 0
W30: Fassade: | X30: =IF(OR(Allgemein!C45="-",Allgemein!C45=""),0,Allgemein!$I$27) -> 0 | Y30: =IF(OR(Allgemein!C45="-",Allgemein!C45=""),"",Allgemein!$J$27) | BI30: Maßnahmenpakete | BJ30: Kosten | BK30: Fördersatz | BL30: Förderbar | BM30: Zuschuss | BR30: Zusammenfassend: | BS30: =BJ15 -> 0 PV-Anlage mit 0 Speichersystem
I31: Ersparniss: | J31: =Datenbank!AJ460 -> #DIV/0! | W31: Fenster: | X31: =IF(OR(Allgemein!C46="-",Allgemein!C46=""),0,Allgemein!$I$28) -> 0 | Y31: =IF(OR(Allgemein!C46="-",Allgemein!C46=""),"",Allgemein!$J$28) | AC31: Einsparung: | AD31: =AD15 -> #DIV/0! | AG31: Einsparung: | AH31: =AH15 -> #DIV/0! | AL31: Einsparung: | AM31: =AM15 -> #DIV/0! | AQ31: Einsparung: | AR31: =AR15 -> #DIV/0! | BI31: Gebäudehülle (BAFA): | BJ31: =Allgemein!E113 -> 0 | BK31: =Allgemein!G113 -> 0 | BL31: =Allgemein!H113 -> 0 | BM31: =Allgemein!I113 -> 0 | BR31: Zusammenfassend: | BS31: =BJ16 -> 0
J32: =Allgemein!C126 -> 0 | W32: Keller: | X32: =IF(OR(Allgemein!C48="-",Allgemein!C48=""),0,Allgemein!$I$30) -> 0 | Y32: =IF(OR(Allgemein!C48="-",Allgemein!C48=""),"",Allgemein!$J$30) | AC32: Kosten: | AD32: =-AD25 -> 0 | AG32: Kosten: | AH32: =-AH25 -> 0 | AL32: Kosten: | AM32: =-AM25 -> 0 | AQ32: Kosten: | AR32: =-AR25 -> 0 | BI32: Dach: | BK32: {=Allgemein!G108:G111} -> 0 | BL32: {=Allgemein!H108:H111} -> 0 | BM32: {=Allgemein!I108:I111} -> 0
I33: Strom und Heizkosten in den nächsten 30 Jahren ohne Sanierung | J33: =Datenbank!AI447 -> #DIV/0! | W33: Heizung: | X33: =IF(OR(Allgemein!C50="-",Allgemein!C50=""),0,Allgemein!$I$31) -> 0 | Y33: =IF(OR(Allgemein!C50="-",Allgemein!C50=""),"",Allgemein!$J$31) | AC33: + | AD33: =AD15-AD25 -> #DIV/0! | AG33: + | AH33: =AH15-AH25 -> #DIV/0! | AL33: + | AM33: =AM15-AM25 -> #DIV/0! | AQ33: + | AR33: =AR15-r_tatKostenEinzelnEMPF -> #DIV/0! | BI33: Fassade: | BK33: 0 | BL33: 0 | BM33: 0
I34: Strom und Heizkosten in den nächsten 30 Jahren mit Sanierung | J34: =Datenbank!AI460 -> #DIV/0! | W34: Gesamt: | X34: =SUM(X29:X33) -> 0 | BI34: Fenster: | BK34: 0 | BL34: 0 | BM34: 0 | BR34: Wirtschaftlichkeit Empfehlungsvariante | BW34: Wirtschaftlichkeit Empfehlungsvariante
BI35: Boden (unterer Gebäudeabschluss): | BK35: 0 | BL35: 0 | BM35: 0 | BS35: Instandhaltung (Sowieso-Kosten) | BT35: Energetische Sanierung | BW35: Jahr | BX35: Mehrkosten im Monat
BI36: Keller: | BK36: =Allgemein!G112 -> 0 | BL36: =Allgemein!H112 -> 0 | BM36: =Allgemein!I112 -> 0 | BR36: Kosten: | BS36: =Allgemein!P122 -> 0 | BT36: =AR20 -> 0 | BW36: 1. Jahr
V37: Variante 1 - Sowieso-Kosten | BI37: Heizung (KfW): | BJ37: =Allgemein!E114 -> 0 | BK37: =Allgemein!G114 -> 0 | BL37: =Allgemein!H114 -> 0 | BM37: =Allgemein!I114 -> 0 | BR37: Heizkosten pro Monat (1. Jahr): | BS37: =Datenbank!D448 -> #DIV/0! | BT37: =Datenbank!D458 -> #DIV/0! | BW37: 5. Jahr
BI38: Direktzuschuss: | BL38: =Allgemein!I118 -> 0 | BR38: Kreditkosten pro Monat: | BS38: =BS36*0.058/12 -> 0 | BT38: =BT36*0.058/12 -> 0 | BW38: 10. Jahr
BR39: Gesamtkosten pro Monat (1. Jahr): | BS39: =SUM(BS37:BS38) -> #DIV/0! | BT39: =SUM(BT37:BT38) -> #DIV/0! | BW39: 20. Jahr
W40: Maßnahmen | X40: Sowieso-Kosten | Y40: Begründung | BW40: 30. Jahr
W41: Dach: | X41: =IF(OR(Allgemein!C60="-",Allgemein!C60=""),0,Allgemein!$I$26) -> 0 | Y41: =IF(OR(Allgemein!C60="-",Allgemein!C60=""),"",Allgemein!$J$26) | BI41: Geförderte Maßnahmen | BJ41: Förderbar | BK41: Kredit | BL41: Zinssatz | BM41: Laufzeit
F42: Kosten pro Monat vor Sanierung | W42: Fassade: | X42: =IF(OR(Allgemein!C61="-",Allgemein!C61=""),0,Allgemein!$I$27) -> 0 | Y42: =IF(OR(Allgemein!C61="-",Allgemein!C61=""),"",Allgemein!$J$27) | BI42: =Allgemein!K108 -> 0 | BJ42: =Allgemein!H115 -> 0 | BK42: =Allgemein!K110 -> 0 | BL42: =Allgemein!K112 -> 0 | BM42: =Allgemein!K113 -> 0
W43: Fenster: | X43: =IF(OR(Allgemein!C62="-",Allgemein!C62=""),0,Allgemein!$I$28) -> 0 | Y43: =IF(OR(Allgemein!C62="-",Allgemein!C62=""),"",Allgemein!$J$28) | BI43: Tilgungszuschuss: | BK43: =Allgemein!K111 -> 0 | BL43: =Allgemein!K118 -> 0
W44: Keller: | X44: =IF(OR(Allgemein!C64="-",Allgemein!C64=""),0,Allgemein!$I$30) -> 0 | Y44: =IF(OR(Allgemein!C64="-",Allgemein!C64=""),"",Allgemein!$J$30)
W45: Heizung: | X45: =IF(OR(Allgemein!C66="-",Allgemein!C66=""),0,Allgemein!$I$31) -> 0 | Y45: =IF(OR(Allgemein!C66="-",Allgemein!C66=""),"",Allgemein!$J$31) | BI45: Summe: | BJ45: =Allgemein!N118 -> 0
W46: Gesamt: | X46: =SUM(X41:X45) -> 0 | AQ46: + | AR46: =IF(r_VarianteEmpfehlung="Variante 1",AD33,IF(r_VarianteEmpfehlung="Variante 2",AH33,IF(r_VarianteEmpfehlung="Variante 3",AM33,0))) -> 0
AC49: iSFP | AR49: Maßnahmen
AR50: =#REF! -> #REF!
V51: Variante 2 - Sowieso-Kosten | AC51: Maßnahmen | AH51: Endenergiebedarf iSFP | AR51: =BJ10 -> 0 0
AC52: Dach: | AR52: =BI11 -> Fassade: | BV52: Kosten pro Monat vor Sanierung und nach Sanierung Umsetzungsvariante
AC53: =_xlfn.TEXTJOIN(" ",,Allgemein!C44,Allgemein!D44,IF(Allgemein!E44="",,"+"),Allgemein!E44) -> - - | AR53: =BJ13 -> 0 0 / 0 0
W54: Maßnahmen | X54: Sowieso-Kosten | Y54: Begründung | AC54: Fassade: | AG54: iSFP | AH54: =IF(Allgemein!D54>250,250,Allgemein!D54) -> 0 | AI54: 0 | AR54: =#REF! -> #REF!
W55: Dach: | X55: =IF(OR(Allgemein!C76="-",Allgemein!C76=""),0,Allgemein!$I$26) -> 0 | Y55: =IF(OR(Allgemein!C76="-",Allgemein!C76=""),"",Allgemein!$J$26) | AC55: =_xlfn.TEXTJOIN(" ",,Allgemein!C45,Allgemein!D45,IF(Allgemein!E45="",,"+"),Allgemein!E45) -> - - | AR55: =#REF! -> #REF!
W56: Fassade: | X56: =IF(OR(Allgemein!C77="-",Allgemein!C77=""),0,Allgemein!$I$27) -> 0 | Y56: =IF(OR(Allgemein!C77="-",Allgemein!C77=""),"",Allgemein!$J$27) | AC56: Fenster: | AR56: =BJ16 -> 0
W57: Fenster: | X57: =IF(OR(Allgemein!C78="-",Allgemein!C78=""),0,Allgemein!$I$28) -> 0 | Y57: =IF(OR(Allgemein!C78="-",Allgemein!C78=""),"",Allgemein!$J$28) | AC57: =_xlfn.TEXTJOIN(" ",,Allgemein!C46,Allgemein!D46,IF(Allgemein!E46="",,"+"),Allgemein!E46) -> - | AG57: {=_xlfn.IFS(AH54<=30,"A+",AND(30<=AH54,AH54<50),"A",AND(50<=AH54,AH54<75),"B",AND(75<=AH54,AH54<100),"C",AND(100<=AH54,AH54<130),"D",AND(130<=AH54,AH54<160),"E",AND(160<=AH54,AH54<200),"F",AND(200<=AH54,AH54<250),"G",AH54>=250,"H")} -> A+ | AH57: =Datenbank!AN104 -> #DIV/0! | AJ57: =Allgemein!C56 -> Nicht ausgefüllt | AR57: =#REF! -> #REF!
W58: Keller: | X58: =IF(OR(Allgemein!C80="-",Allgemein!C80=""),0,Allgemein!$I$30) -> 0 | Y58: =IF(OR(Allgemein!C80="-",Allgemein!C80=""),"",Allgemein!$J$30) | AC58: Boden / Keller: | AR58: =BI19 -> 0
W59: Heizung: | X59: =IF(OR(Allgemein!C82="-",Allgemein!C82=""),0,Allgemein!$I$31) -> 0 | Y59: =IF(OR(Allgemein!C82="-",Allgemein!C82=""),"",Allgemein!$J$31) | AC59: =_xlfn.TEXTJOIN(" ",,Allgemein!C47,Allgemein!D47,IF(Allgemein!E47="",,"+"),Allgemein!E47," / ",Allgemein!C48,Allgemein!D48,IF(Allgemein!E48="",,"+"),Allgemein!E48) -> - - / - - | AR59: =BI20 -> 0
W60: Gesamt: | X60: =SUM(X55:X59) -> 0 | AC60: Heizung: | AR60: =BI21 -> 0
AC61: =_xlfn.TEXTJOIN(" ",,Allgemein!C50,"+",Allgemein!D50,IF(Allgemein!E50="",,"+"),Allgemein!E50) -> + | AR61: =BI23 -> 0
AC62: Photovoltaikanlage: | AR62: Sonstiges:
AC63: =_xlfn.TEXTJOIN(" ",TRUE,Allgemein!C51,"PV-Anlage","mit",Allgemein!D51,"Speichersystem",IF(Allgemein!E51="",,"+"),Allgemein!E51) -> - PV-Anlage mit - Speichersystem | AR63: =BI25 -> 0
AC64: Sonstiges:
V65: Empfehlungsvariante - Sowieso-Kosten | AC65: =_xlfn.TEXTJOIN(" ",,IF(Allgemein!C52="Dezentrale Lüftungsanlage",_xlfn.TEXTJOIN(" ",TRUE,Allgemein!C52,"("&Allgemein!D52,")"),Allgemein!C52),IF(Allgemein!E52="",,"+"),Allgemein!E52) -> -
W68: Maßnahmen | X68: Sowieso-Kosten | Y68: Begründung
W69: Dach: | X69: =IF(Allgemein!$C$91="iSFP",X29,IF(Allgemein!$C$91="Variante 1",X41,IF(Allgemein!$C$91="Variante 2",X55,0))) -> 0 | Y69: =IF(Allgemein!$C$91="iSFP",Y29,IF(Allgemein!$C$91="Variante 1",Y41,IF(Allgemein!$C$91="Variante 2",Y55,0))) -> 0
W70: Fassade: | X70: =IF(Allgemein!$C$91="iSFP",X30,IF(Allgemein!$C$91="Variante 1",X42,IF(Allgemein!$C$91="Variante 2",X56,0))) -> 0 | Y70: =IF(Allgemein!$C$91="iSFP",Y30,IF(Allgemein!$C$91="Variante 1",Y42,IF(Allgemein!$C$91="Variante 2",Y56,0))) -> 0 | AR70: Endenergiebedarf ausgewählte Variante
W71: Fenster: | X71: =IF(Allgemein!$C$91="iSFP",X31,IF(Allgemein!$C$91="Variante 1",X43,IF(Allgemein!$C$91="Variante 2",X57,0))) -> 0 | Y71: =IF(Allgemein!$C$91="iSFP",Y31,IF(Allgemein!$C$91="Variante 1",Y43,IF(Allgemein!$C$91="Variante 2",Y57,0))) -> 0 | AC71: Variante 1
W72: Keller: | X72: =IF(Allgemein!$C$91="iSFP",X32,IF(Allgemein!$C$91="Variante 1",X44,IF(Allgemein!$C$91="Variante 2",X58,0))) -> 0 | Y72: =IF(Allgemein!$C$91="iSFP",Y32,IF(Allgemein!$C$91="Variante 1",Y44,IF(Allgemein!$C$91="Variante 2",Y58,0))) -> 0 | AR72: Vor Sanierung | AS72: =IF(Allgemein!G38>250,250,Allgemein!G38) -> 0 | AT72: 0
W73: Heizung: | X73: =IF(Allgemein!$C$91="iSFP",X33,IF(Allgemein!$C$91="Variante 1",X45,IF(Allgemein!$C$91="Variante 2",X59,0))) -> 0 | Y73: =IF(Allgemein!$C$91="iSFP",Y33,IF(Allgemein!$C$91="Variante 1",Y45,IF(Allgemein!$C$91="Variante 2",Y59,0))) -> 0 | AC73: Maßnahmen | AG73: Endenergiebedarf Variante 1 | AR73: Nach Sanierung | AS73: =IF(Allgemein!C123>250,250,Allgemein!C123) -> 0 | AT73: 0
W74: Gesamt: | X74: =SUM(X69:X73) -> 0 | AC74: Dach:
AC75: =_xlfn.TEXTJOIN(" ",,Allgemein!C60,Allgemein!D60,IF(Allgemein!E60="",,"+"),Allgemein!E60) -> - -
AC76: Fassade:
AC77: =_xlfn.TEXTJOIN(" ",,Allgemein!C61,Allgemein!D61,IF(Allgemein!E61="",,"+"),Allgemein!E61) -> - - | AG77: Variante 1 | AH77: =IF(Allgemein!D70>250,250,Allgemein!D70) -> 0 | AI77: 0
AC78: Fenster: | AH78: Wärmebrückenzuschlag: | AJ78: =Allgemein!D69 -> 0.1
AC79: =_xlfn.TEXTJOIN(" ",,Allgemein!C62,Allgemein!D62,IF(Allgemein!E62="",,"+"),Allgemein!E62) -> - | AG79: {=_xlfn.IFS(AH77<=30,"A+",AND(30<=AH77,AH77<50),"A",AND(50<=AH77,AH77<75),"B",AND(75<=AH77,AH77<100),"C",AND(100<=AH77,AH77<130),"D",AND(130<=AH77,AH77<160),"E",AND(160<=AH77,AH77<200),"F",AND(200<=AH77,AH77<250),"G",AH77>=250,"H")} -> A+ | AH79: =Datenbank!AN214 -> #DIV/0! | AJ79: =Allgemein!C72 -> Nicht ausgefüllt
AC80: Boden / Keller:
AC81: =_xlfn.TEXTJOIN(" ",,Allgemein!C63,Allgemein!D63,IF(Allgemein!E63="",,"+"),Allgemein!E63," / ",Allgemein!C64,Allgemein!D64,IF(Allgemein!E64="",,"+"),Allgemein!E64) -> - - / - -
AC82: Heizung:
AC83: =_xlfn.TEXTJOIN(" ",,Allgemein!C66,"+",Allgemein!D66,IF(Allgemein!E66="",,"+"),Allgemein!E66) -> +
AC84: Photovoltaikanlage:
AC85: =_xlfn.TEXTJOIN(" ",TRUE,Allgemein!C67,"PV-Anlage","mit",Allgemein!D67,"Speichersystem",IF(Allgemein!E67="",,"+"),Allgemein!E67) -> - PV-Anlage mit - Speichersystem | AR85: Energielabel | AS85: {=_xlfn.IFS(AS73=0,"",AS73<=30,"A+",AND(30<=AS73,AS73<50),"A",AND(50<=AS73,AS73<75),"B",AND(75<=AS73,AS73<100),"C",AND(100<=AS73,AS73<130),"D",AND(130<=AS73,AS73<160),"E",AND(160<=AS73,AS73<200),"F",AND(200<=AS73,AS73<250),"G",AS73>=250,"H")}
AC86: Sonstiges:
AC87: =_xlfn.TEXTJOIN(" ",,IF(Allgemein!C68="Dezentrale Lüftungsanlage",_xlfn.TEXTJOIN(" ",TRUE,Allgemein!C68,"("&Allgemein!D68,")"),Allgemein!C68),IF(Allgemein!E68="",,"+"),Allgemein!E68) -> -
AG91: Endenergiebedarf Variante 2
AC92: Variante 2
AC94: Maßnahmen
AC95: Dach: | AG95: Variante 2 | AH95: =IF(Allgemein!D86>250,250,Allgemein!D86) -> 0 | AI95: 0
AC96: =_xlfn.TEXTJOIN(" ",,Allgemein!C76,Allgemein!D76,IF(Allgemein!E76="",,"+"),Allgemein!E76) -> - -
AC97: Fassade: | AH97: Wärmebrückenzuschlag: | AJ97: =Allgemein!D85 -> 0.1
AC98: =_xlfn.TEXTJOIN(" ",,Allgemein!C77,Allgemein!D77,IF(Allgemein!E77="",,"+"),Allgemein!E77) -> - - | AG98: {=_xlfn.IFS(AH95<=30,"A+",AND(30<=AH95,AH95<50),"A",AND(50<=AH95,AH95<75),"B",AND(75<=AH95,AH95<100),"C",AND(100<=AH95,AH95<130),"D",AND(130<=AH95,AH95<160),"E",AND(160<=AH95,AH95<200),"F",AND(200<=AH95,AH95<250),"G",AH95>=250,"H")} -> A+ | AH98: =Datenbank!AN331 -> #DIV/0! | AJ98: =Allgemein!C88 -> Nicht ausgefüllt
AC99: Fenster:
AC100: =_xlfn.TEXTJOIN(" ",,Allgemein!C78,Allgemein!D78,IF(Allgemein!E78="",,"+"),Allgemein!E78) -> -
AC101: Boden / Keller:
AC102: =_xlfn.TEXTJOIN(" ",,Allgemein!C79,Allgemein!D79,IF(Allgemein!E79="",,"+"),Allgemein!E79," / ",Allgemein!C80,Allgemein!D80,IF(Allgemein!E80="",,"+"),Allgemein!E80) -> - - / - -
AC103: Heizung:
AC104: =_xlfn.TEXTJOIN(" ",,Allgemein!C82,"+",Allgemein!D82,IF(Allgemein!E82="",,"+"),Allgemein!E82) -> +
AC105: Photovoltaikanlage:
AC106: =_xlfn.TEXTJOIN(" ",TRUE,Allgemein!C83,"PV-Anlage","mit",Allgemein!D83,"Speichersystem",IF(Allgemein!E83="",,"+"),Allgemein!E83) -> - PV-Anlage mit - Speichersystem
AC107: Sonstiges:
AC108: =_xlfn.TEXTJOIN(" ",,IF(Allgemein!C84="Dezentrale Lüftungsanlage",_xlfn.TEXTJOIN(" ",TRUE,Allgemein!C84,"("&Allgemein!D84,")"),Allgemein!C84),IF(Allgemein!E84="",,"+"),Allgemein!E84) -> -

Sheet Fassade
B2: Projektnummer: | C2: =Allgemein!C2 -> 0 | F2: Maßnahmenpaket Fassade | U2: #VALUE!
B3: Anrede: | C3: =Allgemein!C3 -> 0 | L3: Kurzbeschreibung Maßnahmen
B4: Vorname Nachname: | C4: =Allgemein!C4 -> 0 | F4: Umsetzungsvariante: | L4: =Allgemein!C95 -> 0
B5: Straße, Nr. (Objektadresse): | C5: =Allgemein!C5 -> 0 | F5: Zusatzleistung: | L5: =Allgemein!G95 -> 0
B6: PLZ, Ort: | C6: =Allgemein!C6 -> 0 | F6: Variante 1: | L6: =Allgemein!C45 -> -
B7: Email: | C7: =Allgemein!C7 -> 0 | F7: Variante 2: | L7: =Allgemein!C61 -> -
B8: Telefon: | C8: =Allgemein!C8 -> 0 | F8: Variante 3: | L8: =Allgemein!C77 -> -
B9: Wandtypen | U9: Sicherheitsfaktor allgemein: | V9: 1.05
B10: Bestand | F10: Wände | S10: Wunsch/Anmerkung | U10: Umsetzung | V10: iSFP | W10: Variante 1 | X10: Variante 2
B11: Monolithisches Mauerwerk | D11: #VALUE! | F11: Benennung | G11: Beschreibung | H11: Breite [m] | I11: Höhe [m] | J11: Zusatzfläche (Bsp. Giebel) | K11: Anmerkung Zusatzfläche | L11: Brutto- fläche [m²] | M11: Anzahl Öffnungen | N11: Öffnungs- fläche [m²] | O11: Öffnungs- fläche über 2,5 m² [m²] | P11: Umfang Öffnungen [m] | Q11: Kalkulatorische Fläche [m²] | R11: Nettofläche zu dämmen [m²] | U11: WDVS: | V11: {=_xlfn.XLOOKUP(U11&Allgemein!$C$45,Fassadenpositionen[[#Headers],[WDVS:]]&Fassadenpositionen[Position Fassade],Fassadenpositionen[WDVS:],"",0,1)} -> Nein | W11: {=_xlfn.XLOOKUP(U11&Allgemein!$C$61,Fassadenpositionen[[#Headers],[WDVS:]]&Fassadenpositionen[Position Fassade],Fassadenpositionen[WDVS:],"",0,1)} -> Nein | X11: {=_xlfn.XLOOKUP(U11&Allgemein!$C$77,Fassadenpositionen[[#Headers],[WDVS:]]&Fassadenpositionen[Position Fassade],Fassadenpositionen[WDVS:],"",0,1)} -> Nein
B12: Außenwandtyp_xx | L12: =H12*I12+J12 -> 0 | M12: =SUMIF(Fenster!$D$10:$D$2160,Fassade!F12,Fenster!$J$10:$J$2160) -> 0 | N12: =SUMIF(Fenster!$D$10:$D$2160,Fassade!F12,Fenster!$M$10:$M$2160) -> 0 | O12: =SUMIFS(Fenster!$M$10:$M$2160,Fenster!$D$10:$D$2160,Fassade!F12,Fenster!$L$10:$L$2160,">2,5") -> 0 | P12: =SUMIF(Fenster!$D$10:$D$2160,Fassade!F12,Fenster!$K$10:$K$2160) -> 0 | Q12: =L12-O12 -> 0 | R12: =L12-N12 -> 0 | U12: Zusatz oder Abzugsfläche [m²]: | V12: 0 | W12: 0 | X12: 0
B13: Material Außenwand (1): | L13: =H13*I13+J13 -> 0 | M13: =SUMIF(Fenster!$D$10:$D$2160,Fassade!F13,Fenster!$J$10:$J$2160) -> 0 | N13: =SUMIF(Fenster!$D$10:$D$2160,Fassade!F13,Fenster!$M$10:$M$2160) -> 0 | O13: =SUMIFS(Fenster!$M$10:$M$2160,Fenster!$D$10:$D$2160,Fassade!F13,Fenster!$L$10:$L$2160,">2,5") -> 0 | P13: =SUMIF(Fenster!$D$10:$D$2160,Fassade!F13,Fenster!$K$10:$K$2160) -> 0 | Q13: =L13-O13 -> 0 | R13: =L13-N13 -> 0 | U13: Kalkulatorische Fläche: | V13: =IF(V11="Ja",(Q22+V12)*$V$9,0) -> 0 | W13: =IF(W11="Ja",(Q22+W12)*$V$9,0) -> 0 | X13: =IF(X11="Ja",(Q22+X12)*$V$9,0) -> 0
B14: Stärke Außenwand (1) [cm]: | L14: =H14*I14+J14 -> 0 | M14: =SUMIF(Fenster!$D$10:$D$2160,Fassade!F14,Fenster!$J$10:$J$2160) -> 0 | N14: =SUMIF(Fenster!$D$10:$D$2160,Fassade!F14,Fenster!$M$10:$M$2160) -> 0 | O14: =SUMIFS(Fenster!$M$10:$M$2160,Fenster!$D$10:$D$2160,Fassade!F14,Fenster!$L$10:$L$2160,">2,5") -> 0 | P14: =SUMIF(Fenster!$D$10:$D$2160,Fassade!F14,Fenster!$K$10:$K$2160) -> 0 | Q14: =L14-O14 -> 0 | R14: =L14-N14 -> 0 | U14: Nettofläche zu dämmen: | V14: =IF(V11="Ja",(R22+V12)*$V$9,0) -> 0 | W14: =IF(W11="Ja",(R22+W12)*$V$9,0) -> 0 | X14: =IF(X11="Ja",(R22+X12)*$V$9,0) -> 0
B15: U-Wert [W/(m²K)]: | L15: =H15*I15+J15 -> 0 | M15: =SUMIF(Fenster!$D$10:$D$2160,Fassade!F15,Fenster!$J$10:$J$2160) -> 0 | N15: =SUMIF(Fenster!$D$10:$D$2160,Fassade!F15,Fenster!$M$10:$M$2160) -> 0 | O15: =SUMIFS(Fenster!$M$10:$M$2160,Fenster!$D$10:$D$2160,Fassade!F15,Fenster!$L$10:$L$2160,">2,5") -> 0 | P15: =SUMIF(Fenster!$D$10:$D$2160,Fassade!F15,Fenster!$K$10:$K$2160) -> 0 | Q15: =L15-O15 -> 0 | R15: =L15-N15 -> 0 | U15: Material, Stärke: | V15: =Allgemein!$D$45 -> - | W15: =Allgemein!$D$61 -> - | X15: =Allgemein!$D$77 -> -
B16: Beschreibung Wandtyp: | L16: =H16*I16+J16 -> 0 | M16: =SUMIF(Fenster!$D$10:$D$2160,Fassade!F16,Fenster!$J$10:$J$2160) -> 0 | N16: =SUMIF(Fenster!$D$10:$D$2160,Fassade!F16,Fenster!$M$10:$M$2160) -> 0 | O16: =SUMIFS(Fenster!$M$10:$M$2160,Fenster!$D$10:$D$2160,Fassade!F16,Fenster!$L$10:$L$2160,">2,5") -> 0 | P16: =SUMIF(Fenster!$D$10:$D$2160,Fassade!F16,Fenster!$K$10:$K$2160) -> 0 | Q16: =L16-O16 -> 0 | R16: =L16-N16 -> 0 | U16: Bemerkung:
B17: Kellerwand?: | L17: =H17*I17+J17 -> 0 | M17: =SUMIF(Fenster!$D$10:$D$2160,Fassade!F17,Fenster!$J$10:$J$2160) -> 0 | N17: =SUMIF(Fenster!$D$10:$D$2160,Fassade!F17,Fenster!$M$10:$M$2160) -> 0 | O17: =SUMIFS(Fenster!$M$10:$M$2160,Fenster!$D$10:$D$2160,Fassade!F17,Fenster!$L$10:$L$2160,">2,5") -> 0 | P17: =SUMIF(Fenster!$D$10:$D$2160,Fassade!F17,Fenster!$K$10:$K$2160) -> 0 | Q17: =L17-O17 -> 0 | R17: =L17-N17 -> 0
L18: =H18*I18+J18 -> 0 | M18: =SUMIF(Fenster!$D$10:$D$2160,Fassade!F18,Fenster!$J$10:$J$2160) -> 0 | N18: =SUMIF(Fenster!$D$10:$D$2160,Fassade!F18,Fenster!$M$10:$M$2160) -> 0 | O18: =SUMIFS(Fenster!$M$10:$M$2160,Fenster!$D$10:$D$2160,Fassade!F18,Fenster!$L$10:$L$2160,">2,5") -> 0 | P18: =SUMIF(Fenster!$D$10:$D$2160,Fassade!F18,Fenster!$K$10:$K$2160) -> 0 | Q18: =L18-O18 -> 0 | R18: =L18-N18 -> 0
L19: =H19*I19+J19 -> 0 | M19: =SUMIF(Fenster!$D$10:$D$2160,Fassade!F19,Fenster!$J$10:$J$2160) -> 0 | N19: =SUMIF(Fenster!$D$10:$D$2160,Fassade!F19,Fenster!$M$10:$M$2160) -> 0 | O19: =SUMIFS(Fenster!$M$10:$M$2160,Fenster!$D$10:$D$2160,Fassade!F19,Fenster!$L$10:$L$2160,">2,5") -> 0 | P19: =SUMIF(Fenster!$D$10:$D$2160,Fassade!F19,Fenster!$K$10:$K$2160) -> 0 | Q19: =L19-O19 -> 0 | R19: =L19-N19 -> 0
L20: =H20*I20+J20 -> 0 | M20: =SUMIF(Fenster!$D$10:$D$2160,Fassade!F20,Fenster!$J$10:$J$2160) -> 0 | N20: =SUMIF(Fenster!$D$10:$D$2160,Fassade!F20,Fenster!$M$10:$M$2160) -> 0 | O20: =SUMIFS(Fenster!$M$10:$M$2160,Fenster!$D$10:$D$2160,Fassade!F20,Fenster!$L$10:$L$2160,">2,5") -> 0 | P20: =SUMIF(Fenster!$D$10:$D$2160,Fassade!F20,Fenster!$K$10:$K$2160) -> 0 | Q20: =L20-O20 -> 0 | R20: =L20-N20 -> 0
L21: =H21*I21+J21 -> 0 | M21: =SUMIF(Fenster!$D$10:$D$2160,Fassade!F21,Fenster!$J$10:$J$2160) -> 0 | N21: =SUMIF(Fenster!$D$10:$D$2160,Fassade!F21,Fenster!$M$10:$M$2160) -> 0 | O21: =SUMIFS(Fenster!$M$10:$M$2160,Fenster!$D$10:$D$2160,Fassade!F21,Fenster!$L$10:$L$2160,">2,5") -> 0 | P21: =SUMIF(Fenster!$D$10:$D$2160,Fassade!F21,Fenster!$K$10:$K$2160) -> 0 | Q21: =L21-O21 -> 0 | R21: =L21-N21 -> 0
F22: Summe: | L22: =SUM(L12:L21) -> 0 | M22: =SUM(M12:M21) -> 0 | N22: =SUM(N12:N21) -> 0 | O22: =SUM(O12:O21) -> 0 | P22: =SUM(P12:P21) -> 0 | Q22: =SUM(Q12:Q21) -> 0 | R22: =SUM(R12:R21) -> 0
B24: Monolithisches Mauerwerk | D24: #VALUE! | F24: Benennung | G24: Beschreibung | H24: Breite [m] | I24: Höhe [m] | J24: Zusatzfläche (Bsp. Giebel) | K24: Anmerkung Zusatzfläche | L24: Brutto- fläche [m²] | M24: Anzahl Öffnungen | N24: Öffnungs- fläche [m²] | O24: Öffnungs- fläche über 2,5 m² [m²] | P24: Umfang Öffnungen [m] | Q24: Kalkulatorische Fläche [m²] | R24: Nettofläche zu dämmen [m²] | U24: WDVS: | V24: {=_xlfn.XLOOKUP(U24&Allgemein!$C$45,Fassadenpositionen[[#Headers],[WDVS:]]&Fassadenpositionen[Position Fassade],Fassadenpositionen[WDVS:],"",0,1)} -> Nein | W24: {=_xlfn.XLOOKUP(U24&Allgemein!$C$61,Fassadenpositionen[[#Headers],[WDVS:]]&Fassadenpositionen[Position Fassade],Fassadenpositionen[WDVS:],"",0,1)} -> Nein | X24: {=_xlfn.XLOOKUP(U24&Allgemein!$C$77,Fassadenpositionen[[#Headers],[WDVS:]]&Fassadenpositionen[Position Fassade],Fassadenpositionen[WDVS:],"",0,1)} -> Nein
B25: Außenwandtyp_xx | L25: =H25*I25+J25 -> 0 | M25: =SUMIF(Fenster!$D$10:$D$2160,Fassade!F25,Fenster!$J$10:$J$2160) -> 0 | N25: =SUMIF(Fenster!$D$10:$D$2160,Fassade!F25,Fenster!$M$10:$M$2160) -> 0 | O25: =SUMIFS(Fenster!$M$10:$M$2160,Fenster!$D$10:$D$2160,Fassade!F25,Fenster!$L$10:$L$2160,">2,5") -> 0 | P25: =SUMIF(Fenster!$D$10:$D$2160,Fassade!F25,Fenster!$K$10:$K$2160) -> 0 | Q25: =L25-O25 -> 0 | R25: =L25-N25 -> 0 | U25: Zusatz oder Abzugsfläche [m²]: | V25: 0 | W25: 0 | X25: 0
B26: Material Außenwand (1): | L26: =H26*I26+J26 -> 0 | M26: =SUMIF(Fenster!$D$10:$D$2160,Fassade!F26,Fenster!$J$10:$J$2160) -> 0 | N26: =SUMIF(Fenster!$D$10:$D$2160,Fassade!F26,Fenster!$M$10:$M$2160) -> 0 | O26: =SUMIFS(Fenster!$M$10:$M$2160,Fenster!$D$10:$D$2160,Fassade!F26,Fenster!$L$10:$L$2160,">2,5") -> 0 | P26: =SUMIF(Fenster!$D$10:$D$2160,Fassade!F26,Fenster!$K$10:$K$2160) -> 0 | Q26: =L26-O26 -> 0 | R26: =L26-N26 -> 0 | U26: Kalkulatorische Fläche: | V26: =IF(V24="Ja",(Q35+V25)*$V$9,0) -> 0 | W26: =IF(W24="Ja",(Q35+W25)*$V$9,0) -> 0 | X26: =IF(X24="Ja",(Q35+X25)*$V$9,0) -> 0
B27: Stärke Außenwand (1) [cm]: | L27: =H27*I27+J27 -> 0 | M27: =SUMIF(Fenster!$D$10:$D$2160,Fassade!F27,Fenster!$J$10:$J$2160) -> 0 | N27: =SUMIF(Fenster!$D$10:$D$2160,Fassade!F27,Fenster!$M$10:$M$2160) -> 0 | O27: =SUMIFS(Fenster!$M$10:$M$2160,Fenster!$D$10:$D$2160,Fassade!F27,Fenster!$L$10:$L$2160,">2,5") -> 0 | P27: =SUMIF(Fenster!$D$10:$D$2160,Fassade!F27,Fenster!$K$10:$K$2160) -> 0 | Q27: =L27-O27 -> 0 | R27: =L27-N27 -> 0 | U27: Nettofläche zu dämmen: | V27: =IF(V24="Ja",(R35+V25)*$V$9,0) -> 0 | W27: =IF(W24="Ja",(R35+W25)*$V$9,0) -> 0 | X27: =IF(X24="Ja",(R35+X25)*$V$9,0) -> 0
B28: U-Wert [W/(m²K)]: | L28: =H28*I28+J28 -> 0 | M28: =SUMIF(Fenster!$D$10:$D$2160,Fassade!F28,Fenster!$J$10:$J$2160) -> 0 | N28: =SUMIF(Fenster!$D$10:$D$2160,Fassade!F28,Fenster!$M$10:$M$2160) -> 0 | O28: =SUMIFS(Fenster!$M$10:$M$2160,Fenster!$D$10:$D$2160,Fassade!F28,Fenster!$L$10:$L$2160,">2,5") -> 0 | P28: =SUMIF(Fenster!$D$10:$D$2160,Fassade!F28,Fenster!$K$10:$K$2160) -> 0 | Q28: =L28-O28 -> 0 | R28: =L28-N28 -> 0 | U28: Material, Stärke: | V28: =Allgemein!$D$45 -> - | W28: =Allgemein!$D$61 -> - | X28: =Allgemein!$D$77 -> -
B29: Beschreibung Wandtyp: | L29: =H29*I29+J29 -> 0 | M29: =SUMIF(Fenster!$D$10:$D$2160,Fassade!F29,Fenster!$J$10:$J$2160) -> 0 | N29: =SUMIF(Fenster!$D$10:$D$2160,Fassade!F29,Fenster!$M$10:$M$2160) -> 0 | O29: =SUMIFS(Fenster!$M$10:$M$2160,Fenster!$D$10:$D$2160,Fassade!F29,Fenster!$L$10:$L$2160,">2,5") -> 0 | P29: =SUMIF(Fenster!$D$10:$D$2160,Fassade!F29,Fenster!$K$10:$K$2160) -> 0 | Q29: =L29-O29 -> 0 | R29: =L29-N29 -> 0 | U29: Bemerkung:
B30: Kellerwand?: | L30: =H30*I30+J30 -> 0 | M30: =SUMIF(Fenster!$D$10:$D$2160,Fassade!F30,Fenster!$J$10:$J$2160) -> 0 | N30: =SUMIF(Fenster!$D$10:$D$2160,Fassade!F30,Fenster!$M$10:$M$2160) -> 0 | O30: =SUMIFS(Fenster!$M$10:$M$2160,Fenster!$D$10:$D$2160,Fassade!F30,Fenster!$L$10:$L$2160,">2,5") -> 0 | P30: =SUMIF(Fenster!$D$10:$D$2160,Fassade!F30,Fenster!$K$10:$K$2160) -> 0 | Q30: =L30-O30 -> 0 | R30: =L30-N30 -> 0
L31: =H31*I31+J31 -> 0 | M31: =SUMIF(Fenster!$D$10:$D$2160,Fassade!F31,Fenster!$J$10:$J$2160) -> 0 | N31: =SUMIF(Fenster!$D$10:$D$2160,Fassade!F31,Fenster!$M$10:$M$2160) -> 0 | O31: =SUMIFS(Fenster!$M$10:$M$2160,Fenster!$D$10:$D$2160,Fassade!F31,Fenster!$L$10:$L$2160,">2,5") -> 0 | P31: =SUMIF(Fenster!$D$10:$D$2160,Fassade!F31,Fenster!$K$10:$K$2160) -> 0 | Q31: =L31-O31 -> 0 | R31: =L31-N31 -> 0
L32: =H32*I32+J32 -> 0 | M32: =SUMIF(Fenster!$D$10:$D$2160,Fassade!F32,Fenster!$J$10:$J$2160) -> 0 | N32: =SUMIF(Fenster!$D$10:$D$2160,Fassade!F32,Fenster!$M$10:$M$2160) -> 0 | O32: =SUMIFS(Fenster!$M$10:$M$2160,Fenster!$D$10:$D$2160,Fassade!F32,Fenster!$L$10:$L$2160,">2,5") -> 0 | P32: =SUMIF(Fenster!$D$10:$D$2160,Fassade!F32,Fenster!$K$10:$K$2160) -> 0 | Q32: =L32-O32 -> 0 | R32: =L32-N32 -> 0
L33: =H33*I33+J33 -> 0 | M33: =SUMIF(Fenster!$D$10:$D$2160,Fassade!F33,Fenster!$J$10:$J$2160) -> 0 | N33: =SUMIF(Fenster!$D$10:$D$2160,Fassade!F33,Fenster!$M$10:$M$2160) -> 0 | O33: =SUMIFS(Fenster!$M$10:$M$2160,Fenster!$D$10:$D$2160,Fassade!F33,Fenster!$L$10:$L$2160,">2,5") -> 0 | P33: =SUMIF(Fenster!$D$10:$D$2160,Fassade!F33,Fenster!$K$10:$K$2160) -> 0 | Q33: =L33-O33 -> 0 | R33: =L33-N33 -> 0
L34: =H34*I34+J34 -> 0 | M34: =SUMIF(Fenster!$D$10:$D$2160,Fassade!F34,Fenster!$J$10:$J$2160) -> 0 | N34: =SUMIF(Fenster!$D$10:$D$2160,Fassade!F34,Fenster!$M$10:$M$2160) -> 0 | O34: =SUMIFS(Fenster!$M$10:$M$2160,Fenster!$D$10:$D$2160,Fassade!F34,Fenster!$L$10:$L$2160,">2,5") -> 0 | P34: =SUMIF(Fenster!$D$10:$D$2160,Fassade!F34,Fenster!$K$10:$K$2160) -> 0 | Q34: =L34-O34 -> 0 | R34: =L34-N34 -> 0
F35: Summe: | L35: =SUM(L25:L34) -> 0 | M35: =SUM(M25:M34) -> 0 | N35: =SUM(N25:N34) -> 0 | O35: =SUM(O25:O34) -> 0 | P35: =SUM(P25:P34) -> 0 | Q35: =SUM(Q25:Q34) -> 0 | R35: =SUM(R25:R34) -> 0
B37: Monolithisches Mauerwerk | D37: #VALUE! | F37: Benennung | G37: Beschreibung | H37: Breite [m] | I37: Höhe [m] | J37: Zusatzfläche (Bsp. Giebel) | K37: Anmerkung Zusatzfläche | L37: Brutto- fläche [m²] | M37: Anzahl Öffnungen | N37: Öffnungs- fläche [m²] | O37: Öffnungs- fläche über 2,5 m² [m²] | P37: Umfang Öffnungen [m] | Q37: Kalkulatorische Fläche [m²] | R37: Nettofläche zu dämmen [m²] | U37: WDVS: | V37: {=_xlfn.XLOOKUP(U37&Allgemein!$C$45,Fassadenpositionen[[#Headers],[WDVS:]]&Fassadenpositionen[Position Fassade],Fassadenpositionen[WDVS:],"",0,1)} -> Nein | W37: {=_xlfn.XLOOKUP(U37&Allgemein!$C$61,Fassadenpositionen[[#Headers],[WDVS:]]&Fassadenpositionen[Position Fassade],Fassadenpositionen[WDVS:],"",0,1)} -> Nein | X37: {=_xlfn.XLOOKUP(U37&Allgemein!$C$77,Fassadenpositionen[[#Headers],[WDVS:]]&Fassadenpositionen[Position Fassade],Fassadenpositionen[WDVS:],"",0,1)} -> Nein
B38: Außenwandtyp_xx | L38: =H38*I38+J38 -> 0 | M38: =SUMIF(Fenster!$D$10:$D$2160,Fassade!F38,Fenster!$J$10:$J$2160) -> 0 | N38: =SUMIF(Fenster!$D$10:$D$2160,Fassade!F38,Fenster!$M$10:$M$2160) -> 0 | O38: =SUMIFS(Fenster!$M$10:$M$2160,Fenster!$D$10:$D$2160,Fassade!F38,Fenster!$L$10:$L$2160,">2,5") -> 0 | P38: =SUMIF(Fenster!$D$10:$D$2160,Fassade!F38,Fenster!$K$10:$K$2160) -> 0 | Q38: =L38-O38 -> 0 | R38: =L38-N38 -> 0 | U38: Zusatz oder Abzugsfläche [m²]: | V38: 0 | W38: 0 | X38: 0
B39: Material Außenwand (1): | L39: =H39*I39+J39 -> 0 | M39: =SUMIF(Fenster!$D$10:$D$2160,Fassade!F39,Fenster!$J$10:$J$2160) -> 0 | N39: =SUMIF(Fenster!$D$10:$D$2160,Fassade!F39,Fenster!$M$10:$M$2160) -> 0 | O39: =SUMIFS(Fenster!$M$10:$M$2160,Fenster!$D$10:$D$2160,Fassade!F39,Fenster!$L$10:$L$2160,">2,5") -> 0 | P39: =SUMIF(Fenster!$D$10:$D$2160,Fassade!F39,Fenster!$K$10:$K$2160) -> 0 | Q39: =L39-O39 -> 0 | R39: =L39-N39 -> 0 | U39: Kalkulatorische Fläche: | V39: =IF(V37="Ja",(Q48+V38)*$V$9,0) -> 0 | W39: =IF(W37="Ja",(Q48+W38)*$V$9,0) -> 0 | X39: =IF(X37="Ja",(Q48+X38)*$V$9,0) -> 0
B40: Stärke Außenwand (1) [cm]: | L40: =H40*I40+J40 -> 0 | M40: =SUMIF(Fenster!$D$10:$D$2160,Fassade!F40,Fenster!$J$10:$J$2160) -> 0 | N40: =SUMIF(Fenster!$D$10:$D$2160,Fassade!F40,Fenster!$M$10:$M$2160) -> 0 | O40: =SUMIFS(Fenster!$M$10:$M$2160,Fenster!$D$10:$D$2160,Fassade!F40,Fenster!$L$10:$L$2160,">2,5") -> 0 | P40: =SUMIF(Fenster!$D$10:$D$2160,Fassade!F40,Fenster!$K$10:$K$2160) -> 0 | Q40: =L40-O40 -> 0 | R40: =L40-N40 -> 0 | U40: Nettofläche zu dämmen: | V40: =IF(V37="Ja",(R48+V38)*$V$9,0) -> 0 | W40: =IF(W37="Ja",(R48+W38)*$V$9,0) -> 0 | X40: =IF(X37="Ja",(R48+X38)*$V$9,0) -> 0
B41: U-Wert [W/(m²K)]: | L41: =H41*I41+J41 -> 0 | M41: =SUMIF(Fenster!$D$10:$D$2160,Fassade!F41,Fenster!$J$10:$J$2160) -> 0 | N41: =SUMIF(Fenster!$D$10:$D$2160,Fassade!F41,Fenster!$M$10:$M$2160) -> 0 | O41: =SUMIFS(Fenster!$M$10:$M$2160,Fenster!$D$10:$D$2160,Fassade!F41,Fenster!$L$10:$L$2160,">2,5") -> 0 | P41: =SUMIF(Fenster!$D$10:$D$2160,Fassade!F41,Fenster!$K$10:$K$2160) -> 0 | Q41: =L41-O41 -> 0 | R41: =L41-N41 -> 0 | U41: Material, Stärke: | V41: =Allgemein!$D$45 -> - | W41: =Allgemein!$D$61 -> - | X41: =Allgemein!$D$77 -> -
B42: Beschreibung Wandtyp: | L42: =H42*I42+J42 -> 0 | M42: =SUMIF(Fenster!$D$10:$D$2160,Fassade!F42,Fenster!$J$10:$J$2160) -> 0 | N42: =SUMIF(Fenster!$D$10:$D$2160,Fassade!F42,Fenster!$M$10:$M$2160) -> 0 | O42: =SUMIFS(Fenster!$M$10:$M$2160,Fenster!$D$10:$D$2160,Fassade!F42,Fenster!$L$10:$L$2160,">2,5") -> 0 | P42: =SUMIF(Fenster!$D$10:$D$2160,Fassade!F42,Fenster!$K$10:$K$2160) -> 0 | Q42: =L42-O42 -> 0 | R42: =L42-N42 -> 0 | U42: Bemerkung:
B43: Kellerwand?: | L43: =H43*I43+J43 -> 0 | M43: =SUMIF(Fenster!$D$10:$D$2160,Fassade!F43,Fenster!$J$10:$J$2160) -> 0 | N43: =SUMIF(Fenster!$D$10:$D$2160,Fassade!F43,Fenster!$M$10:$M$2160) -> 0 | O43: =SUMIFS(Fenster!$M$10:$M$2160,Fenster!$D$10:$D$2160,Fassade!F43,Fenster!$L$10:$L$2160,">2,5") -> 0 | P43: =SUMIF(Fenster!$D$10:$D$2160,Fassade!F43,Fenster!$K$10:$K$2160) -> 0 | Q43: =L43-O43 -> 0 | R43: =L43-N43 -> 0
L44: =H44*I44+J44 -> 0 | M44: =SUMIF(Fenster!$D$10:$D$2160,Fassade!F44,Fenster!$J$10:$J$2160) -> 0 | N44: =SUMIF(Fenster!$D$10:$D$2160,Fassade!F44,Fenster!$M$10:$M$2160) -> 0 | O44: =SUMIFS(Fenster!$M$10:$M$2160,Fenster!$D$10:$D$2160,Fassade!F44,Fenster!$L$10:$L$2160,">2,5") -> 0 | P44: =SUMIF(Fenster!$D$10:$D$2160,Fassade!F44,Fenster!$K$10:$K$2160) -> 0 | Q44: =L44-O44 -> 0 | R44: =L44-N44 -> 0
L45: =H45*I45+J45 -> 0 | M45: =SUMIF(Fenster!$D$10:$D$2160,Fassade!F45,Fenster!$J$10:$J$2160) -> 0 | N45: =SUMIF(Fenster!$D$10:$D$2160,Fassade!F45,Fenster!$M$10:$M$2160) -> 0 | O45: =SUMIFS(Fenster!$M$10:$M$2160,Fenster!$D$10:$D$2160,Fassade!F45,Fenster!$L$10:$L$2160,">2,5") -> 0 | P45: =SUMIF(Fenster!$D$10:$D$2160,Fassade!F45,Fenster!$K$10:$K$2160) -> 0 | Q45: =L45-O45 -> 0 | R45: =L45-N45 -> 0
L46: =H46*I46+J46 -> 0 | M46: =SUMIF(Fenster!$D$10:$D$2160,Fassade!F46,Fenster!$J$10:$J$2160) -> 0 | N46: =SUMIF(Fenster!$D$10:$D$2160,Fassade!F46,Fenster!$M$10:$M$2160) -> 0 | O46: =SUMIFS(Fenster!$M$10:$M$2160,Fenster!$D$10:$D$2160,Fassade!F46,Fenster!$L$10:$L$2160,">2,5") -> 0 | P46: =SUMIF(Fenster!$D$10:$D$2160,Fassade!F46,Fenster!$K$10:$K$2160) -> 0 | Q46: =L46-O46 -> 0 | R46: =L46-N46 -> 0
L47: =H47*I47+J47 -> 0 | M47: =SUMIF(Fenster!$D$10:$D$2160,Fassade!F47,Fenster!$J$10:$J$2160) -> 0 | N47: =SUMIF(Fenster!$D$10:$D$2160,Fassade!F47,Fenster!$M$10:$M$2160) -> 0 | O47: =SUMIFS(Fenster!$M$10:$M$2160,Fenster!$D$10:$D$2160,Fassade!F47,Fenster!$L$10:$L$2160,">2,5") -> 0 | P47: =SUMIF(Fenster!$D$10:$D$2160,Fassade!F47,Fenster!$K$10:$K$2160) -> 0 | Q47: =L47-O47 -> 0 | R47: =L47-N47 -> 0
F48: Summe: | L48: =SUM(L38:L47) -> 0 | M48: =SUM(M38:M47) -> 0 | N48: =SUM(N38:N47) -> 0 | O48: =SUM(O38:O47) -> 0 | P48: =SUM(P38:P47) -> 0 | Q48: =SUM(Q38:Q47) -> 0 | R48: =SUM(R38:R47) -> 0
B50: Mauerwerk mit WDVS, Putz | D50: #VALUE! | F50: Benennung | G50: Beschreibung | H50: Breite [m] | I50: Höhe [m] | J50: Zusatzfläche (Bsp. Giebel) | K50: Anmerkung Zusatzfläche | L50: Brutto- fläche [m²] | M50: Anzahl Öffnungen | N50: Öffnungs- fläche [m²] | O50: Öffnungs- fläche über 2,5 m² [m²] | P50: Umfang Öffnungen [m] | Q50: Kalkulatorische Fläche [m²] | R50: Nettofläche zu dämmen [m²] | U50: WDVS: | V50: {=_xlfn.XLOOKUP(U50&Allgemein!$C$45,Fassadenpositionen[[#Headers],[WDVS:]]&Fassadenpositionen[Position Fassade],Fassadenpositionen[WDVS:],"",0,1)} -> Nein | W50: {=_xlfn.XLOOKUP(U50&Allgemein!$C$61,Fassadenpositionen[[#Headers],[WDVS:]]&Fassadenpositionen[Position Fassade],Fassadenpositionen[WDVS:],"",0,1)} -> Nein | X50: {=_xlfn.XLOOKUP(U50&Allgemein!$C$77,Fassadenpositionen[[#Headers],[WDVS:]]&Fassadenpositionen[Position Fassade],Fassadenpositionen[WDVS:],"",0,1)} -> Nein
B51: Außenwandtyp_xx | L51: =H51*I51+J51 -> 0 | M51: =SUMIF(Fenster!$D$10:$D$2160,Fassade!F51,Fenster!$J$10:$J$2160) -> 0 | N51: =SUMIF(Fenster!$D$10:$D$2160,Fassade!F51,Fenster!$M$10:$M$2160) -> 0 | O51: =SUMIFS(Fenster!$M$10:$M$2160,Fenster!$D$10:$D$2160,Fassade!F51,Fenster!$L$10:$L$2160,">2,5") -> 0 | P51: =SUMIF(Fenster!$D$10:$D$2160,Fassade!F51,Fenster!$K$10:$K$2160) -> 0 | Q51: =L51-O51 -> 0 | R51: =L51-N51 -> 0 | U51: Zusatz oder Abzugsfläche [m²]: | V51: 0 | W51: 0 | X51: 0
B52: Material Außenwand (1): | L52: =H52*I52+J52 -> 0 | M52: =SUMIF(Fenster!$D$10:$D$2160,Fassade!F52,Fenster!$J$10:$J$2160) -> 0 | N52: =SUMIF(Fenster!$D$10:$D$2160,Fassade!F52,Fenster!$M$10:$M$2160) -> 0 | O52: =SUMIFS(Fenster!$M$10:$M$2160,Fenster!$D$10:$D$2160,Fassade!F52,Fenster!$L$10:$L$2160,">2,5") -> 0 | P52: =SUMIF(Fenster!$D$10:$D$2160,Fassade!F52,Fenster!$K$10:$K$2160) -> 0 | Q52: =L52-O52 -> 0 | R52: =L52-N52 -> 0 | U52: Kalkulatorische Fläche: | V52: =IF(V50="Ja",(Q61+V51)*$V$9,0) -> 0 | W52: =IF(W50="Ja",(Q61+W51)*$V$9,0) -> 0 | X52: =IF(X50="Ja",(Q61+X51)*$V$9,0) -> 0
B53: Stärke Außenwand (1) [cm]: | L53: =H53*I53+J53 -> 0 | M53: =SUMIF(Fenster!$D$10:$D$2160,Fassade!F53,Fenster!$J$10:$J$2160) -> 0 | N53: =SUMIF(Fenster!$D$10:$D$2160,Fassade!F53,Fenster!$M$10:$M$2160) -> 0 | O53: =SUMIFS(Fenster!$M$10:$M$2160,Fenster!$D$10:$D$2160,Fassade!F53,Fenster!$L$10:$L$2160,">2,5") -> 0 | P53: =SUMIF(Fenster!$D$10:$D$2160,Fassade!F53,Fenster!$K$10:$K$2160) -> 0 | Q53: =L53-O53 -> 0 | R53: =L53-N53 -> 0 | U53: Nettofläche zu dämmen: | V53: =IF(V50="Ja",(R61+V51)*$V$9,0) -> 0 | W53: =IF(W50="Ja",(R61+W51)*$V$9,0) -> 0 | X53: =IF(X50="Ja",(R61+X51)*$V$9,0) -> 0
B54: Material Dämmung (2): | L54: =H54*I54+J54 -> 0 | M54: =SUMIF(Fenster!$D$10:$D$2160,Fassade!F54,Fenster!$J$10:$J$2160) -> 0 | N54: =SUMIF(Fenster!$D$10:$D$2160,Fassade!F54,Fenster!$M$10:$M$2160) -> 0 | O54: =SUMIFS(Fenster!$M$10:$M$2160,Fenster!$D$10:$D$2160,Fassade!F54,Fenster!$L$10:$L$2160,">2,5") -> 0 | P54: =SUMIF(Fenster!$D$10:$D$2160,Fassade!F54,Fenster!$K$10:$K$2160) -> 0 | Q54: =L54-O54 -> 0 | R54: =L54-N54 -> 0 | U54: Material, Stärke: | V54: =Allgemein!$D$45 -> - | W54: =Allgemein!$D$61 -> - | X54: =Allgemein!$D$77 -> -
B55: Stärke Dämmung (2) [cm]: | L55: =H55*I55+J55 -> 0 | M55: =SUMIF(Fenster!$D$10:$D$2160,Fassade!F55,Fenster!$J$10:$J$2160) -> 0 | N55: =SUMIF(Fenster!$D$10:$D$2160,Fassade!F55,Fenster!$M$10:$M$2160) -> 0 | O55: =SUMIFS(Fenster!$M$10:$M$2160,Fenster!$D$10:$D$2160,Fassade!F55,Fenster!$L$10:$L$2160,">2,5") -> 0 | P55: =SUMIF(Fenster!$D$10:$D$2160,Fassade!F55,Fenster!$K$10:$K$2160) -> 0 | Q55: =L55-O55 -> 0 | R55: =L55-N55 -> 0 | U55: Bemerkung:
B56: Wärmeleitfähigkeit [W/(mK)]: | L56: =H56*I56+J56 -> 0 | M56: =SUMIF(Fenster!$D$10:$D$2160,Fassade!F56,Fenster!$J$10:$J$2160) -> 0 | N56: =SUMIF(Fenster!$D$10:$D$2160,Fassade!F56,Fenster!$M$10:$M$2160) -> 0 | O56: =SUMIFS(Fenster!$M$10:$M$2160,Fenster!$D$10:$D$2160,Fassade!F56,Fenster!$L$10:$L$2160,">2,5") -> 0 | P56: =SUMIF(Fenster!$D$10:$D$2160,Fassade!F56,Fenster!$K$10:$K$2160) -> 0 | Q56: =L56-O56 -> 0 | R56: =L56-N56 -> 0
B57: U-Wert [W/(m²K)]: | L57: =H57*I57+J57 -> 0 | M57: =SUMIF(Fenster!$D$10:$D$2160,Fassade!F57,Fenster!$J$10:$J$2160) -> 0 | N57: =SUMIF(Fenster!$D$10:$D$2160,Fassade!F57,Fenster!$M$10:$M$2160) -> 0 | O57: =SUMIFS(Fenster!$M$10:$M$2160,Fenster!$D$10:$D$2160,Fassade!F57,Fenster!$L$10:$L$2160,">2,5") -> 0 | P57: =SUMIF(Fenster!$D$10:$D$2160,Fassade!F57,Fenster!$K$10:$K$2160) -> 0 | Q57: =L57-O57 -> 0 | R57: =L57-N57 -> 0
B58: Beschreibung Wandtyp: | L58: =H58*I58+J58 -> 0 | M58: =SUMIF(Fenster!$D$10:$D$2160,Fassade!F58,Fenster!$J$10:$J$2160) -> 0 | N58: =SUMIF(Fenster!$D$10:$D$2160,Fassade!F58,Fenster!$M$10:$M$2160) -> 0 | O58: =SUMIFS(Fenster!$M$10:$M$2160,Fenster!$D$10:$D$2160,Fassade!F58,Fenster!$L$10:$L$2160,">2,5") -> 0 | P58: =SUMIF(Fenster!$D$10:$D$2160,Fassade!F58,Fenster!$K$10:$K$2160) -> 0 | Q58: =L58-O58 -> 0 | R58: =L58-N58 -> 0
B59: Kellerwand?: | L59: =H59*I59+J59 -> 0 | M59: =SUMIF(Fenster!$D$10:$D$2160,Fassade!F59,Fenster!$J$10:$J$2160) -> 0 | N59: =SUMIF(Fenster!$D$10:$D$2160,Fassade!F59,Fenster!$M$10:$M$2160) -> 0 | O59: =SUMIFS(Fenster!$M$10:$M$2160,Fenster!$D$10:$D$2160,Fassade!F59,Fenster!$L$10:$L$2160,">2,5") -> 0 | P59: =SUMIF(Fenster!$D$10:$D$2160,Fassade!F59,Fenster!$K$10:$K$2160) -> 0 | Q59: =L59-O59 -> 0 | R59: =L59-N59 -> 0
L60: =H60*I60+J60 -> 0 | M60: =SUMIF(Fenster!$D$10:$D$2160,Fassade!F60,Fenster!$J$10:$J$2160) -> 0 | N60: =SUMIF(Fenster!$D$10:$D$2160,Fassade!F60,Fenster!$M$10:$M$2160) -> 0 | O60: =SUMIFS(Fenster!$M$10:$M$2160,Fenster!$D$10:$D$2160,Fassade!F60,Fenster!$L$10:$L$2160,">2,5") -> 0 | P60: =SUMIF(Fenster!$D$10:$D$2160,Fassade!F60,Fenster!$K$10:$K$2160) -> 0 | Q60: =L60-O60 -> 0 | R60: =L60-N60 -> 0
F61: Summe: | L61: =SUM(L51:L60) -> 0 | M61: =SUM(M51:M60) -> 0 | N61: =SUM(N51:N60) -> 0 | O61: =SUM(O51:O60) -> 0 | P61: =SUM(P51:P60) -> 0 | Q61: =SUM(Q51:Q60) -> 0 | R61: =SUM(R51:R60) -> 0
B63: Mauerwerk mit WDVS, Putz | D63: #VALUE! | F63: Benennung | G63: Beschreibung | H63: Breite [m] | I63: Höhe [m] | J63: Zusatzfläche (Bsp. Giebel) | K63: Anmerkung Zusatzfläche | L63: Brutto- fläche [m²] | M63: Anzahl Öffnungen | N63: Öffnungs- fläche [m²] | O63: Öffnungs- fläche über 2,5 m² [m²] | P63: Umfang Öffnungen [m] | Q63: Kalkulatorische Fläche [m²] | R63: Nettofläche zu dämmen [m²] | U63: WDVS: | V63: {=_xlfn.XLOOKUP(U63&Allgemein!$C$45,Fassadenpositionen[[#Headers],[WDVS:]]&Fassadenpositionen[Position Fassade],Fassadenpositionen[WDVS:],"",0,1)} -> Nein | W63: {=_xlfn.XLOOKUP(U63&Allgemein!$C$61,Fassadenpositionen[[#Headers],[WDVS:]]&Fassadenpositionen[Position Fassade],Fassadenpositionen[WDVS:],"",0,1)} -> Nein | X63: {=_xlfn.XLOOKUP(U63&Allgemein!$C$77,Fassadenpositionen[[#Headers],[WDVS:]]&Fassadenpositionen[Position Fassade],Fassadenpositionen[WDVS:],"",0,1)} -> Nein
B64: Außenwandtyp_xx | L64: =H64*I64+J64 -> 0 | M64: =SUMIF(Fenster!$D$10:$D$2160,Fassade!F64,Fenster!$J$10:$J$2160) -> 0 | N64: =SUMIF(Fenster!$D$10:$D$2160,Fassade!F64,Fenster!$M$10:$M$2160) -> 0 | O64: =SUMIFS(Fenster!$M$10:$M$2160,Fenster!$D$10:$D$2160,Fassade!F64,Fenster!$L$10:$L$2160,">2,5") -> 0 | P64: =SUMIF(Fenster!$D$10:$D$2160,Fassade!F64,Fenster!$K$10:$K$2160) -> 0 | Q64: =L64-O64 -> 0 | R64: =L64-N64 -> 0 | U64: Zusatz oder Abzugsfläche [m²]: | V64: 0 | W64: 0 | X64: 0
B65: Material Außenwand (1): | L65: =H65*I65+J65 -> 0 | M65: =SUMIF(Fenster!$D$10:$D$2160,Fassade!F65,Fenster!$J$10:$J$2160) -> 0 | N65: =SUMIF(Fenster!$D$10:$D$2160,Fassade!F65,Fenster!$M$10:$M$2160) -> 0 | O65: =SUMIFS(Fenster!$M$10:$M$2160,Fenster!$D$10:$D$2160,Fassade!F65,Fenster!$L$10:$L$2160,">2,5") -> 0 | P65: =SUMIF(Fenster!$D$10:$D$2160,Fassade!F65,Fenster!$K$10:$K$2160) -> 0 | Q65: =L65-O65 -> 0 | R65: =L65-N65 -> 0 | U65: Kalkulatorische Fläche: | V65: =IF(V63="Ja",(Q74+V64)*$V$9,0) -> 0 | W65: =IF(W63="Ja",(Q74+W64)*$V$9,0) -> 0 | X65: =IF(X63="Ja",(Q74+X64)*$V$9,0) -> 0
B66: Stärke Außenwand (1) [cm]: | L66: =H66*I66+J66 -> 0 | M66: =SUMIF(Fenster!$D$10:$D$2160,Fassade!F66,Fenster!$J$10:$J$2160) -> 0 | N66: =SUMIF(Fenster!$D$10:$D$2160,Fassade!F66,Fenster!$M$10:$M$2160) -> 0 | O66: =SUMIFS(Fenster!$M$10:$M$2160,Fenster!$D$10:$D$2160,Fassade!F66,Fenster!$L$10:$L$2160,">2,5") -> 0 | P66: =SUMIF(Fenster!$D$10:$D$2160,Fassade!F66,Fenster!$K$10:$K$2160) -> 0 | Q66: =L66-O66 -> 0 | R66: =L66-N66 -> 0 | U66: Nettofläche zu dämmen: | V66: =IF(V63="Ja",(R74+V64)*$V$9,0) -> 0 | W66: =IF(W63="Ja",(R74+W64)*$V$9,0) -> 0 | X66: =IF(X63="Ja",(R74+X64)*$V$9,0) -> 0
B67: Material Dämmung (2): | L67: =H67*I67+J67 -> 0 | M67: =SUMIF(Fenster!$D$10:$D$2160,Fassade!F67,Fenster!$J$10:$J$2160) -> 0 | N67: =SUMIF(Fenster!$D$10:$D$2160,Fassade!F67,Fenster!$M$10:$M$2160) -> 0 | O67: =SUMIFS(Fenster!$M$10:$M$2160,Fenster!$D$10:$D$2160,Fassade!F67,Fenster!$L$10:$L$2160,">2,5") -> 0 | P67: =SUMIF(Fenster!$D$10:$D$2160,Fassade!F67,Fenster!$K$10:$K$2160) -> 0 | Q67: =L67-O67 -> 0 | R67: =L67-N67 -> 0 | U67: Material, Stärke: | V67: =Allgemein!$D$45 -> - | W67: =Allgemein!$D$61 -> - | X67: =Allgemein!$D$77 -> -
B68: Stärke Dämmung (2) [cm]: | L68: =H68*I68+J68 -> 0 | M68: =SUMIF(Fenster!$D$10:$D$2160,Fassade!F68,Fenster!$J$10:$J$2160) -> 0 | N68: =SUMIF(Fenster!$D$10:$D$2160,Fassade!F68,Fenster!$M$10:$M$2160) -> 0 | O68: =SUMIFS(Fenster!$M$10:$M$2160,Fenster!$D$10:$D$2160,Fassade!F68,Fenster!$L$10:$L$2160,">2,5") -> 0 | P68: =SUMIF(Fenster!$D$10:$D$2160,Fassade!F68,Fenster!$K$10:$K$2160) -> 0 | Q68: =L68-O68 -> 0 | R68: =L68-N68 -> 0 | U68: Bemerkung:
B69: Wärmeleitfähigkeit [W/(mK)]: | L69: =H69*I69+J69 -> 0 | M69: =SUMIF(Fenster!$D$10:$D$2160,Fassade!F69,Fenster!$J$10:$J$2160) -> 0 | N69: =SUMIF(Fenster!$D$10:$D$2160,Fassade!F69,Fenster!$M$10:$M$2160) -> 0 | O69: =SUMIFS(Fenster!$M$10:$M$2160,Fenster!$D$10:$D$2160,Fassade!F69,Fenster!$L$10:$L$2160,">2,5") -> 0 | P69: =SUMIF(Fenster!$D$10:$D$2160,Fassade!F69,Fenster!$K$10:$K$2160) -> 0 | Q69: =L69-O69 -> 0 | R69: =L69-N69 -> 0
B70: U-Wert [W/(m²K)]: | L70: =H70*I70+J70 -> 0 | M70: =SUMIF(Fenster!$D$10:$D$2160,Fassade!F70,Fenster!$J$10:$J$2160) -> 0 | N70: =SUMIF(Fenster!$D$10:$D$2160,Fassade!F70,Fenster!$M$10:$M$2160) -> 0 | O70: =SUMIFS(Fenster!$M$10:$M$2160,Fenster!$D$10:$D$2160,Fassade!F70,Fenster!$L$10:$L$2160,">2,5") -> 0 | P70: =SUMIF(Fenster!$D$10:$D$2160,Fassade!F70,Fenster!$K$10:$K$2160) -> 0 | Q70: =L70-O70 -> 0 | R70: =L70-N70 -> 0
B71: Beschreibung Wandtyp: | L71: =H71*I71+J71 -> 0 | M71: =SUMIF(Fenster!$D$10:$D$2160,Fassade!F71,Fenster!$J$10:$J$2160) -> 0 | N71: =SUMIF(Fenster!$D$10:$D$2160,Fassade!F71,Fenster!$M$10:$M$2160) -> 0 | O71: =SUMIFS(Fenster!$M$10:$M$2160,Fenster!$D$10:$D$2160,Fassade!F71,Fenster!$L$10:$L$2160,">2,5") -> 0 | P71: =SUMIF(Fenster!$D$10:$D$2160,Fassade!F71,Fenster!$K$10:$K$2160) -> 0 | Q71: =L71-O71 -> 0 | R71: =L71-N71 -> 0
B72: Kellerwand?: | L72: =H72*I72+J72 -> 0 | M72: =SUMIF(Fenster!$D$10:$D$2160,Fassade!F72,Fenster!$J$10:$J$2160) -> 0 | N72: =SUMIF(Fenster!$D$10:$D$2160,Fassade!F72,Fenster!$M$10:$M$2160) -> 0 | O72: =SUMIFS(Fenster!$M$10:$M$2160,Fenster!$D$10:$D$2160,Fassade!F72,Fenster!$L$10:$L$2160,">2,5") -> 0 | P72: =SUMIF(Fenster!$D$10:$D$2160,Fassade!F72,Fenster!$K$10:$K$2160) -> 0 | Q72: =L72-O72 -> 0 | R72: =L72-N72 -> 0
L73: =H73*I73+J73 -> 0 | M73: =SUMIF(Fenster!$D$10:$D$2160,Fassade!F73,Fenster!$J$10:$J$2160) -> 0 | N73: =SUMIF(Fenster!$D$10:$D$2160,Fassade!F73,Fenster!$M$10:$M$2160) -> 0 | O73: =SUMIFS(Fenster!$M$10:$M$2160,Fenster!$D$10:$D$2160,Fassade!F73,Fenster!$L$10:$L$2160,">2,5") -> 0 | P73: =SUMIF(Fenster!$D$10:$D$2160,Fassade!F73,Fenster!$K$10:$K$2160) -> 0 | Q73: =L73-O73 -> 0 | R73: =L73-N73 -> 0
F74: Summe: | L74: =SUM(L64:L73) -> 0 | M74: =SUM(M64:M73) -> 0 | N74: =SUM(N64:N73) -> 0 | O74: =SUM(O64:O73) -> 0 | P74: =SUM(P64:P73) -> 0 | Q74: =SUM(Q64:Q73) -> 0 | R74: =SUM(R64:R73) -> 0
B76: Mauerwerk mit WDVS, Putz | D76: #VALUE! | F76: Benennung | G76: Beschreibung | H76: Breite [m] | I76: Höhe [m] | J76: Zusatzfläche (Bsp. Giebel) | K76: Anmerkung Zusatzfläche | L76: Brutto- fläche [m²] | M76: Anzahl Öffnungen | N76: Öffnungs- fläche [m²] | O76: Öffnungs- fläche über 2,5 m² [m²] | P76: Umfang Öffnungen [m] | Q76: Kalkulatorische Fläche [m²] | R76: Nettofläche zu dämmen [m²] | U76: WDVS: | V76: {=_xlfn.XLOOKUP(U76&Allgemein!$C$45,Fassadenpositionen[[#Headers],[WDVS:]]&Fassadenpositionen[Position Fassade],Fassadenpositionen[WDVS:],"",0,1)} -> Nein | W76: {=_xlfn.XLOOKUP(U76&Allgemein!$C$61,Fassadenpositionen[[#Headers],[WDVS:]]&Fassadenpositionen[Position Fassade],Fassadenpositionen[WDVS:],"",0,1)} -> Nein | X76: {=_xlfn.XLOOKUP(U76&Allgemein!$C$77,Fassadenpositionen[[#Headers],[WDVS:]]&Fassadenpositionen[Position Fassade],Fassadenpositionen[WDVS:],"",0,1)} -> Nein
B77: Außenwandtyp_xx | L77: =H77*I77+J77 -> 0 | M77: =SUMIF(Fenster!$D$10:$D$2160,Fassade!F77,Fenster!$J$10:$J$2160) -> 0 | N77: =SUMIF(Fenster!$D$10:$D$2160,Fassade!F77,Fenster!$M$10:$M$2160) -> 0 | O77: =SUMIFS(Fenster!$M$10:$M$2160,Fenster!$D$10:$D$2160,Fassade!F77,Fenster!$L$10:$L$2160,">2,5") -> 0 | P77: =SUMIF(Fenster!$D$10:$D$2160,Fassade!F77,Fenster!$K$10:$K$2160) -> 0 | Q77: =L77-O77 -> 0 | R77: =L77-N77 -> 0 | U77: Zusatz oder Abzugsfläche [m²]: | V77: 0 | W77: 0 | X77: 0
B78: Material Außenwand (1): | L78: =H78*I78+J78 -> 0 | M78: =SUMIF(Fenster!$D$10:$D$2160,Fassade!F78,Fenster!$J$10:$J$2160) -> 0 | N78: =SUMIF(Fenster!$D$10:$D$2160,Fassade!F78,Fenster!$M$10:$M$2160) -> 0 | O78: =SUMIFS(Fenster!$M$10:$M$2160,Fenster!$D$10:$D$2160,Fassade!F78,Fenster!$L$10:$L$2160,">2,5") -> 0 | P78: =SUMIF(Fenster!$D$10:$D$2160,Fassade!F78,Fenster!$K$10:$K$2160) -> 0 | Q78: =L78-O78 -> 0 | R78: =L78-N78 -> 0 | U78: Kalkulatorische Fläche: | V78: =IF(V76="Ja",(Q87+V77)*$V$9,0) -> 0 | W78: =IF(W76="Ja",(Q87+W77)*$V$9,0) -> 0 | X78: =IF(X76="Ja",(Q87+X77)*$V$9,0) -> 0
B79: Stärke Außenwand (1) [cm]: | L79: =H79*I79+J79 -> 0 | M79: =SUMIF(Fenster!$D$10:$D$2160,Fassade!F79,Fenster!$J$10:$J$2160) -> 0 | N79: =SUMIF(Fenster!$D$10:$D$2160,Fassade!F79,Fenster!$M$10:$M$2160) -> 0 | O79: =SUMIFS(Fenster!$M$10:$M$2160,Fenster!$D$10:$D$2160,Fassade!F79,Fenster!$L$10:$L$2160,">2,5") -> 0 | P79: =SUMIF(Fenster!$D$10:$D$2160,Fassade!F79,Fenster!$K$10:$K$2160) -> 0 | Q79: =L79-O79 -> 0 | R79: =L79-N79 -> 0 | U79: Nettofläche zu dämmen: | V79: =IF(V76="Ja",(R87+V77)*$V$9,0) -> 0 | W79: =IF(W76="Ja",(R87+W77)*$V$9,0) -> 0 | X79: =IF(X76="Ja",(R87+X77)*$V$9,0) -> 0
B80: Material Dämmung (2): | L80: =H80*I80+J80 -> 0 | M80: =SUMIF(Fenster!$D$10:$D$2160,Fassade!F80,Fenster!$J$10:$J$2160) -> 0 | N80: =SUMIF(Fenster!$D$10:$D$2160,Fassade!F80,Fenster!$M$10:$M$2160) -> 0 | O80: =SUMIFS(Fenster!$M$10:$M$2160,Fenster!$D$10:$D$2160,Fassade!F80,Fenster!$L$10:$L$2160,">2,5") -> 0 | P80: =SUMIF(Fenster!$D$10:$D$2160,Fassade!F80,Fenster!$K$10:$K$2160) -> 0 | Q80: =L80-O80 -> 0 | R80: =L80-N80 -> 0 | U80: Material, Stärke: | V80: =Allgemein!$D$45 -> - | W80: =Allgemein!$D$61 -> - | X80: =Allgemein!$D$77 -> -
B81: Stärke Dämmung (2) [cm]: | L81: =H81*I81+J81 -> 0 | M81: =SUMIF(Fenster!$D$10:$D$2160,Fassade!F81,Fenster!$J$10:$J$2160) -> 0 | N81: =SUMIF(Fenster!$D$10:$D$2160,Fassade!F81,Fenster!$M$10:$M$2160) -> 0 | O81: =SUMIFS(Fenster!$M$10:$M$2160,Fenster!$D$10:$D$2160,Fassade!F81,Fenster!$L$10:$L$2160,">2,5") -> 0 | P81: =SUMIF(Fenster!$D$10:$D$2160,Fassade!F81,Fenster!$K$10:$K$2160) -> 0 | Q81: =L81-O81 -> 0 | R81: =L81-N81 -> 0 | U81: Bemerkung:
B82: Wärmeleitfähigkeit [W/(mK)]: | L82: =H82*I82+J82 -> 0 | M82: =SUMIF(Fenster!$D$10:$D$2160,Fassade!F82,Fenster!$J$10:$J$2160) -> 0 | N82: =SUMIF(Fenster!$D$10:$D$2160,Fassade!F82,Fenster!$M$10:$M$2160) -> 0 | O82: =SUMIFS(Fenster!$M$10:$M$2160,Fenster!$D$10:$D$2160,Fassade!F82,Fenster!$L$10:$L$2160,">2,5") -> 0 | P82: =SUMIF(Fenster!$D$10:$D$2160,Fassade!F82,Fenster!$K$10:$K$2160) -> 0 | Q82: =L82-O82 -> 0 | R82: =L82-N82 -> 0
B83: U-Wert [W/(m²K)]: | L83: =H83*I83+J83 -> 0 | M83: =SUMIF(Fenster!$D$10:$D$2160,Fassade!F83,Fenster!$J$10:$J$2160) -> 0 | N83: =SUMIF(Fenster!$D$10:$D$2160,Fassade!F83,Fenster!$M$10:$M$2160) -> 0 | O83: =SUMIFS(Fenster!$M$10:$M$2160,Fenster!$D$10:$D$2160,Fassade!F83,Fenster!$L$10:$L$2160,">2,5") -> 0 | P83: =SUMIF(Fenster!$D$10:$D$2160,Fassade!F83,Fenster!$K$10:$K$2160) -> 0 | Q83: =L83-O83 -> 0 | R83: =L83-N83 -> 0
B84: Beschreibung Wandtyp: | L84: =H84*I84+J84 -> 0 | M84: =SUMIF(Fenster!$D$10:$D$2160,Fassade!F84,Fenster!$J$10:$J$2160) -> 0 | N84: =SUMIF(Fenster!$D$10:$D$2160,Fassade!F84,Fenster!$M$10:$M$2160) -> 0 | O84: =SUMIFS(Fenster!$M$10:$M$2160,Fenster!$D$10:$D$2160,Fassade!F84,Fenster!$L$10:$L$2160,">2,5") -> 0 | P84: =SUMIF(Fenster!$D$10:$D$2160,Fassade!F84,Fenster!$K$10:$K$2160) -> 0 | Q84: =L84-O84 -> 0 | R84: =L84-N84 -> 0
B85: Kellerwand?: | L85: =H85*I85+J85 -> 0 | M85: =SUMIF(Fenster!$D$10:$D$2160,Fassade!F85,Fenster!$J$10:$J$2160) -> 0 | N85: =SUMIF(Fenster!$D$10:$D$2160,Fassade!F85,Fenster!$M$10:$M$2160) -> 0 | O85: =SUMIFS(Fenster!$M$10:$M$2160,Fenster!$D$10:$D$2160,Fassade!F85,Fenster!$L$10:$L$2160,">2,5") -> 0 | P85: =SUMIF(Fenster!$D$10:$D$2160,Fassade!F85,Fenster!$K$10:$K$2160) -> 0 | Q85: =L85-O85 -> 0 | R85: =L85-N85 -> 0
L86: =H86*I86+J86 -> 0 | M86: =SUMIF(Fenster!$D$10:$D$2160,Fassade!F86,Fenster!$J$10:$J$2160) -> 0 | N86: =SUMIF(Fenster!$D$10:$D$2160,Fassade!F86,Fenster!$M$10:$M$2160) -> 0 | O86: =SUMIFS(Fenster!$M$10:$M$2160,Fenster!$D$10:$D$2160,Fassade!F86,Fenster!$L$10:$L$2160,">2,5") -> 0 | P86: =SUMIF(Fenster!$D$10:$D$2160,Fassade!F86,Fenster!$K$10:$K$2160) -> 0 | Q86: =L86-O86 -> 0 | R86: =L86-N86 -> 0
F87: Summe: | L87: =SUM(L77:L86) -> 0 | M87: =SUM(M77:M86) -> 0 | N87: =SUM(N77:N86) -> 0 | O87: =SUM(O77:O86) -> 0 | P87: =SUM(P77:P86) -> 0 | Q87: =SUM(Q77:Q86) -> 0 | R87: =SUM(R77:R86) -> 0
B89: Mauerwerk mit WDVS, Riemchen | D89: #VALUE! | F89: Benennung | G89: Beschreibung | H89: Breite [m] | I89: Höhe [m] | J89: Zusatzfläche (Bsp. Giebel) | K89: Anmerkung Zusatzfläche | L89: Brutto- fläche [m²] | M89: Anzahl Öffnungen | N89: Öffnungs- fläche [m²] | O89: Öffnungs- fläche über 2,5 m² [m²] | P89: Umfang Öffnungen [m] | Q89: Kalkulatorische Fläche [m²] | R89: Nettofläche zu dämmen [m²] | U89: WDVS: | V89: {=_xlfn.XLOOKUP(U89&Allgemein!$C$45,Fassadenpositionen[[#Headers],[WDVS:]]&Fassadenpositionen[Position Fassade],Fassadenpositionen[WDVS:],"",0,1)} -> Nein | W89: {=_xlfn.XLOOKUP(U89&Allgemein!$C$61,Fassadenpositionen[[#Headers],[WDVS:]]&Fassadenpositionen[Position Fassade],Fassadenpositionen[WDVS:],"",0,1)} -> Nein | X89: {=_xlfn.XLOOKUP(U89&Allgemein!$C$77,Fassadenpositionen[[#Headers],[WDVS:]]&Fassadenpositionen[Position Fassade],Fassadenpositionen[WDVS:],"",0,1)} -> Nein
B90: Außenwandtyp_xx | L90: =H90*I90+J90 -> 0 | M90: =SUMIF(Fenster!$D$10:$D$2160,Fassade!F90,Fenster!$J$10:$J$2160) -> 0 | N90: =SUMIF(Fenster!$D$10:$D$2160,Fassade!F90,Fenster!$M$10:$M$2160) -> 0 | O90: =SUMIFS(Fenster!$M$10:$M$2160,Fenster!$D$10:$D$2160,Fassade!F90,Fenster!$L$10:$L$2160,">2,5") -> 0 | P90: =SUMIF(Fenster!$D$10:$D$2160,Fassade!F90,Fenster!$K$10:$K$2160) -> 0 | Q90: =L90-O90 -> 0 | R90: =L90-N90 -> 0 | U90: Zusatz oder Abzugsfläche [m²]: | V90: 0 | W90: 0 | X90: 0
B91: Material Außenwand (1): | L91: =H91*I91+J91 -> 0 | M91: =SUMIF(Fenster!$D$10:$D$2160,Fassade!F91,Fenster!$J$10:$J$2160) -> 0 | N91: =SUMIF(Fenster!$D$10:$D$2160,Fassade!F91,Fenster!$M$10:$M$2160) -> 0 | O91: =SUMIFS(Fenster!$M$10:$M$2160,Fenster!$D$10:$D$2160,Fassade!F91,Fenster!$L$10:$L$2160,">2,5") -> 0 | P91: =SUMIF(Fenster!$D$10:$D$2160,Fassade!F91,Fenster!$K$10:$K$2160) -> 0 | Q91: =L91-O91 -> 0 | R91: =L91-N91 -> 0 | U91: Kalkulatorische Fläche: | V91: =IF(V89="Ja",(Q100+V90)*$V$9,0) -> 0 | W91: =IF(W89="Ja",(Q100+W90)*$V$9,0) -> 0 | X91: =IF(X89="Ja",(Q100+X90)*$V$9,0) -> 0
B92: Stärke Außenwand (1) [cm]: | L92: =H92*I92+J92 -> 0 | M92: =SUMIF(Fenster!$D$10:$D$2160,Fassade!F92,Fenster!$J$10:$J$2160) -> 0 | N92: =SUMIF(Fenster!$D$10:$D$2160,Fassade!F92,Fenster!$M$10:$M$2160) -> 0 | O92: =SUMIFS(Fenster!$M$10:$M$2160,Fenster!$D$10:$D$2160,Fassade!F92,Fenster!$L$10:$L$2160,">2,5") -> 0 | P92: =SUMIF(Fenster!$D$10:$D$2160,Fassade!F92,Fenster!$K$10:$K$2160) -> 0 | Q92: =L92-O92 -> 0 | R92: =L92-N92 -> 0 | U92: Nettofläche zu dämmen: | V92: =IF(V89="Ja",(R100+V90)*$V$9,0) -> 0 | W92: =IF(W89="Ja",(R100+W90)*$V$9,0) -> 0 | X92: =IF(X89="Ja",(R100+X90)*$V$9,0) -> 0
B93: Material Dämmung (2): | L93: =H93*I93+J93 -> 0 | M93: =SUMIF(Fenster!$D$10:$D$2160,Fassade!F93,Fenster!$J$10:$J$2160) -> 0 | N93: =SUMIF(Fenster!$D$10:$D$2160,Fassade!F93,Fenster!$M$10:$M$2160) -> 0 | O93: =SUMIFS(Fenster!$M$10:$M$2160,Fenster!$D$10:$D$2160,Fassade!F93,Fenster!$L$10:$L$2160,">2,5") -> 0 | P93: =SUMIF(Fenster!$D$10:$D$2160,Fassade!F93,Fenster!$K$10:$K$2160) -> 0 | Q93: =L93-O93 -> 0 | R93: =L93-N93 -> 0 | U93: Material, Stärke: | V93: =Allgemein!$D$45 -> - | W93: =Allgemein!$D$61 -> - | X93: =Allgemein!$D$77 -> -
B94: Stärke Dämmung (2) [cm]: | L94: =H94*I94+J94 -> 0 | M94: =SUMIF(Fenster!$D$10:$D$2160,Fassade!F94,Fenster!$J$10:$J$2160) -> 0 | N94: =SUMIF(Fenster!$D$10:$D$2160,Fassade!F94,Fenster!$M$10:$M$2160) -> 0 | O94: =SUMIFS(Fenster!$M$10:$M$2160,Fenster!$D$10:$D$2160,Fassade!F94,Fenster!$L$10:$L$2160,">2,5") -> 0 | P94: =SUMIF(Fenster!$D$10:$D$2160,Fassade!F94,Fenster!$K$10:$K$2160) -> 0 | Q94: =L94-O94 -> 0 | R94: =L94-N94 -> 0 | U94: Bemerkung:
B95: Wärmeleitfähigkeit [W/(mK)]: | L95: =H95*I95+J95 -> 0 | M95: =SUMIF(Fenster!$D$10:$D$2160,Fassade!F95,Fenster!$J$10:$J$2160) -> 0 | N95: =SUMIF(Fenster!$D$10:$D$2160,Fassade!F95,Fenster!$M$10:$M$2160) -> 0 | O95: =SUMIFS(Fenster!$M$10:$M$2160,Fenster!$D$10:$D$2160,Fassade!F95,Fenster!$L$10:$L$2160,">2,5") -> 0 | P95: =SUMIF(Fenster!$D$10:$D$2160,Fassade!F95,Fenster!$K$10:$K$2160) -> 0 | Q95: =L95-O95 -> 0 | R95: =L95-N95 -> 0
B96: U-Wert [W/(m²K)]: | L96: =H96*I96+J96 -> 0 | M96: =SUMIF(Fenster!$D$10:$D$2160,Fassade!F96,Fenster!$J$10:$J$2160) -> 0 | N96: =SUMIF(Fenster!$D$10:$D$2160,Fassade!F96,Fenster!$M$10:$M$2160) -> 0 | O96: =SUMIFS(Fenster!$M$10:$M$2160,Fenster!$D$10:$D$2160,Fassade!F96,Fenster!$L$10:$L$2160,">2,5") -> 0 | P96: =SUMIF(Fenster!$D$10:$D$2160,Fassade!F96,Fenster!$K$10:$K$2160) -> 0 | Q96: =L96-O96 -> 0 | R96: =L96-N96 -> 0
B97: Beschreibung Wandtyp: | L97: =H97*I97+J97 -> 0 | M97: =SUMIF(Fenster!$D$10:$D$2160,Fassade!F97,Fenster!$J$10:$J$2160) -> 0 | N97: =SUMIF(Fenster!$D$10:$D$2160,Fassade!F97,Fenster!$M$10:$M$2160) -> 0 | O97: =SUMIFS(Fenster!$M$10:$M$2160,Fenster!$D$10:$D$2160,Fassade!F97,Fenster!$L$10:$L$2160,">2,5") -> 0 | P97: =SUMIF(Fenster!$D$10:$D$2160,Fassade!F97,Fenster!$K$10:$K$2160) -> 0 | Q97: =L97-O97 -> 0 | R97: =L97-N97 -> 0
B98: Kellerwand?: | L98: =H98*I98+J98 -> 0 | M98: =SUMIF(Fenster!$D$10:$D$2160,Fassade!F98,Fenster!$J$10:$J$2160) -> 0 | N98: =SUMIF(Fenster!$D$10:$D$2160,Fassade!F98,Fenster!$M$10:$M$2160) -> 0 | O98: =SUMIFS(Fenster!$M$10:$M$2160,Fenster!$D$10:$D$2160,Fassade!F98,Fenster!$L$10:$L$2160,">2,5") -> 0 | P98: =SUMIF(Fenster!$D$10:$D$2160,Fassade!F98,Fenster!$K$10:$K$2160) -> 0 | Q98: =L98-O98 -> 0 | R98: =L98-N98 -> 0
L99: =H99*I99+J99 -> 0 | M99: =SUMIF(Fenster!$D$10:$D$2160,Fassade!F99,Fenster!$J$10:$J$2160) -> 0 | N99: =SUMIF(Fenster!$D$10:$D$2160,Fassade!F99,Fenster!$M$10:$M$2160) -> 0 | O99: =SUMIFS(Fenster!$M$10:$M$2160,Fenster!$D$10:$D$2160,Fassade!F99,Fenster!$L$10:$L$2160,">2,5") -> 0 | P99: =SUMIF(Fenster!$D$10:$D$2160,Fassade!F99,Fenster!$K$10:$K$2160) -> 0 | Q99: =L99-O99 -> 0 | R99: =L99-N99 -> 0
F100: Summe: | L100: =SUM(L90:L99) -> 0 | M100: =SUM(M90:M99) -> 0 | N100: =SUM(N90:N99) -> 0 | O100: =SUM(O90:O99) -> 0 | P100: =SUM(P90:P99) -> 0 | Q100: =SUM(Q90:Q99) -> 0 | R100: =SUM(R90:R99) -> 0
B102: Mauerwerk mit WDVS, Riemchen | D102: #VALUE! | F102: Benennung | G102: Beschreibung | H102: Breite [m] | I102: Höhe [m] | J102: Zusatzfläche (Bsp. Giebel) | K102: Anmerkung Zusatzfläche | L102: Brutto- fläche [m²] | M102: Anzahl Öffnungen | N102: Öffnungs- fläche [m²] | O102: Öffnungs- fläche über 2,5 m² [m²] | P102: Umfang Öffnungen [m] | Q102: Kalkulatorische Fläche [m²] | R102: Nettofläche zu dämmen [m²] | U102: WDVS: | V102: {=_xlfn.XLOOKUP(U102&Allgemein!$C$45,Fassadenpositionen[[#Headers],[WDVS:]]&Fassadenpositionen[Position Fassade],Fassadenpositionen[WDVS:],"",0,1)} -> Nein | W102: {=_xlfn.XLOOKUP(U102&Allgemein!$C$61,Fassadenpositionen[[#Headers],[WDVS:]]&Fassadenpositionen[Position Fassade],Fassadenpositionen[WDVS:],"",0,1)} -> Nein | X102: {=_xlfn.XLOOKUP(U102&Allgemein!$C$77,Fassadenpositionen[[#Headers],[WDVS:]]&Fassadenpositionen[Position Fassade],Fassadenpositionen[WDVS:],"",0,1)} -> Nein
B103: Außenwandtyp_xx | L103: =H103*I103+J103 -> 0 | M103: =SUMIF(Fenster!$D$10:$D$2160,Fassade!F103,Fenster!$J$10:$J$2160) -> 0 | N103: =SUMIF(Fenster!$D$10:$D$2160,Fassade!F103,Fenster!$M$10:$M$2160) -> 0 | O103: =SUMIFS(Fenster!$M$10:$M$2160,Fenster!$D$10:$D$2160,Fassade!F103,Fenster!$L$10:$L$2160,">2,5") -> 0 | P103: =SUMIF(Fenster!$D$10:$D$2160,Fassade!F103,Fenster!$K$10:$K$2160) -> 0 | Q103: =L103-O103 -> 0 | R103: =L103-N103 -> 0 | U103: Zusatz oder Abzugsfläche [m²]: | V103: 0 | W103: 0 | X103: 0
B104: Material Außenwand (1): | L104: =H104*I104+J104 -> 0 | M104: =SUMIF(Fenster!$D$10:$D$2160,Fassade!F104,Fenster!$J$10:$J$2160) -> 0 | N104: =SUMIF(Fenster!$D$10:$D$2160,Fassade!F104,Fenster!$M$10:$M$2160) -> 0 | O104: =SUMIFS(Fenster!$M$10:$M$2160,Fenster!$D$10:$D$2160,Fassade!F104,Fenster!$L$10:$L$2160,">2,5") -> 0 | P104: =SUMIF(Fenster!$D$10:$D$2160,Fassade!F104,Fenster!$K$10:$K$2160) -> 0 | Q104: =L104-O104 -> 0 | R104: =L104-N104 -> 0 | U104: Kalkulatorische Fläche: | V104: =IF(V102="Ja",(Q113+V103)*$V$9,0) -> 0 | W104: =IF(W102="Ja",(Q113+W103)*$V$9,0) -> 0 | X104: =IF(X102="Ja",(Q113+X103)*$V$9,0) -> 0
B105: Stärke Außenwand (1) [cm]: | L105: =H105*I105+J105 -> 0 | M105: =SUMIF(Fenster!$D$10:$D$2160,Fassade!F105,Fenster!$J$10:$J$2160) -> 0 | N105: =SUMIF(Fenster!$D$10:$D$2160,Fassade!F105,Fenster!$M$10:$M$2160) -> 0 | O105: =SUMIFS(Fenster!$M$10:$M$2160,Fenster!$D$10:$D$2160,Fassade!F105,Fenster!$L$10:$L$2160,">2,5") -> 0 | P105: =SUMIF(Fenster!$D$10:$D$2160,Fassade!F105,Fenster!$K$10:$K$2160) -> 0 | Q105: =L105-O105 -> 0 | R105: =L105-N105 -> 0 | U105: Nettofläche zu dämmen: | V105: =IF(V102="Ja",(R113+V103)*$V$9,0) -> 0 | W105: =IF(W102="Ja",(R113+W103)*$V$9,0) -> 0 | X105: =IF(X102="Ja",(R113+X103)*$V$9,0) -> 0
B106: Material Dämmung (2): | L106: =H106*I106+J106 -> 0 | M106: =SUMIF(Fenster!$D$10:$D$2160,Fassade!F106,Fenster!$J$10:$J$2160) -> 0 | N106: =SUMIF(Fenster!$D$10:$D$2160,Fassade!F106,Fenster!$M$10:$M$2160) -> 0 | O106: =SUMIFS(Fenster!$M$10:$M$2160,Fenster!$D$10:$D$2160,Fassade!F106,Fenster!$L$10:$L$2160,">2,5") -> 0 | P106: =SUMIF(Fenster!$D$10:$D$2160,Fassade!F106,Fenster!$K$10:$K$2160) -> 0 | Q106: =L106-O106 -> 0 | R106: =L106-N106 -> 0 | U106: Material, Stärke: | V106: =Allgemein!$D$45 -> - | W106: =Allgemein!$D$61 -> - | X106: =Allgemein!$D$77 -> -
B107: Stärke Dämmung (2) [cm]: | L107: =H107*I107+J107 -> 0 | M107: =SUMIF(Fenster!$D$10:$D$2160,Fassade!F107,Fenster!$J$10:$J$2160) -> 0 | N107: =SUMIF(Fenster!$D$10:$D$2160,Fassade!F107,Fenster!$M$10:$M$2160) -> 0 | O107: =SUMIFS(Fenster!$M$10:$M$2160,Fenster!$D$10:$D$2160,Fassade!F107,Fenster!$L$10:$L$2160,">2,5") -> 0 | P107: =SUMIF(Fenster!$D$10:$D$2160,Fassade!F107,Fenster!$K$10:$K$2160) -> 0 | Q107: =L107-O107 -> 0 | R107: =L107-N107 -> 0 | U107: Bemerkung:
B108: Wärmeleitfähigkeit [W/(mK)]: | L108: =H108*I108+J108 -> 0 | M108: =SUMIF(Fenster!$D$10:$D$2160,Fassade!F108,Fenster!$J$10:$J$2160) -> 0 | N108: =SUMIF(Fenster!$D$10:$D$2160,Fassade!F108,Fenster!$M$10:$M$2160) -> 0 | O108: =SUMIFS(Fenster!$M$10:$M$2160,Fenster!$D$10:$D$2160,Fassade!F108,Fenster!$L$10:$L$2160,">2,5") -> 0 | P108: =SUMIF(Fenster!$D$10:$D$2160,Fassade!F108,Fenster!$K$10:$K$2160) -> 0 | Q108: =L108-O108 -> 0 | R108: =L108-N108 -> 0
...

Sheet Fenster
B2: Projektnummer: | C2: =Allgemein!C2 -> 0 | H2: Fenster und Türen | R2: #VALUE!
B3: Anrede: | C3: =Allgemein!C3 -> 0 | J3: Kurzbeschreibung Maßnahmen
B4: Vorname Nachname: | C4: =Allgemein!C4 -> 0 | H4: Umsetzungsvariante: | J4: =Allgemein!C96 -> 0
B5: Straße, Nr. (Objektadresse): | C5: =Allgemein!C5 -> 0 | H5: Zusatzleistung: | J5: =Allgemein!G96 -> 0
B6: PLZ, Ort:: | C6: =Allgemein!C6 -> 0 | H6: Variante 1: | J6: =Allgemein!C46 -> -
B7: Email: | C7: =Allgemein!C7 -> 0 | H7: Variante 2: | J7: =Allgemein!C62 -> -
B8: Telefon: | C8: =Allgemein!C8 -> 0 | H8: Variante 3: | J8: =Allgemein!C78 -> -
B9: Allgemeines zu Fenster und Türen
B10: Bestand | J10: Zusammenfassung Bestand | L10: Umsetzung
B11: Fenstertypen | C11: Verglasung | D11: Material | E11: Baujahr | F11: U-Wert [W/(m²K)] | G11: Rolladen? | H11: Beschreibung | J11: Gesamtfläche Fenster [m²]: | M11: iSFP | N11: Variante 1 | O11: Variante 2 | R11: iSFP | S11: Variante 1 | T11: Variante 2
B12: Fenstertyp 1 | J12: {=SUMPRODUCT(IF(IF($C$25:$C$74<>"",_xlfn.TEXTBEFORE($C$25:$C$74,"_")="Fenster",),$M$25:$M$74,0))} -> 0 | L12: Fensteraustausch: | M12: {=_xlfn.XLOOKUP(L12&Allgemein!C46,Tabelle2527[[#Headers],[Fensteraustausch:]]&Tabelle2527[Position Fenster],Tabelle2527[Fensteraustausch:],"",0,1)} -> Nein | N12: {=_xlfn.XLOOKUP(L12&Allgemein!C62,Tabelle2527[[#Headers],[Fensteraustausch:]]&Tabelle2527[Position Fenster],Tabelle2527[Fensteraustausch:],"",0,1)} -> Nein | O12: {=_xlfn.XLOOKUP(L12&Allgemein!C78,Tabelle2527[[#Headers],[Fensteraustausch:]]&Tabelle2527[Position Fenster],Tabelle2527[Fensteraustausch:],"",0,1)} -> Nein | Q12: Türaustausch: | R12: {=_xlfn.XLOOKUP(Q12&Allgemein!C46,Tabelle2527[[#Headers],[Türaustausch:]]&Tabelle2527[Position Fenster],Tabelle2527[Türaustausch:],"",0,1)} -> Nein | S12: {=_xlfn.XLOOKUP(Q12&Allgemein!C62,Tabelle2527[[#Headers],[Türaustausch:]]&Tabelle2527[Position Fenster],Tabelle2527[Türaustausch:],"",0,1)} -> Nein | T12: {=_xlfn.XLOOKUP(Q12&Allgemein!C78,Tabelle2527[[#Headers],[Türaustausch:]]&Tabelle2527[Position Fenster],Tabelle2527[Türaustausch:],"",0,1)} -> Nein
B13: Fenstertyp 2 | L13: Austauschfläche [m²]: | M13: =SUMIF(R25:R74,"Ja",$O$25:$O$74) -> 0 | N13: =SUMIF(S25:S74,"Ja",$O$25:$O$74) -> 0 | O13: =SUMIF(T25:T74,"Ja",$O$25:$O$74) -> 0 | Q13: Anzahl Austausch: | R13: {=SUMPRODUCT(IF(IF($C$25:$C$74<>"",IF(R25:R74="Ja",_xlfn.TEXTBEFORE($C$25:$C$74,"_")="Tür",)),$J$25:$J$74,0))} -> 0 | S13: {=SUMPRODUCT(IF(IF($C$25:$C$74<>"",IF(S25:S74="Ja",_xlfn.TEXTBEFORE($C$25:$C$74,"_")="Tür",)),$J$25:$J$74,0))} -> 0 | T13: {=SUMPRODUCT(IF(IF($C$25:$C$74<>"",IF(T25:T74="Ja",_xlfn.TEXTBEFORE($C$25:$C$74,"_")="Tür",)),$J$25:$J$74,0))} -> 0
B14: Fenstertyp 3 | J14: Gesamt Anzahl Türen: | L14: Austausch Anzahl: | M14: =IF(M12="Nein",0,SUMIF(R25:R74,"Ja",$J$25:$J$74)) -> 0 | N14: =IF(N12="Nein",0,SUMIF(S25:S74,"Ja",$J$25:$J$74)) -> 0 | O14: =IF(O12="Nein",0,SUMIF(T25:T74,"Ja",$J$25:$J$74)) -> 0 | Q14: Art:
B15: Fenstertyp 4 | J15: {=SUMPRODUCT(IF(IF($C$25:$C$74<>"",_xlfn.TEXTBEFORE($C$25:$C$74,"_")="Tür",),$J$25:$J$74,0))} -> 0 | L15: Art: | Q15: Bemerkung Ausführung:
B16: Fenstertyp 5 | L16: Summe Fensterbreite [m]: | M16: {=SUMPRODUCT(IF(IF($C$25:$C$74<>"",IF(R25:R74="Ja",_xlfn.TEXTBEFORE($C$25:$C$74,"_")="Fenster",)),$H$25:$H$74*$J$25:$J$74,0))} -> 0 | N16: {=SUMPRODUCT(IF(IF($C$25:$C$74<>"",IF(S25:S74="Ja",_xlfn.TEXTBEFORE($C$25:$C$74,"_")="Fenster",)),$H$25:$H$74*$J$25:$J$74,0))} -> 0 | O16: {=SUMPRODUCT(IF(IF($C$25:$C$74<>"",IF(T25:T74="Ja",_xlfn.TEXTBEFORE($C$25:$C$74,"_")="Fenster",)),$H$25:$H$74*$J$25:$J$74,0))} -> 0
B17: Türtypen | L17: Bemerkung Ausführung:
B18: Türtyp 1
B19: Türtyp 2
B20: Türtyp 3
B21: Türtyp_4
B22: vorhandene Fenster und Türen
N23: Wunsch/Anmerkung | R23: iSFP | S23: Variante 1 | T23: Variante 2
B24: Typ | C24: Benennung | D24: Außenwand | E24: Beschreibung Außenwand | F24: Geschoss | G24: Ausrichtung | H24: Breite [m] | I24: Höhe [m] | J24: Anzahl | K24: Umfang [m] | L24: Fläche-E [m²] | M24: Fläche-G [m²] | N24: Austausch gewünscht? | O24: Austauschfläche Fenster [m²] | P24: Rolladen neu? | Q24: Bemerkung | R24: Austausch iSFP? | S24: Austausch V1?2 | T24: Austausch V2?2
E25: =IF(D25="","",_xlfn.XLOOKUP(D25,Fassade!$F$10:$F$515,Fassade!$G$10:$G$515,"",0,1)) | K25: =(2*H25+2*I25)*J25 -> 0 | L25: =H25*I25 -> 0 | M25: =PRODUCT(H25*I25*J25) -> 0 | O25: =IF(B25="",0,IF(AND(N25="Ja",_xlfn.TEXTBEFORE(Tabelle36[[#This Row],[Benennung]],"_")="Fenster"),H25*I25*J25,0)) -> 0 | R25: =IF(AND(_xlfn.TEXTBEFORE(Tabelle36[[#This Row],[Benennung]],"_")="Fenster",$M$12="Nein"),"Nein",IF(AND(_xlfn.TEXTBEFORE(Tabelle36[[#This Row],[Benennung]],"_")="Tür",$R$12="Nein"),"Nein",IF(Tabelle36[[#This Row],[Austausch gewünscht?]]="Ja","Ja",IF(Tabelle36[[#This Row],[Austausch gewünscht?]]="Nein","Nein","")))) -> #N/A | S25: =IF(AND(_xlfn.TEXTBEFORE(Tabelle36[[#This Row],[Benennung]],"_")="Fenster",$N$12="Nein"),"Nein",IF(AND(_xlfn.TEXTBEFORE(Tabelle36[[#This Row],[Benennung]],"_")="Tür",$S$12="Nein"),"Nein",IF(Tabelle36[[#This Row],[Austausch gewünscht?]]="Ja","Ja",IF(Tabelle36[[#This Row],[Austausch gewünscht?]]="Nein","Nein","")))) -> #N/A | T25: =IF(AND(_xlfn.TEXTBEFORE(Tabelle36[[#This Row],[Benennung]],"_")="Fenster",$O$12="Nein"),"Nein",IF(AND(_xlfn.TEXTBEFORE(Tabelle36[[#This Row],[Benennung]],"_")="Tür",$T$12="Nein"),"Nein",IF(Tabelle36[[#This Row],[Austausch gewünscht?]]="Ja","Ja",IF(Tabelle36[[#This Row],[Austausch gewünscht?]]="Nein","Nein","")))) -> #N/A
E26: =IF(D26="","",_xlfn.XLOOKUP(D26,Fassade!$F$10:$F$515,Fassade!$G$10:$G$515,"",0,1)) | K26: =(2*H26+2*I26)*J26 -> 0 | L26: =H26*I26 -> 0 | M26: =PRODUCT(H26*I26*J26) -> 0 | O26: =IF(B26="",0,IF(AND(N26="Ja",_xlfn.TEXTBEFORE(Tabelle36[[#This Row],[Benennung]],"_")="Fenster"),H26*I26*J26,0)) -> 0 | R26: =IF(AND(_xlfn.TEXTBEFORE(Tabelle36[[#This Row],[Benennung]],"_")="Fenster",$M$12="Nein"),"Nein",IF(AND(_xlfn.TEXTBEFORE(Tabelle36[[#This Row],[Benennung]],"_")="Tür",$R$12="Nein"),"Nein",IF(Tabelle36[[#This Row],[Austausch gewünscht?]]="Ja","Ja",IF(Tabelle36[[#This Row],[Austausch gewünscht?]]="Nein","Nein","")))) -> #N/A | S26: =IF(AND(_xlfn.TEXTBEFORE(Tabelle36[[#This Row],[Benennung]],"_")="Fenster",$N$12="Nein"),"Nein",IF(AND(_xlfn.TEXTBEFORE(Tabelle36[[#This Row],[Benennung]],"_")="Tür",$S$12="Nein"),"Nein",IF(Tabelle36[[#This Row],[Austausch gewünscht?]]="Ja","Ja",IF(Tabelle36[[#This Row],[Austausch gewünscht?]]="Nein","Nein","")))) -> #N/A | T26: =IF(AND(_xlfn.TEXTBEFORE(Tabelle36[[#This Row],[Benennung]],"_")="Fenster",$O$12="Nein"),"Nein",IF(AND(_xlfn.TEXTBEFORE(Tabelle36[[#This Row],[Benennung]],"_")="Tür",$T$12="Nein"),"Nein",IF(Tabelle36[[#This Row],[Austausch gewünscht?]]="Ja","Ja",IF(Tabelle36[[#This Row],[Austausch gewünscht?]]="Nein","Nein","")))) -> #N/A
E27: =IF(D27="","",_xlfn.XLOOKUP(D27,Fassade!$F$10:$F$515,Fassade!$G$10:$G$515,"",0,1)) | K27: =(2*H27+2*I27)*J27 -> 0 | L27: =H27*I27 -> 0 | M27: =PRODUCT(H27*I27*J27) -> 0 | O27: =IF(B27="",0,IF(AND(N27="Ja",_xlfn.TEXTBEFORE(Tabelle36[[#This Row],[Benennung]],"_")="Fenster"),H27*I27*J27,0)) -> 0 | R27: =IF(AND(_xlfn.TEXTBEFORE(Tabelle36[[#This Row],[Benennung]],"_")="Fenster",$M$12="Nein"),"Nein",IF(AND(_xlfn.TEXTBEFORE(Tabelle36[[#This Row],[Benennung]],"_")="Tür",$R$12="Nein"),"Nein",IF(Tabelle36[[#This Row],[Austausch gewünscht?]]="Ja","Ja",IF(Tabelle36[[#This Row],[Austausch gewünscht?]]="Nein","Nein","")))) -> #N/A | S27: =IF(AND(_xlfn.TEXTBEFORE(Tabelle36[[#This Row],[Benennung]],"_")="Fenster",$N$12="Nein"),"Nein",IF(AND(_xlfn.TEXTBEFORE(Tabelle36[[#This Row],[Benennung]],"_")="Tür",$S$12="Nein"),"Nein",IF(Tabelle36[[#This Row],[Austausch gewünscht?]]="Ja","Ja",IF(Tabelle36[[#This Row],[Austausch gewünscht?]]="Nein","Nein","")))) -> #N/A | T27: =IF(AND(_xlfn.TEXTBEFORE(Tabelle36[[#This Row],[Benennung]],"_")="Fenster",$O$12="Nein"),"Nein",IF(AND(_xlfn.TEXTBEFORE(Tabelle36[[#This Row],[Benennung]],"_")="Tür",$T$12="Nein"),"Nein",IF(Tabelle36[[#This Row],[Austausch gewünscht?]]="Ja","Ja",IF(Tabelle36[[#This Row],[Austausch gewünscht?]]="Nein","Nein","")))) -> #N/A
E28: =IF(D28="","",_xlfn.XLOOKUP(D28,Fassade!$F$10:$F$515,Fassade!$G$10:$G$515,"",0,1)) | K28: =(2*H28+2*I28)*J28 -> 0 | L28: =H28*I28 -> 0 | M28: =PRODUCT(H28*I28*J28) -> 0 | O28: =IF(B28="",0,IF(AND(N28="Ja",_xlfn.TEXTBEFORE(Tabelle36[[#This Row],[Benennung]],"_")="Fenster"),H28*I28*J28,0)) -> 0 | R28: =IF(AND(_xlfn.TEXTBEFORE(Tabelle36[[#This Row],[Benennung]],"_")="Fenster",$M$12="Nein"),"Nein",IF(AND(_xlfn.TEXTBEFORE(Tabelle36[[#This Row],[Benennung]],"_")="Tür",$R$12="Nein"),"Nein",IF(Tabelle36[[#This Row],[Austausch gewünscht?]]="Ja","Ja",IF(Tabelle36[[#This Row],[Austausch gewünscht?]]="Nein","Nein","")))) -> #N/A | S28: =IF(AND(_xlfn.TEXTBEFORE(Tabelle36[[#This Row],[Benennung]],"_")="Fenster",$N$12="Nein"),"Nein",IF(AND(_xlfn.TEXTBEFORE(Tabelle36[[#This Row],[Benennung]],"_")="Tür",$S$12="Nein"),"Nein",IF(Tabelle36[[#This Row],[Austausch gewünscht?]]="Ja","Ja",IF(Tabelle36[[#This Row],[Austausch gewünscht?]]="Nein","Nein","")))) -> #N/A | T28: =IF(AND(_xlfn.TEXTBEFORE(Tabelle36[[#This Row],[Benennung]],"_")="Fenster",$O$12="Nein"),"Nein",IF(AND(_xlfn.TEXTBEFORE(Tabelle36[[#This Row],[Benennung]],"_")="Tür",$T$12="Nein"),"Nein",IF(Tabelle36[[#This Row],[Austausch gewünscht?]]="Ja","Ja",IF(Tabelle36[[#This Row],[Austausch gewünscht?]]="Nein","Nein","")))) -> #N/A
E29: =IF(D29="","",_xlfn.XLOOKUP(D29,Fassade!$F$10:$F$515,Fassade!$G$10:$G$515,"",0,1)) | K29: =(2*H29+2*I29)*J29 -> 0 | L29: =H29*I29 -> 0 | M29: =PRODUCT(H29*I29*J29) -> 0 | O29: =IF(B29="",0,IF(AND(N29="Ja",_xlfn.TEXTBEFORE(Tabelle36[[#This Row],[Benennung]],"_")="Fenster"),H29*I29*J29,0)) -> 0 | R29: =IF(AND(_xlfn.TEXTBEFORE(Tabelle36[[#This Row],[Benennung]],"_")="Fenster",$M$12="Nein"),"Nein",IF(AND(_xlfn.TEXTBEFORE(Tabelle36[[#This Row],[Benennung]],"_")="Tür",$R$12="Nein"),"Nein",IF(Tabelle36[[#This Row],[Austausch gewünscht?]]="Ja","Ja",IF(Tabelle36[[#This Row],[Austausch gewünscht?]]="Nein","Nein","")))) -> #N/A | S29: =IF(AND(_xlfn.TEXTBEFORE(Tabelle36[[#This Row],[Benennung]],"_")="Fenster",$N$12="Nein"),"Nein",IF(AND(_xlfn.TEXTBEFORE(Tabelle36[[#This Row],[Benennung]],"_")="Tür",$S$12="Nein"),"Nein",IF(Tabelle36[[#This Row],[Austausch gewünscht?]]="Ja","Ja",IF(Tabelle36[[#This Row],[Austausch gewünscht?]]="Nein","Nein","")))) -> #N/A | T29: =IF(AND(_xlfn.TEXTBEFORE(Tabelle36[[#This Row],[Benennung]],"_")="Fenster",$O$12="Nein"),"Nein",IF(AND(_xlfn.TEXTBEFORE(Tabelle36[[#This Row],[Benennung]],"_")="Tür",$T$12="Nein"),"Nein",IF(Tabelle36[[#This Row],[Austausch gewünscht?]]="Ja","Ja",IF(Tabelle36[[#This Row],[Austausch gewünscht?]]="Nein","Nein","")))) -> #N/A
E30: =IF(D30="","",_xlfn.XLOOKUP(D30,Fassade!$F$10:$F$515,Fassade!$G$10:$G$515,"",0,1)) | K30: =(2*H30+2*I30)*J30 -> 0 | L30: =H30*I30 -> 0 | M30: =PRODUCT(H30*I30*J30) -> 0 | O30: =IF(B30="",0,IF(AND(N30="Ja",_xlfn.TEXTBEFORE(Tabelle36[[#This Row],[Benennung]],"_")="Fenster"),H30*I30*J30,0)) -> 0 | R30: =IF(AND(_xlfn.TEXTBEFORE(Tabelle36[[#This Row],[Benennung]],"_")="Fenster",$M$12="Nein"),"Nein",IF(AND(_xlfn.TEXTBEFORE(Tabelle36[[#This Row],[Benennung]],"_")="Tür",$R$12="Nein"),"Nein",IF(Tabelle36[[#This Row],[Austausch gewünscht?]]="Ja","Ja",IF(Tabelle36[[#This Row],[Austausch gewünscht?]]="Nein","Nein","")))) -> #N/A | S30: =IF(AND(_xlfn.TEXTBEFORE(Tabelle36[[#This Row],[Benennung]],"_")="Fenster",$N$12="Nein"),"Nein",IF(AND(_xlfn.TEXTBEFORE(Tabelle36[[#This Row],[Benennung]],"_")="Tür",$S$12="Nein"),"Nein",IF(Tabelle36[[#This Row],[Austausch gewünscht?]]="Ja","Ja",IF(Tabelle36[[#This Row],[Austausch gewünscht?]]="Nein","Nein","")))) -> #N/A | T30: =IF(AND(_xlfn.TEXTBEFORE(Tabelle36[[#This Row],[Benennung]],"_")="Fenster",$O$12="Nein"),"Nein",IF(AND(_xlfn.TEXTBEFORE(Tabelle36[[#This Row],[Benennung]],"_")="Tür",$T$12="Nein"),"Nein",IF(Tabelle36[[#This Row],[Austausch gewünscht?]]="Ja","Ja",IF(Tabelle36[[#This Row],[Austausch gewünscht?]]="Nein","Nein","")))) -> #N/A
E31: =IF(D31="","",_xlfn.XLOOKUP(D31,Fassade!$F$10:$F$515,Fassade!$G$10:$G$515,"",0,1)) | K31: =(2*H31+2*I31)*J31 -> 0 | L31: =H31*I31 -> 0 | M31: =PRODUCT(H31*I31*J31) -> 0 | O31: =IF(B31="",0,IF(AND(N31="Ja",_xlfn.TEXTBEFORE(Tabelle36[[#This Row],[Benennung]],"_")="Fenster"),H31*I31*J31,0)) -> 0 | R31: =IF(AND(_xlfn.TEXTBEFORE(Tabelle36[[#This Row],[Benennung]],"_")="Fenster",$M$12="Nein"),"Nein",IF(AND(_xlfn.TEXTBEFORE(Tabelle36[[#This Row],[Benennung]],"_")="Tür",$R$12="Nein"),"Nein",IF(Tabelle36[[#This Row],[Austausch gewünscht?]]="Ja","Ja",IF(Tabelle36[[#This Row],[Austausch gewünscht?]]="Nein","Nein","")))) -> #N/A | S31: =IF(AND(_xlfn.TEXTBEFORE(Tabelle36[[#This Row],[Benennung]],"_")="Fenster",$N$12="Nein"),"Nein",IF(AND(_xlfn.TEXTBEFORE(Tabelle36[[#This Row],[Benennung]],"_")="Tür",$S$12="Nein"),"Nein",IF(Tabelle36[[#This Row],[Austausch gewünscht?]]="Ja","Ja",IF(Tabelle36[[#This Row],[Austausch gewünscht?]]="Nein","Nein","")))) -> #N/A | T31: =IF(AND(_xlfn.TEXTBEFORE(Tabelle36[[#This Row],[Benennung]],"_")="Fenster",$O$12="Nein"),"Nein",IF(AND(_xlfn.TEXTBEFORE(Tabelle36[[#This Row],[Benennung]],"_")="Tür",$T$12="Nein"),"Nein",IF(Tabelle36[[#This Row],[Austausch gewünscht?]]="Ja","Ja",IF(Tabelle36[[#This Row],[Austausch gewünscht?]]="Nein","Nein","")))) -> #N/A
E32: =IF(D32="","",_xlfn.XLOOKUP(D32,Fassade!$F$10:$F$515,Fassade!$G$10:$G$515,"",0,1)) | K32: =(2*H32+2*I32)*J32 -> 0 | L32: =H32*I32 -> 0 | M32: =PRODUCT(H32*I32*J32) -> 0 | O32: =IF(B32="",0,IF(AND(N32="Ja",_xlfn.TEXTBEFORE(Tabelle36[[#This Row],[Benennung]],"_")="Fenster"),H32*I32*J32,0)) -> 0 | R32: =IF(AND(_xlfn.TEXTBEFORE(Tabelle36[[#This Row],[Benennung]],"_")="Fenster",$M$12="Nein"),"Nein",IF(AND(_xlfn.TEXTBEFORE(Tabelle36[[#This Row],[Benennung]],"_")="Tür",$R$12="Nein"),"Nein",IF(Tabelle36[[#This Row],[Austausch gewünscht?]]="Ja","Ja",IF(Tabelle36[[#This Row],[Austausch gewünscht?]]="Nein","Nein","")))) -> #N/A | S32: =IF(AND(_xlfn.TEXTBEFORE(Tabelle36[[#This Row],[Benennung]],"_")="Fenster",$N$12="Nein"),"Nein",IF(AND(_xlfn.TEXTBEFORE(Tabelle36[[#This Row],[Benennung]],"_")="Tür",$S$12="Nein"),"Nein",IF(Tabelle36[[#This Row],[Austausch gewünscht?]]="Ja","Ja",IF(Tabelle36[[#This Row],[Austausch gewünscht?]]="Nein","Nein","")))) -> #N/A | T32: =IF(AND(_xlfn.TEXTBEFORE(Tabelle36[[#This Row],[Benennung]],"_")="Fenster",$O$12="Nein"),"Nein",IF(AND(_xlfn.TEXTBEFORE(Tabelle36[[#This Row],[Benennung]],"_")="Tür",$T$12="Nein"),"Nein",IF(Tabelle36[[#This Row],[Austausch gewünscht?]]="Ja","Ja",IF(Tabelle36[[#This Row],[Austausch gewünscht?]]="Nein","Nein","")))) -> #N/A
E33: =IF(D33="","",_xlfn.XLOOKUP(D33,Fassade!$F$10:$F$515,Fassade!$G$10:$G$515,"",0,1)) | K33: =(2*H33+2*I33)*J33 -> 0 | L33: =H33*I33 -> 0 | M33: =PRODUCT(H33*I33*J33) -> 0 | O33: =IF(B33="",0,IF(AND(N33="Ja",_xlfn.TEXTBEFORE(Tabelle36[[#This Row],[Benennung]],"_")="Fenster"),H33*I33*J33,0)) -> 0 | R33: =IF(AND(_xlfn.TEXTBEFORE(Tabelle36[[#This Row],[Benennung]],"_")="Fenster",$M$12="Nein"),"Nein",IF(AND(_xlfn.TEXTBEFORE(Tabelle36[[#This Row],[Benennung]],"_")="Tür",$R$12="Nein"),"Nein",IF(Tabelle36[[#This Row],[Austausch gewünscht?]]="Ja","Ja",IF(Tabelle36[[#This Row],[Austausch gewünscht?]]="Nein","Nein","")))) -> #N/A | S33: =IF(AND(_xlfn.TEXTBEFORE(Tabelle36[[#This Row],[Benennung]],"_")="Fenster",$N$12="Nein"),"Nein",IF(AND(_xlfn.TEXTBEFORE(Tabelle36[[#This Row],[Benennung]],"_")="Tür",$S$12="Nein"),"Nein",IF(Tabelle36[[#This Row],[Austausch gewünscht?]]="Ja","Ja",IF(Tabelle36[[#This Row],[Austausch gewünscht?]]="Nein","Nein","")))) -> #N/A | T33: =IF(AND(_xlfn.TEXTBEFORE(Tabelle36[[#This Row],[Benennung]],"_")="Fenster",$O$12="Nein"),"Nein",IF(AND(_xlfn.TEXTBEFORE(Tabelle36[[#This Row],[Benennung]],"_")="Tür",$T$12="Nein"),"Nein",IF(Tabelle36[[#This Row],[Austausch gewünscht?]]="Ja","Ja",IF(Tabelle36[[#This Row],[Austausch gewünscht?]]="Nein","Nein","")))) -> #N/A
E34: =IF(D34="","",_xlfn.XLOOKUP(D34,Fassade!$F$10:$F$515,Fassade!$G$10:$G$515,"",0,1)) | K34: =(2*H34+2*I34)*J34 -> 0 | L34: =H34*I34 -> 0 | M34: =PRODUCT(H34*I34*J34) -> 0 | O34: =IF(B34="",0,IF(AND(N34="Ja",_xlfn.TEXTBEFORE(Tabelle36[[#This Row],[Benennung]],"_")="Fenster"),H34*I34*J34,0)) -> 0 | R34: =IF(AND(_xlfn.TEXTBEFORE(Tabelle36[[#This Row],[Benennung]],"_")="Fenster",$M$12="Nein"),"Nein",IF(AND(_xlfn.TEXTBEFORE(Tabelle36[[#This Row],[Benennung]],"_")="Tür",$R$12="Nein"),"Nein",IF(Tabelle36[[#This Row],[Austausch gewünscht?]]="Ja","Ja",IF(Tabelle36[[#This Row],[Austausch gewünscht?]]="Nein","Nein","")))) -> #N/A | S34: =IF(AND(_xlfn.TEXTBEFORE(Tabelle36[[#This Row],[Benennung]],"_")="Fenster",$N$12="Nein"),"Nein",IF(AND(_xlfn.TEXTBEFORE(Tabelle36[[#This Row],[Benennung]],"_")="Tür",$S$12="Nein"),"Nein",IF(Tabelle36[[#This Row],[Austausch gewünscht?]]="Ja","Ja",IF(Tabelle36[[#This Row],[Austausch gewünscht?]]="Nein","Nein","")))) -> #N/A | T34: =IF(AND(_xlfn.TEXTBEFORE(Tabelle36[[#This Row],[Benennung]],"_")="Fenster",$O$12="Nein"),"Nein",IF(AND(_xlfn.TEXTBEFORE(Tabelle36[[#This Row],[Benennung]],"_")="Tür",$T$12="Nein"),"Nein",IF(Tabelle36[[#This Row],[Austausch gewünscht?]]="Ja","Ja",IF(Tabelle36[[#This Row],[Austausch gewünscht?]]="Nein","Nein","")))) -> #N/A
E35: =IF(D35="","",_xlfn.XLOOKUP(D35,Fassade!$F$10:$F$515,Fassade!$G$10:$G$515,"",0,1)) | K35: =(2*H35+2*I35)*J35 -> 0 | L35: =H35*I35 -> 0 | M35: =PRODUCT(H35*I35*J35) -> 0 | O35: =IF(B35="",0,IF(AND(N35="Ja",_xlfn.TEXTBEFORE(Tabelle36[[#This Row],[Benennung]],"_")="Fenster"),H35*I35*J35,0)) -> 0 | R35: =IF(AND(_xlfn.TEXTBEFORE(Tabelle36[[#This Row],[Benennung]],"_")="Fenster",$M$12="Nein"),"Nein",IF(AND(_xlfn.TEXTBEFORE(Tabelle36[[#This Row],[Benennung]],"_")="Tür",$R$12="Nein"),"Nein",IF(Tabelle36[[#This Row],[Austausch gewünscht?]]="Ja","Ja",IF(Tabelle36[[#This Row],[Austausch gewünscht?]]="Nein","Nein","")))) -> #N/A | S35: =IF(AND(_xlfn.TEXTBEFORE(Tabelle36[[#This Row],[Benennung]],"_")="Fenster",$N$12="Nein"),"Nein",IF(AND(_xlfn.TEXTBEFORE(Tabelle36[[#This Row],[Benennung]],"_")="Tür",$S$12="Nein"),"Nein",IF(Tabelle36[[#This Row],[Austausch gewünscht?]]="Ja","Ja",IF(Tabelle36[[#This Row],[Austausch gewünscht?]]="Nein","Nein","")))) -> #N/A | T35: =IF(AND(_xlfn.TEXTBEFORE(Tabelle36[[#This Row],[Benennung]],"_")="Fenster",$O$12="Nein"),"Nein",IF(AND(_xlfn.TEXTBEFORE(Tabelle36[[#This Row],[Benennung]],"_")="Tür",$T$12="Nein"),"Nein",IF(Tabelle36[[#This Row],[Austausch gewünscht?]]="Ja","Ja",IF(Tabelle36[[#This Row],[Austausch gewünscht?]]="Nein","Nein","")))) -> #N/A
E36: =IF(D36="","",_xlfn.XLOOKUP(D36,Fassade!$F$10:$F$515,Fassade!$G$10:$G$515,"",0,1)) | K36: =(2*H36+2*I36)*J36 -> 0 | L36: =H36*I36 -> 0 | M36: =PRODUCT(H36*I36*J36) -> 0 | O36: =IF(B36="",0,IF(AND(N36="Ja",_xlfn.TEXTBEFORE(Tabelle36[[#This Row],[Benennung]],"_")="Fenster"),H36*I36*J36,0)) -> 0 | R36: =IF(AND(_xlfn.TEXTBEFORE(Tabelle36[[#This Row],[Benennung]],"_")="Fenster",$M$12="Nein"),"Nein",IF(AND(_xlfn.TEXTBEFORE(Tabelle36[[#This Row],[Benennung]],"_")="Tür",$R$12="Nein"),"Nein",IF(Tabelle36[[#This Row],[Austausch gewünscht?]]="Ja","Ja",IF(Tabelle36[[#This Row],[Austausch gewünscht?]]="Nein","Nein","")))) -> #N/A | S36: =IF(AND(_xlfn.TEXTBEFORE(Tabelle36[[#This Row],[Benennung]],"_")="Fenster",$N$12="Nein"),"Nein",IF(AND(_xlfn.TEXTBEFORE(Tabelle36[[#This Row],[Benennung]],"_")="Tür",$S$12="Nein"),"Nein",IF(Tabelle36[[#This Row],[Austausch gewünscht?]]="Ja","Ja",IF(Tabelle36[[#This Row],[Austausch gewünscht?]]="Nein","Nein","")))) -> #N/A | T36: =IF(AND(_xlfn.TEXTBEFORE(Tabelle36[[#This Row],[Benennung]],"_")="Fenster",$O$12="Nein"),"Nein",IF(AND(_xlfn.TEXTBEFORE(Tabelle36[[#This Row],[Benennung]],"_")="Tür",$T$12="Nein"),"Nein",IF(Tabelle36[[#This Row],[Austausch gewünscht?]]="Ja","Ja",IF(Tabelle36[[#This Row],[Austausch gewünscht?]]="Nein","Nein","")))) -> #N/A
... E74: =IF(D74="","",_xlfn.XLOOKUP(D74,Fassade!$F$10:$F$515,Fassade!$G$10:$G$515,"",0,1)) | K74: =(2*H74+2*I74)*J74 -> 0 | L74: =H74*I74 -> 0 | M74: =PRODUCT(H74*I74*J74) -> 0 | O74: =IF(B74="",0,IF(AND(N74="Ja",_xlfn.TEXTBEFORE(Tabelle36[[#This Row],[Benennung]],"_")="Fenster"),H74*I74*J74,0)) -> 0 | R74: =IF(AND(_xlfn.TEXTBEFORE(Tabelle36[[#This Row],[Benennung]],"_")="Fenster",$M$12="Nein"),"Nein",IF(AND(_xlfn.TEXTBEFORE(Tabelle36[[#This Row],[Benennung]],"_")="Tür",$R$12="Nein"),"Nein",IF(Tabelle36[[#This Row],[Austausch gewünscht?]]="Ja","Ja",IF(Tabelle36[[#This Row],[Austausch gewünscht?]]="Nein","Nein","")))) -> #N/A | S74: =IF(AND(_xlfn.TEXTBEFORE(Tabelle36[[#This Row],[Benennung]],"_")="Fenster",$N$12="Nein"),"Nein",IF(AND(_xlfn.TEXTBEFORE(Tabelle36[[#This Row],[Benennung]],"_")="Tür",$S$12="Nein"),"Nein",IF(Tabelle36[[#This Row],[Austausch gewünscht?]]="Ja","Ja",IF(Tabelle36[[#This Row],[Austausch gewünscht?]]="Nein","Nein","")))) -> #N/A | T74: =IF(AND(_xlfn.TEXTBEFORE(Tabelle36[[#This Row],[Benennung]],"_")="Fenster",$O$12="Nein"),"Nein",IF(AND(_xlfn.TEXTBEFORE(Tabelle36[[#This Row],[Benennung]],"_")="Tür",$T$12="Nein"),"Nein",IF(Tabelle36[[#This Row],[Austausch gewünscht?]]="Ja","Ja",IF(Tabelle36[[#This Row],[Austausch gewünscht?]]="Nein","Nein","")))) -> #N/A
B75: Ergebnis | J75: =SUBTOTAL(109,Tabelle36[Anzahl]) -> 0 | K75: =SUBTOTAL(109,Tabelle36[Umfang '[m']]) -> 0 | M75: =SUBTOTAL(109,Tabelle36[Fläche-G '[m²']]) -> 0 | O75: =SUBTOTAL(109,Tabelle36[Austauschfläche Fenster '[m²']]) -> 0 | R75: =COUNTIF(Tabelle36[Austausch iSFP?],"Ja") -> 0 | S75: =COUNTIF(Tabelle36[Austausch V1?2],"Ja") -> 0 | T75: =COUNTIF(Tabelle36[Austausch V2?2],"Ja") -> 0

Sheet PV
B2: Projektnummer: | C2: =Allgemein!C2 -> 0 | F2: Maßnahmenpaket PV | I2: #VALUE!
B3: Anrede: | C3: =Allgemein!C3 -> 0 | G3: Kurzbeschreibung Maßnahmen
B4: Vorname Nachname: | C4: =Allgemein!C4 -> 0 | F4: Umsetzungsvariante: | G4: =Allgemein!C101 -> 0
B5: Straße, Nr. (Objektadresse): | C5: =Allgemein!C5 -> 0 | F5: Zusatzleistung: | G5: =Allgemein!G101 -> 0
B6: PLZ, Ort: | C6: =Allgemein!C6 -> 0 | F6: Variante 1: | G6: =_xlfn.TEXTJOIN(" ",TRUE,Allgemein!C51,"PV-Anlage","mit",Allgemein!D51,"Speichersystem") -> - PV-Anlage mit - Speichersystem
B7: Email: | C7: =Allgemein!C7 -> 0 | F7: Variante 2: | G7: =_xlfn.TEXTJOIN(" ",TRUE,Allgemein!C67,"PV-Anlage","mit",Allgemein!D67,"Speichersystem") -> - PV-Anlage mit - Speichersystem
B8: Telefon: | C8: =Allgemein!C8 -> 0 | F8: Variante 3: | G8: =_xlfn.TEXTJOIN(" ",TRUE,Allgemein!C83,"PV-Anlage","mit",Allgemein!D83,"Speichersystem") -> - PV-Anlage mit - Speichersystem
B9: Neubau Photovoltaikanlage:
B10: Bestand | H10: Wunsch/Anmerkung
B11: Anlagenmontage | F11: AC-Leitungsverlegung | H11: Allgemein
B12: Traufhöhe: | D12: Gerüst auf öffentlichem Weg oder Behinderung Dritter?: | F12: Kabelweg Zählerschrank und Wechselrichter: | H12: Wunsch nach bestimmter Anlagengröße: | J12: Anlagengröße [kWp]:
F13: Länge Zählerschrank - Wechselrichter: | H13: Wunsch nach bestimmter Speichergröße: | J13: Speichergröße [kWh]:
B14: Störquellen Gerüst: | D14: Verschattungsquellen: | F14: Internetanschluss im Installationsraum?: | H14: Zusatzoptionen:
B15: Störquellen Dach: | D15: Beschreibung Verschattung: | H15: Anlagenerweiterung geplant? | J15: Notstrom gewünscht?:
D16: geschätzte Höhe Verschattung [m]: | H16: EMMA gewünscht? | J16: Optimierer gewünscht?:
J17: SolarEdge oder Huawei?
B18: DC-Kabelverlegung | D18: DC-Zusatz | F18: Ausstattung | H18: Wallbox
B19: Kabelführung: | D19: Anmerkung: | F19: Wallbox vorhanden?: | H19: Installation Wallbox gewünscht?: | J19: Abstand Wallbox zum Zählerschrank:
B20: PV-Module und Anlagentechnik auf dem selben Gebäude?: | D20: Gerüstaufbau bei Traufhöhe > 4m: | E20: =IF(C12="Über 4 m","Ja","Nein") -> Nein
B21: Länge der DC-Kabelführung: | D21: Aufständerung benötigt?: | E21: =IF(Dach!C12="Flachdach","Ja","Nein") -> Nein | F21: E-Auto vorhanden?: | H21: E-Auto geplant?:
B23: Installationsumgebung | F23: Beschreibung Wallbox:
B24: HAR/HWR für Anlagenkomponenten vorhanden?: | D24: Wenn Nein, wo sonst?:
B25: Temperaturbereich sichergestellt?: | D25: Wenn Nein, Unterschrift Kunden: | F25: Ungefähre Fahrleistung [km/a]:
B26: Mindestabstände Anlagenkomponenten eingehalten?:

Sheet Dach
B2: Projektnummer: | C2: =Allgemein!C2 -> 0 | F2: Maßnahmenpaket Dach | J2: #VALUE!
B3: Anrede: | C3: =Allgemein!C3 -> 0 | G3: Kurzbeschreibung Maßnahmen
B4: Vorname Nachname: | C4: =Allgemein!C4 -> 0 | F4: Umsetzungsvariante: | G4: =Allgemein!C94 -> 0
B5: Straße, Nr. (Objektadresse): | C5: =Allgemein!C5 -> 0 | F5: Zusatzleistung: | G5: =Allgemein!G94 -> 0
B6: PLZ, Ort: | C6: =Allgemein!C6 -> 0 | F6: Variante 1: | G6: =Allgemein!C44 -> -
B7: Email: | C7: =Allgemein!C7 -> 0 | F7: Variante 2: | G7: =Allgemein!C60 -> -
B8: Telefon: | C8: =Allgemein!C8 -> 0 | F8: Variante 3: | G8: =Allgemein!C76 -> -
B9: Allgemeines zum Dach:
B10: Bestand | F10: Wunsch/Anmerkung | H10: Umsetzung | I10: iSFP | J10: Variante 1 | K10: Variante 2
B11: Dachbenennung: | D11: Dachfläche [m²]: | E11: =_xlfn.XLOOKUP(C15,Datenbank!CC118:CC188,Datenbank!CD118:CD188,0,1,1)*(Allgemein!C19+SQRT(Allgemein!C19)*4*Dach!C17/100) -> 0 | F11: Anmerkungen Dach: | H11: Dacheindeckung: | I11: {=_xlfn.XLOOKUP(Dach!H11&Allgemein!C44,Dachpositionen[[#Headers],[Dacheindeckung:]]&Dachpositionen[Position Dach],Dachpositionen[Dacheindeckung:],"",0,1)} -> Nein | J11: {=_xlfn.XLOOKUP(Dach!H11&Allgemein!C60,Dachpositionen[[#Headers],[Dacheindeckung:]]&Dachpositionen[Position Dach],Dachpositionen[Dacheindeckung:],"",0,1)} -> Nein | K11: {=_xlfn.XLOOKUP(Dach!H11&Allgemein!C76,Dachpositionen[[#Headers],[Dacheindeckung:]]&Dachpositionen[Position Dach],Dachpositionen[Dacheindeckung:],"",0,1)} -> Nein
B12: Dachform: | H12: Fläche: | I12: =E11 -> 0 | J12: =E11 -> 0 | K12: =E11 -> 0
B13: aktuelle Nutzung Dachboden: | H13: Bemerkung:
B14: Dachneigung [°]: | H14: Dämmung Dachschrägen: | I14: {=_xlfn.XLOOKUP(Dach!H14&Allgemein!C44,Dachpositionen[[#Headers],[Dämmung Dachschrägen:]]&Dachpositionen[Position Dach],Dachpositionen[Dämmung Dachschrägen:],"",0,1)} -> Nein | J14: {=_xlfn.XLOOKUP(Dach!H14&Allgemein!C60,Dachpositionen[[#Headers],[Dämmung Dachschrägen:]]&Dachpositionen[Position Dach],Dachpositionen[Dämmung Dachschrägen:],"",0,1)} -> Nein | K14: {=_xlfn.XLOOKUP(Dach!H14&Allgemein!C76,Dachpositionen[[#Headers],[Dämmung Dachschrägen:]]&Dachpositionen[Position Dach],Dachpositionen[Dämmung Dachschrägen:],"",0,1)} -> Nein
H15: Bis in Dachspitz?
B16: Dachüberstand [cm]: | H16: Fläche zu Dämmen [m²]: | I16: =E11 -> 0 | J16: =E11 -> 0 | K16: =E11 -> 0
F17: Geplante Nutzung Dachboden: | H17: Stärke/Material | I17: =Allgemein!D44 -> - | J17: =Allgemein!D60 -> - | K17: =Allgemein!D76 -> -
B18: Dacheindeckung: | H18: Bemerkung:
B19: Dacheindeckung: | D19: Dachziegel oder Dachpfanne | F19: Erneuerung gewünscht?: | H19: Trockenbau innen: | I19: {=_xlfn.XLOOKUP(Dach!H19&Allgemein!C44,Dachpositionen[[#Headers],[Trockenbau innen:]]&Dachpositionen[Position Dach],Dachpositionen[Trockenbau innen:],"",0,1)} -> Nein | J19: {=_xlfn.XLOOKUP(Dach!H19&Allgemein!C60,Dachpositionen[[#Headers],[Trockenbau innen:]]&Dachpositionen[Position Dach],Dachpositionen[Trockenbau innen:],"",0,1)} -> Nein | K19: {=_xlfn.XLOOKUP(Dach!H19&Allgemein!C76,Dachpositionen[[#Headers],[Trockenbau innen:]]&Dachpositionen[Position Dach],Dachpositionen[Trockenbau innen:],"",0,1)} -> Nein
D20: Höhe [cm]: | F20: Beschreibung Nutzung Dachboden: | H20: Fläche [m²]: | I20: =I16 -> 0 | J20: =J16 -> 0 | K20: =K16 -> 0
B21: Baujahr Dacheindeckung: | D21: Breite [cm]: | H21: Bemerkung:
D22: Überdeckungsmaß [cm]: | H22: Dämmung obere Geschossdecke: | I22: {=_xlfn.XLOOKUP(Dach!H22&Allgemein!C44,Dachpositionen[[#Headers],[Dämmung obere Geschossdecke:]]&Dachpositionen[Position Dach],Dachpositionen[Dämmung obere Geschossdecke:],"",0,1)} -> Nein | J22: {=_xlfn.XLOOKUP(Dach!H22&Allgemein!C60,Dachpositionen[[#Headers],[Dämmung obere Geschossdecke:]]&Dachpositionen[Position Dach],Dachpositionen[Dämmung obere Geschossdecke:],"",0,1)} -> Nein | K22: {=_xlfn.XLOOKUP(Dach!H22&Allgemein!C76,Dachpositionen[[#Headers],[Dämmung obere Geschossdecke:]]&Dachpositionen[Position Dach],Dachpositionen[Dämmung obere Geschossdecke:],"",0,1)} -> Nein
B23: Gibt es Störquellen auf dem Dach? | D23: Verlegungsart: | H23: Fläche [m²]: | I23: =E36 -> 0 | J23: =E36 -> 0 | K23: =E36 -> 0
D24: Anzahl Dachziegel vorhanden: | H24: Stärke/Material | I24: =Allgemein!D44 -> - | J24: =Allgemein!D60 -> - | K24: =Allgemein!D76 -> -
D25: Blech oder Trapezblech | H25: Bemerkung:
D26: Material: | H26: Dachstuhl Neu komplett: | I26: {=_xlfn.XLOOKUP(Dach!H26&Allgemein!C44,Dachpositionen[[#Headers],[Dachstuhl Neu komplett:]]&Dachpositionen[Position Dach],Dachpositionen[Dachstuhl Neu komplett:],"",0,1)} -> Nein | J26: {=_xlfn.XLOOKUP(Dach!H26&Allgemein!C60,Dachpositionen[[#Headers],[Dachstuhl Neu komplett:]]&Dachpositionen[Position Dach],Dachpositionen[Dachstuhl Neu komplett:],"",0,1)} -> Nein | K26: {=_xlfn.XLOOKUP(Dach!H26&Allgemein!C76,Dachpositionen[[#Headers],[Dachstuhl Neu komplett:]]&Dachpositionen[Position Dach],Dachpositionen[Dachstuhl Neu komplett:],"",0,1)} -> Nein
D27: Stärke [mm]: | H27: Fläche [m²]: | I27: =E11 -> 0 | J27: =E11 -> 0 | K27: =E11 -> 0
B28: Dachdämmung Schrägen | H28: Bemerkung:
B29: Material: | D29: Dämmungsmethode: | H29: Gauben:
B30: Dämmstärke [cm]: | H30: Anzahl vor Sanierung: | I30: =IF(C48="---",0,C48) -> 0 | J30: =IF(C48="---",0,C48) -> 0 | K30: =IF(C48="---",0,C48) -> 0
B31: Einbaujahr: | H31: Anzahl nach Sanierung: | I31: =I30 -> 0 | J31: =J30 -> 0 | K31: =K30 -> 0
H32: Bemerkung:
H33: Dachflächenfenster:
H34: Anzahl vor Sanierung: | I34: =SUM(G55,G59,G63,G67,G71,G75) -> 0 | J34: =SUM(G55,G59,G63,G67,G71,G75) -> 0 | K34: =SUM(G55,G59,G63,G67,G71,G75) -> 0
B35: Oberste Geschossdecke | H35: Anzahl Austausch: | I35: =IF(G56="Ja",G55,0)+IF(G60="Ja",G59,0)+IF(G64="Ja",G63,0)+IF(G68="Ja",G67,0)+IF(G72="Ja",G71,0)+IF(G76="Ja",G75,0) -> 0 | J35: =IF(G56="Ja",G55,0)+IF(G60="Ja",G59,0)+IF(G64="Ja",G63,0)+IF(G68="Ja",G67,0)+IF(G72="Ja",G71,0)+IF(G76="Ja",G75,0) -> 0 | K35: =IF(G56="Ja",G55,0)+IF(G60="Ja",G59,0)+IF(G64="Ja",G63,0)+IF(G68="Ja",G67,0)+IF(G72="Ja",G71,0)+IF(G76="Ja",G75,0) -> 0
B36: Bauweise: | D36: Fläche [m²]: | E36: =Allgemein!C19 -> 0 | H36: Anzahl Zusatz Neu: | I36: 0 | J36: 0 | K36: 0
B37: Material: | H37: Anzahl nach Sanierung: | I37: =I34+I36 -> 0 | J37: =J34+J36 -> 0 | K37: =K34+K36 -> 0
B38: Dämmstärke [cm]: | H38: Art:
B39: Einbaujahr: | H39: Bemerkung;
H40: Bemerkung Allgemein
B41: Zugang zum Dachboden:
B42: Länge Bodenklapptreppe [cm]:
B43: Breite Bodenklapptreppe [cm]:
B44: Dachkonstruktion:
B45: Material: | D45: Sparrenbreite [cm]:
B46: Kniestock [cm]: | D46: Sparrenhöhe [cm]:
D47: lichter Sparrenabstand [cm]:
B48: Gauben Anzahl:
B49: Gaube_1 | C49: Beschreibung: | F49: Ausrichtung:
B50: Gaube_2 | C50: Beschreibung: | F50: Ausrichtung:
B51: Gaube_3 | C51: Beschreibung: | F51: Ausrichtung:
B52: Gaube_4 | C52: Beschreibung: | F52: Ausrichtung:
B53: Gaube_5 | C53: Beschreibung: | F53: Ausrichtung:
B54: Dachflächenfenster
B55: Dachflächenfenster: | D55: Breite [m]: | F55: Anzahl
B56: Einbaujahr: | D56: Höhe [m]: | F56: Austausch?
B57: Material: | D57: Verglasung: | F57: Rolladen neu?
B58: U-Wert [W/(m²K)]: | D58: Rolladen: | F58: Bemerkung/Wunsch
B59: Dachflächenfenster: | D59: Breite [m]: | F59: Anzahl
B60: Einbaujahr: | D60: Höhe [m]: | F60: Austausch?
B61: Material: | D61: Verglasung: | F61: Rolladen neu?
B62: U-Wert [W/(m²K)]: | D62: Rolladen: | F62: Bemerkung/Wunsch
B63: Dachflächenfenster: | D63: Breite [m]: | F63: Anzahl
B64: Einbaujahr: | D64: Höhe [m]: | F64: Austausch?
B65: Material: | D65: Verglasung: | F65: Rolladen neu?
B66: U-Wert [W/(m²K)]: | D66: Rolladen: | F66: Bemerkung/Wunsch
... B78: U-Wert [W/(m²K)]: | D78: Rolladen: | F78: Bemerkung/Wunsch
B79: Photovoltaik
B80: Baujahr: | D80: Anlagengröße [kWp]: | F80: Beschreibung:
D81: Speichergröße [kWh]:
B84: Solarthermie
B85: Baujahr: | F85: Beschreibung:

Sheet weiteres Dach
B2: Projektnummer: | C2: =Allgemein!C2 -> 0 | F2: Maßnahmenpaket Dach | J2: #VALUE!
B3: Anrede: | C3: =Allgemein!C3 -> 0 | G3: Kurzbeschreibung Maßnahmen
B4: Vorname Nachname: | C4: =Allgemein!C4 -> 0 | F4: Umsetzungsvariante: | G4: =Allgemein!C94 -> 0
B5: Straße, Nr. (Objektadresse): | C5: =Allgemein!C5 -> 0 | F5: Zusatzleistung: | G5: =Allgemein!G94 -> 0
B6: PLZ, Ort: | C6: =Allgemein!C6 -> 0 | F6: Variante 1: | G6: =Allgemein!C44 -> -
B7: Email: | C7: =Allgemein!C7 -> 0 | F7: Variante 2: | G7: =Allgemein!C60 -> -
B8: Telefon: | C8: =Allgemein!C8 -> 0 | F8: Variante 3: | G8: =Allgemein!C76 -> -
B9: Allgemeines zum Dach:
B10: Bestand | F10: Wunsch/Anmerkung | H10: Umsetzung | I10: iSFP | J10: Variante 1 | K10: Variante 2
B11: Dachbenennung: | D11: Dachfläche [m²]: | E11: =_xlfn.XLOOKUP(C15,Datenbank!CC118:CC188,Datenbank!CD118:CD188,0,1,1)*(Allgemein!C19+SQRT(Allgemein!C19)*4*'weiteres Dach'!C17/100) -> 0 | F11: Anmerkungen Dach: | H11: Dacheindeckung: | I11: {=_xlfn.XLOOKUP('weiteres Dach'!H11&Allgemein!C44,Dachpositionen[[#Headers],[Dacheindeckung:]]&Dachpositionen[Position Dach],Dachpositionen[Dacheindeckung:],"",0,1)} -> Nein | J11: {=_xlfn.XLOOKUP('weiteres Dach'!H11&Allgemein!C60,Dachpositionen[[#Headers],[Dacheindeckung:]]&Dachpositionen[Position Dach],Dachpositionen[Dacheindeckung:],"",0,1)} -> Nein | K11: {=_xlfn.XLOOKUP('weiteres Dach'!H11&Allgemein!C76,Dachpositionen[[#Headers],[Dacheindeckung:]]&Dachpositionen[Position Dach],Dachpositionen[Dacheindeckung:],"",0,1)} -> Nein
B12: Dachform: | H12: Fläche: | I12: =E11 -> 0 | J12: =E11 -> 0 | K12: =E11 -> 0
B13: aktuelle Nutzung Dachboden: | H13: Bemerkung:
B14: Dachneigung [°]: | H14: Dämmung Dachschrägen: | I14: {=_xlfn.XLOOKUP('weiteres Dach'!H14&Allgemein!C44,Dachpositionen[[#Headers],[Dämmung Dachschrägen:]]&Dachpositionen[Position Dach],Dachpositionen[Dämmung Dachschrägen:],"",0,1)} -> Nein | J14: {=_xlfn.XLOOKUP('weiteres Dach'!H14&Allgemein!C60,Dachpositionen[[#Headers],[Dämmung Dachschrägen:]]&Dachpositionen[Position Dach],Dachpositionen[Dämmung Dachschrägen:],"",0,1)} -> Nein | K14: {=_xlfn.XLOOKUP('weiteres Dach'!H14&Allgemein!C76,Dachpositionen[[#Headers],[Dämmung Dachschrägen:]]&Dachpositionen[Position Dach],Dachpositionen[Dämmung Dachschrägen:],"",0,1)} -> Nein
H15: Bis in Dachspitz?
B16: Dachüberstand [cm]: | H16: Fläche zu Dämmen [m²]: | I16: =E11 -> 0 | J16: =E11 -> 0 | K16: =E11 -> 0
F17: Geplante Nutzung Dachboden: | H17: Stärke/Material | I17: =Allgemein!D44 -> - | J17: =Allgemein!D60 -> - | K17: =Allgemein!D76 -> -
B18: Dacheindeckung: | H18: Bemerkung:
B19: Dacheindeckung: | D19: Dachziegel oder Dachpfanne | F19: Erneuerung gewünscht?: | H19: Trockenbau innen: | I19: {=_xlfn.XLOOKUP('weiteres Dach'!H19&Allgemein!C44,Dachpositionen[[#Headers],[Trockenbau innen:]]&Dachpositionen[Position Dach],Dachpositionen[Trockenbau innen:],"",0,1)} -> Nein | J19: {=_xlfn.XLOOKUP('weiteres Dach'!H19&Allgemein!C60,Dachpositionen[[#Headers],[Trockenbau innen:]]&Dachpositionen[Position Dach],Dachpositionen[Trockenbau innen:],"",0,1)} -> Nein | K19: {=_xlfn.XLOOKUP('weiteres Dach'!H19&Allgemein!C76,Dachpositionen[[#Headers],[Trockenbau innen:]]&Dachpositionen[Position Dach],Dachpositionen[Trockenbau innen:],"",0,1)} -> Nein
D20: Höhe [cm]: | H20: Fläche [m²]: | I20: =I16 -> 0 | J20: =J16 -> 0 | K20: =K16 -> 0
B21: Baujahr Dacheindeckung: | D21: Breite [cm]: | H21: Bemerkung:
D22: Überdeckungsmaß [cm]: | H22: Dämmung obere Geschossdecke: | I22: {=_xlfn.XLOOKUP('weiteres Dach'!H22&Allgemein!C44,Dachpositionen[[#Headers],[Dämmung obere Geschossdecke:]]&Dachpositionen[Position Dach],Dachpositionen[Dämmung obere Geschossdecke:],"",0,1)} -> Nein | J22: {=_xlfn.XLOOKUP('weiteres Dach'!H22&Allgemein!C60,Dachpositionen[[#Headers],[Dämmung obere Geschossdecke:]]&Dachpositionen[Position Dach],Dachpositionen[Dämmung obere Geschossdecke:],"",0,1)} -> Nein | K22: {=_xlfn.XLOOKUP('weiteres Dach'!H22&Allgemein!C76,Dachpositionen[[#Headers],[Dämmung obere Geschossdecke:]]&Dachpositionen[Position Dach],Dachpositionen[Dämmung obere Geschossdecke:],"",0,1)} -> Nein
B23: Gibt es Störquellen auf dem Dach?: | D23: Verlegungsart: | H23: Fläche [m²]: | I23: =E36 -> 0 | J23: =E36 -> 0 | K23: =E36 -> 0
D24: Anzahl Dachziegel vorhanden: | H24: Stärke/Material | I24: =Allgemein!D44 -> - | J24: =Allgemein!D60 -> - | K24: =Allgemein!D76 -> -
D25: Blech oder Trapezblech | H25: Bemerkung:
D26: Material: | H26: Dachstuhl Neu komplett: | I26: {=_xlfn.XLOOKUP('weiteres Dach'!H26&Allgemein!C44,Dachpositionen[[#Headers],[Dachstuhl Neu komplett:]]&Dachpositionen[Position Dach],Dachpositionen[Dachstuhl Neu komplett:],"",0,1)} -> Nein | J26: {=_xlfn.XLOOKUP('weiteres Dach'!H26&Allgemein!C60,Dachpositionen[[#Headers],[Dachstuhl Neu komplett:]]&Dachpositionen[Position Dach],Dachpositionen[Dachstuhl Neu komplett:],"",0,1)} -> Nein | K26: {=_xlfn.XLOOKUP('weiteres Dach'!H26&Allgemein!C76,Dachpositionen[[#Headers],[Dachstuhl Neu komplett:]]&Dachpositionen[Position Dach],Dachpositionen[Dachstuhl Neu komplett:],"",0,1)} -> Nein
D27: Stärke [mm]: | H27: Fläche [m²]: | I27: =E11 -> 0 | J27: =E11 -> 0 | K27: =E11 -> 0
B28: Dachdämmung Schrägen | H28: Bemerkung:
B29: Material: | D29: Dämmungsmethode: | H29: Gauben:
B30: Dämmstärke [cm]: | H30: Anzahl vor Sanierung: | I30: =C48 -> 0 | J30: =C48 -> 0 | K30: =C48 -> 0
B31: Einbaujahr: | H31: Anzahl nach Sanierung: | I31: =I30 -> 0 | J31: =J30 -> 0 | K31: =K30 -> 0
H32: Bemerkung:
H33: Dachflächenfenster:
H34: Anzahl vor Sanierung: | I34: =SUM(G55,G59,G63,G67,G71,G75) -> 0 | J34: =SUM(G55,G59,G63,G67,G71,G75) -> 0 | K34: =SUM(G55,G59,G63,G67,G71,G75) -> 0
B35: Oberste Geschossdecke | H35: Anzahl Austausch: | I35: =IF(G56="Ja",G55,0)+IF(G60="Ja",G59,0)+IF(G64="Ja",G63,0)+IF(G68="Ja",G67,0)+IF(G72="Ja",G71,0)+IF(G76="Ja",G75,0) -> 0 | J35: =IF(G56="Ja",G55,0)+IF(G60="Ja",G59,0)+IF(G64="Ja",G63,0)+IF(G68="Ja",G67,0)+IF(G72="Ja",G71,0)+IF(G76="Ja",G75,0) -> 0 | K35: =IF(G56="Ja",G55,0)+IF(G60="Ja",G59,0)+IF(G64="Ja",G63,0)+IF(G68="Ja",G67,0)+IF(G72="Ja",G71,0)+IF(G76="Ja",G75,0) -> 0
B36: Bauweise: | D36: Fläche [m²]: | E36: =Allgemein!C19 -> 0 | H36: Anzahl Zusatz Neu: | I36: 0 | J36: 0 | K36: 0
B37: Material: | H37: Anzahl nach Sanierung: | I37: =I34+I36 -> 0 | J37: =J34+J36 -> 0 | K37: =K34+K36 -> 0
B38: Dämmstärke [cm]: | H38: Art:
B39: Einbaujahr: | H39: Bemerkung;
H40: Bemerkung Allgemein
B41: Zugang zum Dachboden:
B42: Länge Bodenklapptreppe [cm]:
B43: Breite Bodenklapptreppe [cm]:
B44: Dachkonstruktion:
B45: Material: | D45: Sparrenbreite [cm]:
B46: Kniestock [cm]: | D46: Sparrenhöhe [cm]:
D47: lichter Sparrenabstand [cm]:
B48: Gauben Anzahl:
B49: Gaube_1 | C49: Beschreibung: | F49: Ausrichtung:
B50: Gaube_2 | C50: Beschreibung: | F50: Ausrichtung:
B51: Gaube_3 | C51: Beschreibung: | F51: Ausrichtung:
B52: Gaube_4 | C52: Beschreibung: | F52: Ausrichtung:
B53: Gaube_5 | C53: Beschreibung: | F53: Ausrichtung:
B54: Dachflächenfenster
B55: Dachflächenfenster: | D55: Breite [m]: | F55: Anzahl
B56: Einbaujahr: | D56: Höhe [m]: | F56: Austausch?
B57: Material: | D57: Verglasung: | F57: Rolladen neu?
B58: U-Wert [W/(m²K)]: | D58: Rolladen: | F58: Bemerkung/Wunsch
B59: Dachflächenfenster: | D59: Breite [m]: | F59: Anzahl
B60: Einbaujahr: | D60: Höhe [m]: | F60: Austausch?
B61: Material: | D61: Verglasung: | F61: Rolladen neu?
B62: U-Wert [W/(m²K)]: | D62: Rolladen: | F62: Bemerkung/Wunsch
B63: Dachflächenfenster: | D63: Breite [m]: | F63: Anzahl
B64: Einbaujahr: | D64: Höhe [m]: | F64: Austausch?
B65: Material: | D65: Verglasung: | F65: Rolladen neu?
B66: U-Wert [W/(m²K)]: | D66: Rolladen: | F66: Bemerkung/Wunsch
... B78: U-Wert [W/(m²K)]: | D78: Rolladen: | F78: Bemerkung/Wunsch
B79: Photovoltaik
B80: Baujahr: | D80: Anlagengröße [kWp]: | F80: Beschreibung:
D81: Speichergröße [kWh]:
B84: Solarthermie
B85: Baujahr: | F85: Beschreibung:

Sheet Boden u. Keller
B2: Projektnummer: | C2: =Allgemein!C2 -> 0 | D2: Boden u. Keller | H2: #VALUE!
B3: Anrede: | C3: =Allgemein!C3 -> 0 | E3: Kurzbeschreibung Maßnahmen
B4: Vorname Nachname: | C4: =Allgemein!C4 -> 0 | D4: Umsetzungsvariante: | E4: =Allgemein!C97 -> 0
B5: Straße, Nr. (Objektadresse): | C5: =Allgemein!C5 -> 0 | D5: Zusatzleistung: | E5: =Allgemein!G97 -> 0
B6: PLZ, Ort: | C6: =Allgemein!C6 -> 0 | D6: Variante 1: | E6: =Allgemein!C47 -> -
B7: Email: | C7: =Allgemein!C7 -> 0 | D7: Variante 2 | E7: =Allgemein!C63 -> -
B8: Telefon: | C8: =Allgemein!C8 -> 0 | D8: Variante 3: | E8: =Allgemein!C79 -> -
B9: Keller
B10: Bestand | D10: Wunsch/Anmerkung | F10: Umsetzung | G10: iSFP | H10: Variante 1 | I10: Variante 2
B11: Keller | D11: geplante Kellernutzung: | F11: Kellerdeckendämmung: | G11: {=_xlfn.XLOOKUP(F11&Allgemein!C47,Tabelle2529[[#Headers],[Kellerdeckendämmung:]]&Tabelle2529[Position Keller],Tabelle2529[Kellerdeckendämmung:],"",0,1)} -> Nein | H11: {=_xlfn.XLOOKUP(F11&Allgemein!C63,Tabelle2529[[#Headers],[Kellerdeckendämmung:]]&Tabelle2529[Position Keller],Tabelle2529[Kellerdeckendämmung:],"",0,1)} -> Nein | I11: {=_xlfn.XLOOKUP(F11&Allgemein!C79,Tabelle2529[[#Headers],[Kellerdeckendämmung:]]&Tabelle2529[Position Keller],Tabelle2529[Kellerdeckendämmung:],"",0,1)} -> Nein
B12: Kellertyp: | F12: zu dämmende Fläche [m²]: | G12: =IF(G11="Ja",E13,0) -> 0 | H12: =IF(H11="Ja",E13,0) -> 0 | I12: =IF(I11="Ja",E13,0) -> 0
B13: vorhandene Kellernutzung: | D13: Kellerdeckenfläche (ohne AW) [m²]: | E13: =Allgemein!C19 -> 0 | F13: Stärke/Material | G13: =Allgemein!D47 -> - | H13: =Allgemein!D63 -> - | I13: =Allgemein!D79 -> -
B14: Einbautiefe des Kellers [m]: (Abstand UK Kellerdecke bis OK Gelände) | D14: Gebäudeumfang [m]: | E14: =Allgemein!E19*2+Allgemein!E20*2 -> 0 | F14: Dämmung des Fußbodens: | G14: {=_xlfn.XLOOKUP(F14&Allgemein!C47,Tabelle2529[[#Headers],[Dämmung des Fußbodens:]]&Tabelle2529[Position Keller],Tabelle2529[Dämmung des Fußbodens:],"",0,1)} -> Nein | H14: {=_xlfn.XLOOKUP(F14&Allgemein!C63,Tabelle2529[[#Headers],[Dämmung des Fußbodens:]]&Tabelle2529[Position Keller],Tabelle2529[Dämmung des Fußbodens:],"",0,1)} -> Nein | I14: {=_xlfn.XLOOKUP(F14&Allgemein!C79,Tabelle2529[[#Headers],[Dämmung des Fußbodens:]]&Tabelle2529[Position Keller],Tabelle2529[Dämmung des Fußbodens:],"",0,1)} -> Nein
D15: Kelleraußenfläche [m²]: | F15: zu dämmende Fläche [m²]: | G15: =IF(G14="Ja",E13,0) -> 0 | H15: =IF(H14="Ja",E13,0) -> 0 | I15: =IF(I14="Ja",E13,0) -> 0
B16: Höhe des Keller [m]: | D16: Kellerinnenfläche [m²]: | F16: Stärke/Material | G16: =Allgemein!D47 -> - | H16: =Allgemein!D63 -> - | I16: =Allgemein!D79 -> -
D17: Beschreibung Kellernutzung: | F17: Einblasdämmung: | G17: {=_xlfn.XLOOKUP(F17&Allgemein!C47,Tabelle2529[[#Headers],[Einblasdämmung:]]&Tabelle2529[Position Keller],Tabelle2529[Einblasdämmung:],"",0,1)} -> Nein | H17: {=_xlfn.XLOOKUP(F17&Allgemein!C63,Tabelle2529[[#Headers],[Einblasdämmung:]]&Tabelle2529[Position Keller],Tabelle2529[Einblasdämmung:],"",0,1)} -> Nein | I17: {=_xlfn.XLOOKUP(F17&Allgemein!C79,Tabelle2529[[#Headers],[Einblasdämmung:]]&Tabelle2529[Position Keller],Tabelle2529[Einblasdämmung:],"",0,1)} -> Nein
B18: Höhe über Türsturz/Fenstersturz bis Decke (kleinster Wert maßgebend) [cm]: | F18: zu dämmende Fläche [m²]: | G18: =IF(G17="Ja",E13,0) -> 0 | H18: =IF(H17="Ja",E13,0) -> 0 | I18: =IF(I17="Ja",E13,0) -> 0
B19: Kellerdecke | F19: Stärke/Material (bitte manuell eingeben)
B20: Deckentyp | F20: Dämmung Kelleraußenwand: | G20: =_xlfn.XLOOKUP(Allgemein!$C$48,'Datenbank-Preise'!B74:B79,'Datenbank-Preise'!D74:D79,"Nein",0,1) -> Nein | H20: =_xlfn.XLOOKUP(Allgemein!$C$64,'Datenbank-Preise'!B74:B79,'Datenbank-Preise'!D74:D79,"Nein",0,1) -> Nein | I20: =_xlfn.XLOOKUP(Allgemein!$C$80,'Datenbank-Preise'!B74:B79,'Datenbank-Preise'!D74:D79,"Nein",0,1) -> Nein
B21: Beschreibung Decke | F21: zu dämmende Fläche [m²]: | G21: =IF(G20="Ja",$E$15,0) -> 0 | H21: =IF(H20="Ja",$E$15,0) -> 0 | I21: =IF(I20="Ja",$E$15,0) -> 0
B22: Besonderheiten Decke | F22: Stärke/Material (bitte manuell eingeben)
B23: Fußbodenaufbau EG | F23: Dämmung Kellerinnenwand: | G23: =_xlfn.XLOOKUP(Allgemein!$C$48,'Datenbank-Preise'!B74:B79,'Datenbank-Preise'!C74:C79,"Nein",0,1) -> Nein | H23: =_xlfn.XLOOKUP(Allgemein!$C$64,'Datenbank-Preise'!B74:B79,'Datenbank-Preise'!C74:C79,"Nein",0,1) -> Nein | I23: =_xlfn.XLOOKUP(Allgemein!$C$80,'Datenbank-Preise'!B74:B79,'Datenbank-Preise'!C74:C79,"Nein",0,1) -> Nein
B24: Beschreibung Fußbodenaufbau | D24: Einblasen von Dämmung mgl.?: | F24: zu dämmende Fläche [m²]: | G24: =IF(G23="Ja",$E$16,0) -> 0 | H24: =IF(H23="Ja",$E$16,0) -> 0 | I24: =IF(I23="Ja",$E$16,0) -> 0
B25: Gründung | F25: Stärke/Material (bitte manuell eingeben)
B26: Gründungsart: | F26: Ausschachten: | G26: =_xlfn.XLOOKUP(Allgemein!$C$48,'Datenbank-Preise'!B74:B79,'Datenbank-Preise'!E74:E79,"Nein",0,1) -> Nein | H26: =_xlfn.XLOOKUP(Allgemein!$C$64,'Datenbank-Preise'!B74:B79,'Datenbank-Preise'!E74:E79,"Nein",0,1) -> Nein | I26: =_xlfn.XLOOKUP(Allgemein!$C$80,'Datenbank-Preise'!B74:B79,'Datenbank-Preise'!E74:E79,"Nein",0,1) -> Nein
B27: Besonderheiten der Gründung: | F27: Fläche [m²]: | G27: =IF(G26="Ja",$E$15,0) -> 0 | H27: =IF(H26="Ja",$E$15,0) -> 0 | I27: =IF(I26="Ja",$E$15,0) -> 0
B28: Feuchtigkeit Keller | F28: Bemerkung:
B29: Horizontalsperre vorhanden?: | F29: Horizontalsperre: | G29: =_xlfn.XLOOKUP(Allgemein!$C$48,'Datenbank-Preise'!B74:B79,'Datenbank-Preise'!F74:F79,"Nein",0,1) -> Nein | H29: =_xlfn.XLOOKUP(Allgemein!$C$64,'Datenbank-Preise'!B74:B79,'Datenbank-Preise'!F74:F79,"Nein",0,1) -> Nein | I29: =_xlfn.XLOOKUP(Allgemein!$C$80,'Datenbank-Preise'!B74:B79,'Datenbank-Preise'!F74:F79,"Nein",0,1) -> Nein
B30: Vertikale Abdichtung vorhanden?: | F30: Umfang [m]: | G30: =IF(G29="Ja",$E$14,0) -> 0 | H30: =IF(H29="Ja",$E$14,0) -> 0 | I30: =IF(I29="Ja",$E$14,0) -> 0
B31: Feuchtigkeitsmessung: | F31: Bemerkung:
B32: Messpunkt | C32: Messwert in Digits | D32: Bewertung | E32: Anmerkung | F32: Bemerkung Ausführung?:

Sheet Elektro
B2: Projektnummer: | C2: =Allgemein!C2 -> 0 | F2: Maßnahmenpaket Elektro | I2: #VALUE!
B3: Anrede: | C3: =Allgemein!C3 -> 0
B4: Vorname Nachname: | C4: =Allgemein!C4 -> 0
B5: Straße, Nr. (Objektadresse): | C5: =Allgemein!C5 -> 0 | F5: Kurzbeschreibung Umsetzung? | G5: _
B6: PLZ, Ort: | C6: =Allgemein!C6 -> 0
B7: Email: | C7: =Allgemein!C7 -> 0 | F7: Preis: | G7: Preis in PV, WP oder Sonstiges einrechnen
B8: Telefon: | C8: =Allgemein!C8 -> 0
B9: Allgemeines zur Elektroinstallation:
B10: Bestand | F10: Wunsch/Anmerkung | H10: Umsetzung
B11: Anschlussart: | H11: Zusatzpositionen | I11: 1
B12: HAK Standort: | I12: 2
B13: HAK Größe: | I13: 3
I14: 4
B15: Potentialausgleichsschiene: | I15: 5
B16: Erdung Potentialausgleichsschiene: | I16: 6
H17: Weitere Anmerkung:
B18: VDE konformer Zählerschrank:
B19: Freifläche für weiteren Zählerschrank?:
B21: Weitere Anmerkungen:

Sheet Wärmepumpe
B2: Projektnummer: | C2: =Allgemein!C2 -> 0 | E2: Heizung | J2: #VALUE!
B3: Anrede: | C3: =Allgemein!C3 -> 0 | F3: Kurzbeschreibung Maßnahmen
B4: Vorname Nachname: | C4: =Allgemein!C4 -> 0 | E4: Umsetzungsvariante: | F4: =Allgemein!C100 -> 0
B5: Straße, Nr. (Objektadresse): | C5: =Allgemein!C5 -> 0 | E5: Zusatzleistung: | F5: =Allgemein!G100 -> 0
B6: PLZ, Ort: | C6: =Allgemein!C6 -> 0 | E6: Variante 1: | F6: =Allgemein!C50 -> 0
B7: Email: | C7: =Allgemein!C7 -> 0 | E7: Variante 2: | F7: =Allgemein!C66 -> 0
B8: Telefon: | C8: =Allgemein!C8 -> 0 | E8: Variante 3: | F8: =Allgemein!C82 -> 0
B9: Gebäudezustand
B10: Gebäudezustand IST | F10: Wunsch/Anmerkung | H10: Gebäudezustand SOLL
B11: Beheizte Raumfläche in m²: | C11: =Allgemein!C40 -> 0 | D11: Beschreibung IST-Zustand: | F11: Positionierung Außengerät: | H11: Heizlast: | I11: =Allgemein!C125&" kW" -> 0 kW | J11: Beschreibung SOLL-Zustand:
B12: Anzahl an Personen: | C12: =Allgemein!C16 -> 0 | D12: =_xlfn.TEXTJOIN(" + ",TRUE,Allgemein!D26,Allgemein!D27,Allgemein!D28,Allgemein!D29,Allgemein!D30,Allgemein!D31) -> - + - + - + - + - + - | F12: Aufstellort frei geräumt?: | H12: Endenergiebedarf/JAZ: | I12: =_xlfn.TEXTJOIN(" / ",FALSE,Allgemein!C123&" kWh/m²a",Allgemein!C133) -> 0 kWh/m²a / 3,5
B13: Baujahr Gebäude: | C13: =Allgemein!E14 -> 0 | F13: Aufstellart Außengerät: | H13: Heizwärmebedarf: | I13: =Allgemein!C134&" kWh/a" -> 0 kWh/a
B14: Heizungsanlage
B15: Bestandsanlage | F15: Wunsch/Anmerkung | H15: Umsetzung | I15: iSFP | J15: Variante 1 | K15: Variante 2
B16: Haupt-Heiztechnik | F16: Entfernung zw. Außen- und Innengerät: | H16: Wärmepumpe: | I16: =Datenbank!J95 -> 0 | J16: =Datenbank!J204 -> 0 | K16: =Datenbank!J321 -> 0
B17: Energieträger : | D17: Hersteller: | H17: Hersteller:
B18: Baujahr: | D18: Verbrauch: | E18: =_xlfn.TEXTJOIN(" ",FALSE,Allgemein!L17,Allgemein!O16&"/a") -> /a | H18: Typ:
B19: Nebenheiztechnik | H19: Bemerkung Ausführung:
B20: Unterstützender Wärmeerzeuger?: | D20: Besonderheiten: | F20: Einbringmaß / Breite in m (engste Stelle):
B21: Energieträger: | D21: Beschreibung Nutzerverhalten: | H21: Ausbau Bestandsheizung: | I21: {=_xlfn.XLOOKUP(H21&Allgemein!C50,Heizungspositionen[[#Headers],[Ausbau Bestandsheizung:]]&Heizungspositionen[Position Heizung],Heizungspositionen[Ausbau Bestandsheizung:],"",0,1)} -> 0 | J21: {=_xlfn.XLOOKUP(H21&Allgemein!C66,Heizungspositionen[[#Headers],[Ausbau Bestandsheizung:]]&Heizungspositionen[Position Heizung],Heizungspositionen[Ausbau Bestandsheizung:],"",0,1)} -> 0 | K21: {=_xlfn.XLOOKUP(H21&Allgemein!C82,Heizungspositionen[[#Headers],[Ausbau Bestandsheizung:]]&Heizungspositionen[Position Heizung],Heizungspositionen[Ausbau Bestandsheizung:],"",0,1)} -> 0
B22: Wärmeversorgung | H22: Bemerkung Ausführung:
B23: Art der Wärmeversorgung: | D23: Beschreibung: | F23: Höhe Aufstellort [lichte Höhe] in m:
B24: Art der Wärmeabgabe: | H24: neue Standardheizkörper: | I24: {=_xlfn.XLOOKUP(H24&Allgemein!D50,Wärmeübertragungspositionen[[#Headers],[neue Standardheizkörper:]]&Wärmeübertragungspositionen[Position Wärmeabgabe],Wärmeübertragungspositionen[neue Standardheizkörper:],"",0,1)} | J24: {=_xlfn.XLOOKUP(H24&Allgemein!D66,Wärmeübertragungspositionen[[#Headers],[neue Standardheizkörper:]]&Wärmeübertragungspositionen[Position Wärmeabgabe],Wärmeübertragungspositionen[neue Standardheizkörper:],"",0,1)} | K24: {=_xlfn.XLOOKUP(H24&Allgemein!D82,Wärmeübertragungspositionen[[#Headers],[neue Standardheizkörper:]]&Wärmeübertragungspositionen[Position Wärmeabgabe],Wärmeübertragungspositionen[neue Standardheizkörper:],"",0,1)}
B25: Heizflächen | F25: Beschreibung Aufstellung: | H25: Kompaktheizkörper:
B26: Kompakt- und Handtuchheizkörper [St.]: | C26: {=SUM(IF(Heizflächen!I12:I36="Kompaktheizkörper profiliert",1,0))+SUM(IF(Heizflächen!I12:I36="Kompaktheizkörper glatt",1,0))+SUM(IF(Heizflächen!I12:I36="Handtuchheizkörper",1,0))} -> 0 | D26: Flächenheizung [m²]: | E26: =SUMIF(Heizflächen!I12:I36,"Fußbodenheizung",Heizflächen!E12:E36)-SUMIF(Heizflächen!I12:I36,"Fußbodenheizung",Heizflächen!F12:F36) -> 0 | H26: Handtuchheizkörper:
B27: Radiatoren [St.]: | C27: {=SUM(IF(Heizflächen!J12:J36="Radiator",1,0))} -> 0 | D27: Anmerkungen: | H27: Wärmepumpenheizkörper: | I27: {=_xlfn.XLOOKUP(H27&Allgemein!D50,Wärmeübertragungspositionen[[#Headers],[Wärmepumpenheizkörper:]]&Wärmeübertragungspositionen[Position Wärmeabgabe],Wärmeübertragungspositionen[Wärmepumpenheizkörper:],"",0,1)} | J27: {=_xlfn.XLOOKUP(H27&Allgemein!D66,Wärmeübertragungspositionen[[#Headers],[Wärmepumpenheizkörper:]]&Wärmeübertragungspositionen[Position Wärmeabgabe],Wärmeübertragungspositionen[Wärmepumpenheizkörper:],"",0,1)} | K27: {=_xlfn.XLOOKUP(H27&Allgemein!D82,Wärmeübertragungspositionen[[#Headers],[Wärmepumpenheizkörper:]]&Wärmeübertragungspositionen[Position Wärmeabgabe],Wärmeübertragungspositionen[Wärmepumpenheizkörper:],"",0,1)}
B28: Heizkreise | F28: Anmerkungen: | H28: geplante Anzahl [St.]
B29: Heizkreis | C29: Heizkreistemperatur | D29: Art der Wärmeabgabe | E29: Verteilnetz | H29: Bemerkung Ausführung:
H30: Flächenheizung: | I30: {=_xlfn.XLOOKUP(H30&Allgemein!D50,Wärmeübertragungspositionen[[#Headers],[Flächenheizung:]]&Wärmeübertragungspositionen[Position Wärmeabgabe],Wärmeübertragungspositionen[Flächenheizung:],"",0,1)} | J30: {=_xlfn.XLOOKUP(H30&Allgemein!D66,Wärmeübertragungspositionen[[#Headers],[Flächenheizung:]]&Wärmeübertragungspositionen[Position Wärmeabgabe],Wärmeübertragungspositionen[Flächenheizung:],"",0,1)} | K30: {=_xlfn.XLOOKUP(H30&Allgemein!D82,Wärmeübertragungspositionen[[#Headers],[Flächenheizung:]]&Wärmeübertragungspositionen[Position Wärmeabgabe],Wärmeübertragungspositionen[Flächenheizung:],"",0,1)}
H31: geplante Heizfläche [m²]:
H32: Bemerkung Ausführung:
B33: Warmwasseraufbereitung
B34: Bestand | F34: Wunsch/Anmerkung | H34: Umsetzung | I34: iSFP | J34: Variante 1 | K34: Variante 2
B35: Warmwasseraufbereitung: | H35: Neuer Trinkwasserspeicher: | I35: {=_xlfn.XLOOKUP(H35&Allgemein!C50,Heizungspositionen[[#Headers],[Neuer Trinkwasserspeicher:]]&Heizungspositionen[Position Heizung],Heizungspositionen[Neuer Trinkwasserspeicher:],"",0,1)} -> 0 | J35: {=_xlfn.XLOOKUP(H35&Allgemein!C66,Heizungspositionen[[#Headers],[Neuer Trinkwasserspeicher:]]&Heizungspositionen[Position Heizung],Heizungspositionen[Neuer Trinkwasserspeicher:],"",0,1)} -> 0 | K35: {=_xlfn.XLOOKUP(H35&Allgemein!C82,Heizungspositionen[[#Headers],[Neuer Trinkwasserspeicher:]]&Heizungspositionen[Position Heizung],Heizungspositionen[Neuer Trinkwasserspeicher:],"",0,1)} -> 0
B36: Art der Warmwasseraufbereitung: | D36: Baujahr: | H36: Art:
B37: Energieträger: | H37: Bemerkung Ausführung:
B38: Unterstützender Trinkwarmwassererzeuger | D38: Baujahr:
B39: Art der Warmwasseraufbereitung: | D39: Energieträger:
B40: Warmwasserbereitstellung:
B41: Zirkulationsleitung vorh.?: | D41: Zirkulationspumpe vorh.?:

Sheet Heizflächen
B2: Projektnummer: | E2: =Allgemein!C2 -> 0 | I2: Heizflächen | S2: #VALUE!
B3: Anrede: | E3: =Allgemein!C3 -> 0
B4: Vorname Nachname: | E4: =Allgemein!C4 -> 0
B5: Straße, Nr. (Objektadresse): | E5: =Allgemein!C5 -> 0
B6: PLZ, Ort: | E6: =Allgemein!C6 -> 0
B7: Email: | E7: =Allgemein!C7 -> 0
B8: Telefon: | E8: =Allgemein!C8 -> 0
B9: vorhandene Heizflächen
B10: Räume | H10: Heizflächenübersicht | M10: Kompakt-/ Handtuchheizkörper | O10: Radiatoren | S10: Fußbodenheizung
B11: Benennung | C11: Geschoss | D11: Raum | E11: Raumfläche [m²] | F11: Abzugsfläche [m²] | G11: Auslegungstemperatur [°C] | H11: Nummer | I11: Heizkörper/Heizfläche | J11: Typ | K11: Heizkörper in Nische? | L11: Abstand über HK [mm] (wenn Nische) | M11: Breite [mm] | N11: Höhe [mm] | O11: Bauhöhe [mm] | P11: Nabenabstand [mm] | Q11: Bautiefe [mm] | R11: Gliederanzahl | S11: Verlegeabstand der Heizrohre T [m] | T11: Überdeckung su [m] | U11: Heizrohrdurchmesser D [m] | V11: Fußbodenbelag
H12: 1
H13: 2
H14: 3
H15: 4
H16: 5
H17: 6
H18: 7
H19: 8
H20: 9
H21: 10
H22: 11
H23: 12
... H61: 50
B62: Berechnung | M62: Auswertung
B63: Bestand | G63: Wunsch/Anmerkung | J63: Umsetzung | M63: Bestand | Q63: Wunsch/Anmerkung | T63: Umsetzung
B64: Geschoss | C64: Nummer | D64: Raum | E64: Leistung Heizfläche [W] | F64: Volumenstrom [l/min] | G64: Austausch? | H64: Materialwunsch | I64: Befestigung ok? | M64: Geschoss | N64: Raum | O64: Heizlast aufgeteilt [W] | P64: vorhandene Wärmeleistung [W] | T64: gewünschte Vor- und Rücklauftemperatur [°C]: | U64: 35/30
B65: =Heizflächen!C12 -> 0 | C65: =Heizflächen!H12 -> 1 | D65: =Heizflächen!D12 -> 0 | E65: {=IF(Heizflächen!I12="Fußbodenheizung",_xlfn.XLOOKUP(C12&D12&H12,Tabelle14[Geschoss]&Tabelle14[Raum]&Tabelle14[Heizkörpernummer],Tabelle14[Q '[W']],0,0,1),_xlfn.XLOOKUP(C12&D12&H12,Tabelle3[Geschoss]&Tabelle3[Raum]&Tabelle3[Heizkörpernummer],Tabelle3[Heizleistung des Heizkörpers QBetrieb],0,0,1))} -> 0 | F65: =0.86*((E65)/((_xlfn.XLOOKUP($U$64,Tabelle5[Auswählbare Vor-und Rücklauftemperaturen],Tabelle5[Vorlauf],"",0,1))-_xlfn.XLOOKUP($U$64,Tabelle5[Auswählbare Vor-und Rücklauftemperaturen],Tabelle5[Rücklauf],"",0,1))/60) -> 0 | M65: =Datenbank!FJ7 -> 0 | N65: =Datenbank!FK7 -> 0 | O65: {=(Allgemein!$C$125*1000*1.15)*((_xlfn.XLOOKUP(N65,Tabelle1[Raum],$E$12:$E$36,0,0,1))/(Datenbank!$FN$57))} -> #DIV/0! | P65: =SUMIFS(Tabelle3[Heizleistung des Heizkörpers QBetrieb],Tabelle3[Geschoss],M65,Tabelle3[Raum],N65)+SUMIFS(Tabelle14[Q '[W']],Tabelle14[Geschoss],M65,Tabelle14[Raum],N65) -> 0
B66: =Heizflächen!C13 -> 0 | C66: =Heizflächen!H13 -> 2 | D66: =Heizflächen!D13 -> 0 | E66: {=IF(Heizflächen!I13="Fußbodenheizung",_xlfn.XLOOKUP(C13&D13&H13,Tabelle14[Geschoss]&Tabelle14[Raum]&Tabelle14[Heizkörpernummer],Tabelle14[Q '[W']],0,0,1),_xlfn.XLOOKUP(C13&D13&H13,Tabelle3[Geschoss]&Tabelle3[Raum]&Tabelle3[Heizkörpernummer],Tabelle3[Heizleistung des Heizkörpers QBetrieb],0,0,1))} -> 0 | F66: =0.86*((E66)/((_xlfn.XLOOKUP($U$64,Tabelle5[Auswählbare Vor-und Rücklauftemperaturen],Tabelle5[Vorlauf],"",0,1))-_xlfn.XLOOKUP($U$64,Tabelle5[Auswählbare Vor-und Rücklauftemperaturen],Tabelle5[Rücklauf],"",0,1))/60) -> 0 | M66: =Datenbank!FJ8 -> 0 | N66: =Datenbank!FK8 -> 0 | O66: {=(Allgemein!$C$125*1000*1.15)*((_xlfn.XLOOKUP(N66,Tabelle1[Raum],$E$12:$E$36,0,0,1))/(Datenbank!$FN$57))} -> #DIV/0! | P66: =SUMIFS(Tabelle3[Heizleistung des Heizkörpers QBetrieb],Tabelle3[Geschoss],M66,Tabelle3[Raum],N66)+SUMIFS(Tabelle14[Q '[W']],Tabelle14[Geschoss],M66,Tabelle14[Raum],N66) -> 0
B67: =Heizflächen!C14 -> 0 | C67: =Heizflächen!H14 -> 3 | D67: =Heizflächen!D14 -> 0 | E67: {=IF(Heizflächen!I14="Fußbodenheizung",_xlfn.XLOOKUP(C14&D14&H14,Tabelle14[Geschoss]&Tabelle14[Raum]&Tabelle14[Heizkörpernummer],Tabelle14[Q '[W']],0,0,1),_xlfn.XLOOKUP(C14&D14&H14,Tabelle3[Geschoss]&Tabelle3[Raum]&Tabelle3[Heizkörpernummer],Tabelle3[Heizleistung des Heizkörpers QBetrieb],0,0,1))} -> 0 | F67: =0.86*((E67)/((_xlfn.XLOOKUP($U$64,Tabelle5[Auswählbare Vor-und Rücklauftemperaturen],Tabelle5[Vorlauf],"",0,1))-_xlfn.XLOOKUP($U$64,Tabelle5[Auswählbare Vor-und Rücklauftemperaturen],Tabelle5[Rücklauf],"",0,1))/60) -> 0 | M67: =Datenbank!FJ9 -> 0 | N67: =Datenbank!FK9 -> 0 | O67: {=(Allgemein!$C$125*1000*1.15)*((_xlfn.XLOOKUP(N67,Tabelle1[Raum],$E$12:$E$36,0,0,1))/(Datenbank!$FN$57))} -> #DIV/0! | P67: =SUMIFS(Tabelle3[Heizleistung des Heizkörpers QBetrieb],Tabelle3[Geschoss],M67,Tabelle3[Raum],N67)+SUMIFS(Tabelle14[Q '[W']],Tabelle14[Geschoss],M67,Tabelle14[Raum],N67) -> 0
B68: =Heizflächen!C15 -> 0 | C68: =Heizflächen!H15 -> 4 | D68: =Heizflächen!D15 -> 0 | E68: {=IF(Heizflächen!I15="Fußbodenheizung",_xlfn.XLOOKUP(C15&D15&H15,Tabelle14[Geschoss]&Tabelle14[Raum]&Tabelle14[Heizkörpernummer],Tabelle14[Q '[W']],0,0,1),_xlfn.XLOOKUP(C15&D15&H15,Tabelle3[Geschoss]&Tabelle3[Raum]&Tabelle3[Heizkörpernummer],Tabelle3[Heizleistung des Heizkörpers QBetrieb],0,0,1))} -> 0 | F68: =0.86*((E68)/((_xlfn.XLOOKUP($U$64,Tabelle5[Auswählbare Vor-und Rücklauftemperaturen],Tabelle5[Vorlauf],"",0,1))-_xlfn.XLOOKUP($U$64,Tabelle5[Auswählbare Vor-und Rücklauftemperaturen],Tabelle5[Rücklauf],"",0,1))/60) -> 0 | M68: =Datenbank!FJ10 -> 0 | N68: =Datenbank!FK10 -> 0 | O68: {=(Allgemein!$C$125*1000*1.15)*((_xlfn.XLOOKUP(N68,Tabelle1[Raum],$E$12:$E$36,0,0,1))/(Datenbank!$FN$57))} -> #DIV/0! | P68: =SUMIFS(Tabelle3[Heizleistung des Heizkörpers QBetrieb],Tabelle3[Geschoss],M68,Tabelle3[Raum],N68)+SUMIFS(Tabelle14[Q '[W']],Tabelle14[Geschoss],M68,Tabelle14[Raum],N68) -> 0
B69: =Heizflächen!C16 -> 0 | C69: =Heizflächen!H16 -> 5 | D69: =Heizflächen!D16 -> 0 | E69: {=IF(Heizflächen!I16="Fußbodenheizung",_xlfn.XLOOKUP(C16&D16&H16,Tabelle14[Geschoss]&Tabelle14[Raum]&Tabelle14[Heizkörpernummer],Tabelle14[Q '[W']],0,0,1),_xlfn.XLOOKUP(C16&D16&H16,Tabelle3[Geschoss]&Tabelle3[Raum]&Tabelle3[Heizkörpernummer],Tabelle3[Heizleistung des Heizkörpers QBetrieb],0,0,1))} -> 0 | F69: =0.86*((E69)/((_xlfn.XLOOKUP($U$64,Tabelle5[Auswählbare Vor-und Rücklauftemperaturen],Tabelle5[Vorlauf],"",0,1))-_xlfn.XLOOKUP($U$64,Tabelle5[Auswählbare Vor-und Rücklauftemperaturen],Tabelle5[Rücklauf],"",0,1))/60) -> 0 | M69: =Datenbank!FJ11 -> 0 | N69: =Datenbank!FK11 -> 0 | O69: {=(Allgemein!$C$125*1000*1.15)*((_xlfn.XLOOKUP(N69,Tabelle1[Raum],$E$12:$E$36,0,0,1))/(Datenbank!$FN$57))} -> #DIV/0! | P69: =SUMIFS(Tabelle3[Heizleistung des Heizkörpers QBetrieb],Tabelle3[Geschoss],M69,Tabelle3[Raum],N69)+SUMIFS(Tabelle14[Q '[W']],Tabelle14[Geschoss],M69,Tabelle14[Raum],N69) -> 0
B70: =Heizflächen!C17 -> 0 | C70: =Heizflächen!H17 -> 6 | D70: =Heizflächen!D17 -> 0 | E70: {=IF(Heizflächen!I17="Fußbodenheizung",_xlfn.XLOOKUP(C17&D17&H17,Tabelle14[Geschoss]&Tabelle14[Raum]&Tabelle14[Heizkörpernummer],Tabelle14[Q '[W']],0,0,1),_xlfn.XLOOKUP(C17&D17&H17,Tabelle3[Geschoss]&Tabelle3[Raum]&Tabelle3[Heizkörpernummer],Tabelle3[Heizleistung des Heizkörpers QBetrieb],0,0,1))} -> 0 | F70: =0.86*((E70)/((_xlfn.XLOOKUP($U$64,Tabelle5[Auswählbare Vor-und Rücklauftemperaturen],Tabelle5[Vorlauf],"",0,1))-_xlfn.XLOOKUP($U$64,Tabelle5[Auswählbare Vor-und Rücklauftemperaturen],Tabelle5[Rücklauf],"",0,1))/60) -> 0 | M70: =Datenbank!FJ12 -> 0 | N70: =Datenbank!FK12 -> 0 | O70: {=(Allgemein!$C$125*1000*1.15)*((_xlfn.XLOOKUP(N70,Tabelle1[Raum],$E$12:$E$36,0,0,1))/(Datenbank!$FN$57))} -> #DIV/0! | P70: =SUMIFS(Tabelle3[Heizleistung des Heizkörpers QBetrieb],Tabelle3[Geschoss],M70,Tabelle3[Raum],N70)+SUMIFS(Tabelle14[Q '[W']],Tabelle14[Geschoss],M70,Tabelle14[Raum],N70) -> 0
B71: =Heizflächen!C18 -> 0 | C71: =Heizflächen!H18 -> 7 | D71: =Heizflächen!D18 -> 0 | E71: {=IF(Heizflächen!I18="Fußbodenheizung",_xlfn.XLOOKUP(C18&D18&H18,Tabelle14[Geschoss]&Tabelle14[Raum]&Tabelle14[Heizkörpernummer],Tabelle14[Q '[W']],0,0,1),_xlfn.XLOOKUP(C18&D18&H18,Tabelle3[Geschoss]&Tabelle3[Raum]&Tabelle3[Heizkörpernummer],Tabelle3[Heizleistung des Heizkörpers QBetrieb],0,0,1))} -> 0 | F71: =0.86*((E71)/((_xlfn.XLOOKUP($U$64,Tabelle5[Auswählbare Vor-und Rücklauftemperaturen],Tabelle5[Vorlauf],"",0,1))-_xlfn.XLOOKUP($U$64,Tabelle5[Auswählbare Vor-und Rücklauftemperaturen],Tabelle5[Rücklauf],"",0,1))/60) -> 0 | M71: =Datenbank!FJ13 -> 0 | N71: =Datenbank!FK13 -> 0 | O71: {=(Allgemein!$C$125*1000*1.15)*((_xlfn.XLOOKUP(N71,Tabelle1[Raum],$E$12:$E$36,0,0,1))/(Datenbank!$FN$57))} -> #DIV/0! | P71: =SUMIFS(Tabelle3[Heizleistung des Heizkörpers QBetrieb],Tabelle3[Geschoss],M71,Tabelle3[Raum],N71)+SUMIFS(Tabelle14[Q '[W']],Tabelle14[Geschoss],M71,Tabelle14[Raum],N71) -> 0
B72: =Heizflächen!C19 -> 0 | C72: =Heizflächen!H19 -> 8 | D72: =Heizflächen!D19 -> 0 | E72: {=IF(Heizflächen!I19="Fußbodenheizung",_xlfn.XLOOKUP(C19&D19&H19,Tabelle14[Geschoss]&Tabelle14[Raum]&Tabelle14[Heizkörpernummer],Tabelle14[Q '[W']],0,0,1),_xlfn.XLOOKUP(C19&D19&H19,Tabelle3[Geschoss]&Tabelle3[Raum]&Tabelle3[Heizkörpernummer],Tabelle3[Heizleistung des Heizkörpers QBetrieb],0,0,1))} -> 0 | F72: =0.86*((E72)/((_xlfn.XLOOKUP($U$64,Tabelle5[Auswählbare Vor-und Rücklauftemperaturen],Tabelle5[Vorlauf],"",0,1))-_xlfn.XLOOKUP($U$64,Tabelle5[Auswählbare Vor-und Rücklauftemperaturen],Tabelle5[Rücklauf],"",0,1))/60) -> 0 | M72: =Datenbank!FJ14 -> 0 | N72: =Datenbank!FK14 -> 0 | O72: {=(Allgemein!$C$125*1000*1.15)*((_xlfn.XLOOKUP(N72,Tabelle1[Raum],$E$12:$E$36,0,0,1))/(Datenbank!$FN$57))} -> #DIV/0! | P72: =SUMIFS(Tabelle3[Heizleistung des Heizkörpers QBetrieb],Tabelle3[Geschoss],M72,Tabelle3[Raum],N72)+SUMIFS(Tabelle14[Q '[W']],Tabelle14[Geschoss],M72,Tabelle14[Raum],N72) -> 0
B73: =Heizflächen!C20 -> 0 | C73: =Heizflächen!H20 -> 9 | D73: =Heizflächen!D20 -> 0 | E73: {=IF(Heizflächen!I20="Fußbodenheizung",_xlfn.XLOOKUP(C20&D20&H20,Tabelle14[Geschoss]&Tabelle14[Raum]&Tabelle14[Heizkörpernummer],Tabelle14[Q '[W']],0,0,1),_xlfn.XLOOKUP(C20&D20&H20,Tabelle3[Geschoss]&Tabelle3[Raum]&Tabelle3[Heizkörpernummer],Tabelle3[Heizleistung des Heizkörpers QBetrieb],0,0,1))} -> 0 | F73: =0.86*((E73)/((_xlfn.XLOOKUP($U$64,Tabelle5[Auswählbare Vor-und Rücklauftemperaturen],Tabelle5[Vorlauf],"",0,1))-_xlfn.XLOOKUP($U$64,Tabelle5[Auswählbare Vor-und Rücklauftemperaturen],Tabelle5[Rücklauf],"",0,1))/60) -> 0 | M73: =Datenbank!FJ15 -> 0 | N73: =Datenbank!FK15 -> 0 | O73: {=(Allgemein!$C$125*1000*1.15)*((_xlfn.XLOOKUP(N73,Tabelle1[Raum],$E$12:$E$36,0,0,1))/(Datenbank!$FN$57))} -> #DIV/0! | P73: =SUMIFS(Tabelle3[Heizleistung des Heizkörpers QBetrieb],Tabelle3[Geschoss],M73,Tabelle3[Raum],N73)+SUMIFS(Tabelle14[Q '[W']],Tabelle14[Geschoss],M73,Tabelle14[Raum],N73) -> 0
B74: =Heizflächen!C21 -> 0 | C74: =Heizflächen!H21 -> 10 | D74: =Heizflächen!D21 -> 0 | E74: {=IF(Heizflächen!I21="Fußbodenheizung",_xlfn.XLOOKUP(C21&D21&H21,Tabelle14[Geschoss]&Tabelle14[Raum]&Tabelle14[Heizkörpernummer],Tabelle14[Q '[W']],0,0,1),_xlfn.XLOOKUP(C21&D21&H21,Tabelle3[Geschoss]&Tabelle3[Raum]&Tabelle3[Heizkörpernummer],Tabelle3[Heizleistung des Heizkörpers QBetrieb],0,0,1))} -> 0 | F74: =0.86*((E74)/((_xlfn.XLOOKUP($U$64,Tabelle5[Auswählbare Vor-und Rücklauftemperaturen],Tabelle5[Vorlauf],"",0,1))-_xlfn.XLOOKUP($U$64,Tabelle5[Auswählbare Vor-und Rücklauftemperaturen],Tabelle5[Rücklauf],"",0,1))/60) -> 0 | M74: =Datenbank!FJ16 -> 0 | N74: =Datenbank!FK16 -> 0 | O74: {=(Allgemein!$C$125*1000*1.15)*((_xlfn.XLOOKUP(N74,Tabelle1[Raum],$E$12:$E$36,0,0,1))/(Datenbank!$FN$57))} -> #DIV/0! | P74: =SUMIFS(Tabelle3[Heizleistung des Heizkörpers QBetrieb],Tabelle3[Geschoss],M74,Tabelle3[Raum],N74)+SUMIFS(Tabelle14[Q '[W']],Tabelle14[Geschoss],M74,Tabelle14[Raum],N74) -> 0
B75: =Heizflächen!C22 -> 0 | C75: =Heizflächen!H22 -> 11 | D75: =Heizflächen!D22 -> 0 | E75: {=IF(Heizflächen!I22="Fußbodenheizung",_xlfn.XLOOKUP(C22&D22&H22,Tabelle14[Geschoss]&Tabelle14[Raum]&Tabelle14[Heizkörpernummer],Tabelle14[Q '[W']],0,0,1),_xlfn.XLOOKUP(C22&D22&H22,Tabelle3[Geschoss]&Tabelle3[Raum]&Tabelle3[Heizkörpernummer],Tabelle3[Heizleistung des Heizkörpers QBetrieb],0,0,1))} -> 0 | F75: =0.86*((E75)/((_xlfn.XLOOKUP($U$64,Tabelle5[Auswählbare Vor-und Rücklauftemperaturen],Tabelle5[Vorlauf],"",0,1))-_xlfn.XLOOKUP($U$64,Tabelle5[Auswählbare Vor-und Rücklauftemperaturen],Tabelle5[Rücklauf],"",0,1))/60) -> 0 | M75: =Datenbank!FJ17 -> 0 | N75: =Datenbank!FK17 -> 0 | O75: {=(Allgemein!$C$125*1000*1.15)*((_xlfn.XLOOKUP(N75,Tabelle1[Raum],$E$12:$E$36,0,0,1))/(Datenbank!$FN$57))} -> #DIV/0! | P75: =SUMIFS(Tabelle3[Heizleistung des Heizkörpers QBetrieb],Tabelle3[Geschoss],M75,Tabelle3[Raum],N75)+SUMIFS(Tabelle14[Q '[W']],Tabelle14[Geschoss],M75,Tabelle14[Raum],N75) -> 0
B76: =Heizflächen!C23 -> 0 | C76: =Heizflächen!H23 -> 12 | D76: =Heizflächen!D23 -> 0 | E76: {=IF(Heizflächen!I23="Fußbodenheizung",_xlfn.XLOOKUP(C23&D23&H23,Tabelle14[Geschoss]&Tabelle14[Raum]&Tabelle14[Heizkörpernummer],Tabelle14[Q '[W']],0,0,1),_xlfn.XLOOKUP(C23&D23&H23,Tabelle3[Geschoss]&Tabelle3[Raum]&Tabelle3[Heizkörpernummer],Tabelle3[Heizleistung des Heizkörpers QBetrieb],0,0,1))} -> 0 | F76: =0.86*((E76)/((_xlfn.XLOOKUP($U$64,Tabelle5[Auswählbare Vor-und Rücklauftemperaturen],Tabelle5[Vorlauf],"",0,1))-_xlfn.XLOOKUP($U$64,Tabelle5[Auswählbare Vor-und Rücklauftemperaturen],Tabelle5[Rücklauf],"",0,1))/60) -> 0 | M76: =Datenbank!FJ18 -> 0 | N76: =Datenbank!FK18 -> 0 | O76: {=(Allgemein!$C$125*1000*1.15)*((_xlfn.XLOOKUP(N76,Tabelle1[Raum],$E$12:$E$36,0,0,1))/(Datenbank!$FN$57))} -> #DIV/0! | P76: =SUMIFS(Tabelle3[Heizleistung des Heizkörpers QBetrieb],Tabelle3[Geschoss],M76,Tabelle3[Raum],N76)+SUMIFS(Tabelle14[Q '[W']],Tabelle14[Geschoss],M76,Tabelle14[Raum],N76) -> 0
... B114: =Heizflächen!C61 -> 0 | C114: =Heizflächen!H61 -> 50 | D114: =Heizflächen!D61 -> 0 | E114: {=IF(Heizflächen!I61="Fußbodenheizung",_xlfn.XLOOKUP(C61&D61&H61,Tabelle14[Geschoss]&Tabelle14[Raum]&Tabelle14[Heizkörpernummer],Tabelle14[Q '[W']],0,0,1),_xlfn.XLOOKUP(C61&D61&H61,Tabelle3[Geschoss]&Tabelle3[Raum]&Tabelle3[Heizkörpernummer],Tabelle3[Heizleistung des Heizkörpers QBetrieb],0,0,1))} -> 0 | F114: =0.86*((E114)/((_xlfn.XLOOKUP($U$64,Tabelle5[Auswählbare Vor-und Rücklauftemperaturen],Tabelle5[Vorlauf],"",0,1))-_xlfn.XLOOKUP($U$64,Tabelle5[Auswählbare Vor-und Rücklauftemperaturen],Tabelle5[Rücklauf],"",0,1))/60) -> 0 | M114: =Datenbank!FJ56 -> 0 | N114: =Datenbank!FK56 -> 0 | O114: {=(Allgemein!$C$125*1000*1.15)*((_xlfn.XLOOKUP(N114,Tabelle1[Raum],$E$12:$E$36,0,0,1))/(Datenbank!$FN$57))} -> #DIV/0! | P114: =SUMIFS(Tabelle3[Heizleistung des Heizkörpers QBetrieb],Tabelle3[Geschoss],M114,Tabelle3[Raum],N114)+SUMIFS(Tabelle14[Q '[W']],Tabelle14[Geschoss],M114,Tabelle14[Raum],N114) -> 0

Sheet Datenbank
BH1: Wärmeleistung (55/45/20)
G2: EE-Klasse | I2: WP | K2: EH-Haus | M2: Heizmedium | N2: Einheit | O2: Heizwert [kWh/Einheit] | P2: CO2 Emmisionen [g/kWh] | Q2: Preissteigerung | DQ2: Berechnung Heizkörper | EM2: Berechnung Fußbodenheizung
B3: Sanierungslotse | E3: auf Standardpreis | G3: EE-Klasse | I3: WP-Building | K3: ein Effizienzhaus 40 | M3: Öl | N3: l | O3: 9.94 | P3: 266 | Q3: =Allgemein!C143 -> 0.04 | S3: Ja | T3: iSFP | DX3: Bei welchen Auslegungstemperaturen wurde HK genormt? (Standardauswahl 55/45) | DZ3: 55/45 | ED3: Abminderung nur bei Abstand über HK<100mm | EE3: 55/45/20 | FX3: Ist-Bauweise
B4: T. Jaschke | E4: auf Gesamtpreis | G4: - | I4: - | K4: ein Effizienzhaus 55 | M4: Flüssiggas | N4: kg | O4: 12.77 | P4: 239 | Q4: =Allgemein!C142 -> 0.04 | S4: Nein | T4: Variante 1 | BH4: Typ | BI4: Breite [mm] | BJ4: Höhe [mm] | BK4: Bauhöhe Radiator [mm] | BL4: Nabenabstand Radiator [mm] | BM4: Bautiefe Radiator [mm] | BN4: Wärmeleistung (Radiatoren je Glied) [W]
B5: L. Könnecke | K5: ein Effizienzhaus 70 | M5: Erdgas | N5: m³ | O5: 9.77 | P5: 201 | Q5: =Allgemein!C142 -> 0.04 | T5: Variante 2 | BH5: Typ 33 | BI5: 400 | BJ5: 300 | BN5: 293
K6: ein Effizienzhaus 85 | M6: Erdgas | N6: kWh | O6: 1 | P6: 201 | Q6: =Allgemein!C142 -> 0.04 | T6: nicht festgelegt | AO6: Energieeffizienzklasse | AP6: untere Grenze | AQ6: obere Grenze | BH6: Typ 33 | BI6: 500 | BJ6: 300 | BN6: 366 | FN6: Fläche [m²]
K7: ein Effizienzhaus Denkmal | M7: Steinkohle | N7: kg | O7: 8.36 | P7: 338 | Q7: =Allgemein!C144 -> 0.04 | AO7: A+ | AP7: 0 | AQ7: 25 | BH7: Typ 33 | BI7: 600 | BJ7: 300 | BN7: 439 | DQ7: Geschoss | DR7: Raum | DS7: Heizkörpernummer | DT7: Auslegungsinnentemperatur [°C] | DU7: gewünschte Vorlauftemperatur | DV7: gewünschte Rücklauftemperatur | DW7: gewünschte Übertemperatur Δθm1 | DX7: Norm Vorlauftemperatur | DY7: Norm Rücklauftemperatur | DZ7: Norm Innentemperatur | EA7: Norm-Übertemperatur Δθm2 | EB7: Heizkörperexponent n | EC7: Heizkörper in Nische? | ED7: Abminderungsfaktor | EE7: f = (Δθm1/Δθm2)^n | EF7: Norm Heizleistung QNorm | EG7: Gliederanzahl | EH7: Heizleistung des Heizkörpers QBetrieb | EM7: Geschoss | EN7: Raum | EO7: mT | EP7: mu | EQ7: mD | ER7: aT | ES7: au | ET7: aD | EU7: gewünschte Vorlauftemperatur | EV7: gewünschte Rücklauftemperatur | EW7: gewünschte Übertemperatur Δθm | EX7: Wärmedurchlasswiderstand Bodenbelag | EY7: aB | EZ7: B [W/(m²K)] | FA7: q [W/m²] | FB7: Q [W] | FC7: Heizkörpernummer | FG7: ÜBERTRAG DER EINTRÄGE: | FI7: 1 | FJ7: {=_xlfn.UNIQUE(Tabelle3[[Geschoss]:[Raum]])} -> 0 | FK7: 0 | FL7: {=_xlfn.UNIQUE(Heizflächen!C12:E61)} -> 0 | FM7: 0 | FN7: 0
K8: leider keinen Effizienzhausstandard | M8: Braunkohle | N8: kg | O8: 5.6 | P8: 399 | Q8: =Allgemein!C144 -> 0.04 | AO8: A | AP8: 30 | AQ8: 50 | BH8: Typ 33 | BI8: 700 | BJ8: 300 | BN8: 513 | DQ8: =Heizflächen!C12 -> 0 | DR8: =Heizflächen!D12 -> 0 | DS8: =Heizflächen!H12 -> 1 | DT8: =Heizflächen!G12 -> 0 | DU8: =_xlfn.XLOOKUP(Heizflächen!$U$64,Tabelle5[Auswählbare Vor-und Rücklauftemperaturen],Tabelle5[Vorlauf],0,0,1) -> 35 | DV8: =_xlfn.XLOOKUP(Heizflächen!$U$64,Tabelle5[Auswählbare Vor-und Rücklauftemperaturen],Tabelle5[Rücklauf],0,0,1) -> 30 | DW8: =((Tabelle3[[#This Row],[gewünschte Vorlauftemperatur]]-Tabelle3[[#This Row],[gewünschte Rücklauftemperatur]])/LN((Tabelle3[[#This Row],[gewünschte Vorlauftemperatur]]-Tabelle3[[#This Row],[Auslegungsinnentemperatur '[°C']]])/(Tabelle3[[#This Row],[gewünschte Rücklauftemperatur]]-Tabelle3[[#This Row],[Auslegungsinnentemperatur '[°C']]]))) -> 32.435796 | DX8: =_xlfn.XLOOKUP($DZ$3,Tabelle6[Systemtemperatur bei Norm-Wärmeleistungsbestimmung],Tabelle6[Vorlauf],0,0,1) -> 55 | DY8: =_xlfn.XLOOKUP($DZ$3,Tabelle6[Systemtemperatur bei Norm-Wärmeleistungsbestimmung],Tabelle6[Rücklauf],0,0,1) -> 45 | DZ8: =_xlfn.XLOOKUP($DZ$3,Tabelle6[Systemtemperatur bei Norm-Wärmeleistungsbestimmung],Tabelle6[Norm Innentemperatur],0,0,1) -> 20 | EA8: =((Tabelle3[[#This Row],[Norm Vorlauftemperatur]]-Tabelle3[[#This Row],[Norm Rücklauftemperatur]])/LN((Tabelle3[[#This Row],[Norm Vorlauftemperatur]]-Tabelle3[[#This Row],[Norm Innentemperatur]])/(Tabelle3[[#This Row],[Norm Rücklauftemperatur]]-Tabelle3[[#This Row],[Norm Innentemperatur]]))) -> 29.720134 | EB8: =_xlfn.XLOOKUP(Heizflächen!I12,Tabelle2[Typ],Tabelle2[Heizkörperexponent],0,1,1) -> 0 | EC8: =Heizflächen!K12 -> 0 | ED8: =IF(Tabelle3[[#This Row],[Heizkörper in Nische?]]="Nein",1,_xlfn.XLOOKUP(Heizflächen!L12, Tabelle8[Höhe über HK],Tabelle8[Abminderungsfaktor],1,0,1)) -> 1 | EE8: =(DW8/EA8)^Tabelle3[[#This Row],[Heizkörperexponent n]] -> 1 | EF8: {=_xlfn.XLOOKUP(Heizflächen!J12&Heizflächen!M12&Heizflächen!N12&Heizflächen!O12&Heizflächen!P12&Heizflächen!Q12,Tabelle4[Typ]&Tabelle4[Breite '[mm']]&Tabelle4[Höhe '[mm']]&Tabelle4[Bauhöhe Radiator '[mm']]&Tabelle4[Nabenabstand Radiator '[mm']]&Tabelle4[Bautiefe Radiator '[mm']],Tabelle4[Wärmeleistung (Radiatoren je Glied) '[W']],,-1,1)} -> 0 | EG8: =Heizflächen!R12 -> 0 | EH8: =IF(AND(Tabelle3[[#This Row],[Gliederanzahl]]>0,Heizflächen!J12="Radiator"),Tabelle3[[#This Row],[Norm Heizleistung QNorm]]*Tabelle3[[#This Row],[f = (Δθm1/Δθm2)^n]]*Tabelle3[[#This Row],[Abminderungsfaktor]]*Tabelle3[[#This Row],[Gliederanzahl]],Tabelle3[[#This Row],[Abminderungsfaktor]]*Tabelle3[[#This Row],[f = (Δθm1/Δθm2)^n]]*Tabelle3[[#This Row],[Norm Heizleistung QNorm]]) -> 0 | EM8: =Heizflächen!C12 -> 0 | EN8: =Heizflächen!D12 -> 0 | EO8: =1-(Heizflächen!S12/0.075) -> 1 | EP8: =100*(0.045-Heizflächen!T12) -> 4.5 | EQ8: =250*(Heizflächen!U12-0.02) -> -5 | ER8: =_xlfn.XLOOKUP(Tabelle14[[#This Row],[Wärmedurchlasswiderstand Bodenbelag]],Tabelle17[Wärmedurchlasswiderstand Rλ,B in '[m²K/W']],Tabelle17[aT],0,-1,1) -> 1.23 | ES8: {=_xlfn.XLOOKUP(Heizflächen!S12&Tabelle14[[#This Row],[Wärmedurchlasswiderstand Bodenbelag]],Tabelle18[T]&Tabelle18[Rλ,B in '[m²K/W']],Tabelle18[au],0,-1,1)} -> 0 | ET8: {=_xlfn.XLOOKUP(Heizflächen!S12&Tabelle14[[#This Row],[Wärmedurchlasswiderstand Bodenbelag]],Tabelle19[T]&Tabelle19[Rλ,B in '[m²K/W']],Tabelle19[aD],0,-1,1)} -> 0 | EU8: =_xlfn.XLOOKUP(Heizflächen!$U$64,Tabelle5[Auswählbare Vor-und Rücklauftemperaturen],Tabelle5[Vorlauf],0,0,1) -> 35 | EV8: =_xlfn.XLOOKUP(Heizflächen!$U$64,Tabelle5[Auswählbare Vor-und Rücklauftemperaturen],Tabelle5[Rücklauf],0,0,1) -> 30 | EW8: =((Tabelle14[[#This Row],[gewünschte Vorlauftemperatur]]-Tabelle14[[#This Row],[gewünschte Rücklauftemperatur]])/LN((Tabelle14[[#This Row],[gewünschte Vorlauftemperatur]]-Heizflächen!G12)/(Tabelle14[[#This Row],[gewünschte Rücklauftemperatur]]-Heizflächen!G12))) -> 32.435796 | EX8: =_xlfn.XLOOKUP(Heizflächen!V12,Tabelle13[Bodenbelagsmaterial],Tabelle13[Wärmedurchlasswiderstand Rλ,B in '[m²K/W']],0,0,1) -> 0 | EY8: =((1/10.8)+(0.045/1))/((1/10.8)+(0.045/1.4)+Tabelle14[[#This Row],[Wärmedurchlasswiderstand Bodenbelag]]) -> 1.1030753 | EZ8: 6.7 | FA8: =Tabelle14[[#This Row],[B '[W/(m²K)']]]*Tabelle14[[#This Row],[aB]]*(Tabelle14[[#This Row],[aT]]^Tabelle14[[#This Row],[mT]])*(Tabelle14[[#This Row],[au]]^Tabelle14[[#This Row],[mu]])*(Tabelle14[[#This Row],[aD]]^Tabelle14[[#This Row],[mD]])*Tabelle14[[#This Row],[gewünschte Übertemperatur Δθm]] -> #DIV/0! | FB8: =IFERROR(Tabelle14[[#This Row],[q '[W/m²']]]*(Heizflächen!E12-Heizflächen!F12),0) -> 0 | FC8: =Heizflächen!H12 -> 1 | FI8: 2
K9: Nicht ausgefüllt | M9: Ottokraftstoffe | N9: l | O9: 9.02 | P9: 264 | Q9: =Allgemein!C144 -> 0.04 | AO9: B | AP9: 50 | AQ9: 75 | BH9: Typ 33 | BI9: 800 | BJ9: 300 | BN9: 586 | DQ9: =Heizflächen!C13 -> 0 | DR9: =Heizflächen!D13 -> 0 | DS9: =Heizflächen!H13 -> 2 | DT9: =Heizflächen!G13 -> 0 | DU9: =_xlfn.XLOOKUP(Heizflächen!$U$64,Tabelle5[Auswählbare Vor-und Rücklauftemperaturen],Tabelle5[Vorlauf],0,0,1) -> 35 | DV9: =_xlfn.XLOOKUP(Heizflächen!$U$64,Tabelle5[Auswählbare Vor-und Rücklauftemperaturen],Tabelle5[Rücklauf],0,0,1) -> 30 | DW9: =((Tabelle3[[#This Row],[gewünschte Vorlauftemperatur]]-Tabelle3[[#This Row],[gewünschte Rücklauftemperatur]])/LN((Tabelle3[[#This Row],[gewünschte Vorlauftemperatur]]-Tabelle3[[#This Row],[Auslegungsinnentemperatur '[°C']]])/(Tabelle3[[#This Row],[gewünschte Rücklauftemperatur]]-Tabelle3[[#This Row],[Auslegungsinnentemperatur '[°C']]]))) -> 32.435796 | DX9: =_xlfn.XLOOKUP($DZ$3,Tabelle6[Systemtemperatur bei Norm-Wärmeleistungsbestimmung],Tabelle6[Vorlauf],0,0,1) -> 55 | DY9: =_xlfn.XLOOKUP($DZ$3,Tabelle6[Systemtemperatur bei Norm-Wärmeleistungsbestimmung],Tabelle6[Rücklauf],0,0,1) -> 45 | DZ9: =_xlfn.XLOOKUP($DZ$3,Tabelle6[Systemtemperatur bei Norm-Wärmeleistungsbestimmung],Tabelle6[Norm Innentemperatur],0,0,1) -> 20 | EA9: =((Tabelle3[[#This Row],[Norm Vorlauftemperatur]]-Tabelle3[[#This Row],[Norm Rücklauftemperatur]])/LN((Tabelle3[[#This Row],[Norm Vorlauftemperatur]]-Tabelle3[[#This Row],[Norm Innentemperatur]])/(Tabelle3[[#This Row],[Norm Rücklauftemperatur]]-Tabelle3[[#This Row],[Norm Innentemperatur]]))) -> 29.720134 | EB9: =_xlfn.XLOOKUP(Heizflächen!I13,Tabelle2[Typ],Tabelle2[Heizkörperexponent],0,1,1) -> 0 | EC9: =Heizflächen!K13 -> 0 | ED9: =IF(Tabelle3[[#This Row],[Heizkörper in Nische?]]="Nein",1,_xlfn.XLOOKUP(Heizflächen!L13, Tabelle8[Höhe über HK],Tabelle8[Abminderungsfaktor],1,0,1)) -> 1 | EE9: =(DW9/EA9)^Tabelle3[[#This Row],[Heizkörperexponent n]] -> 1 | EF9: {=_xlfn.XLOOKUP(Heizflächen!J13&Heizflächen!M13&Heizflächen!N13&Heizflächen!O13&Heizflächen!P13&Heizflächen!Q13,Tabelle4[Typ]&Tabelle4[Breite '[mm']]&Tabelle4[Höhe '[mm']]&Tabelle4[Bauhöhe Radiator '[mm']]&Tabelle4[Nabenabstand Radiator '[mm']]&Tabelle4[Bautiefe Radiator '[mm']],Tabelle4[Wärmeleistung (Radiatoren je Glied) '[W']],,-1,1)} -> 0 | EG9: =Heizflächen!R13 -> 0 | EH9: =IF(AND(Tabelle3[[#This Row],[Gliederanzahl]]>0,Heizflächen!J13="Radiator"),Tabelle3[[#This Row],[Norm Heizleistung QNorm]]*Tabelle3[[#This Row],[f = (Δθm1/Δθm2)^n]]*Tabelle3[[#This Row],[Abminderungsfaktor]]*Tabelle3[[#This Row],[Gliederanzahl]],Tabelle3[[#This Row],[Abminderungsfaktor]]*Tabelle3[[#This Row],[f = (Δθm1/Δθm2)^n]]*Tabelle3[[#This Row],[Norm Heizleistung QNorm]]) -> 0 | EM9: =Heizflächen!C13 -> 0 | EN9: =Heizflächen!D13 -> 0 | EO9: =1-(Heizflächen!S13/0.075) -> 1 | EP9: =100*(0.045-Heizflächen!T13) -> 4.5 | EQ9: =250*(Heizflächen!U13-0.02) -> -5 | ER9: =_xlfn.XLOOKUP(Tabelle14[[#This Row],[Wärmedurchlasswiderstand Bodenbelag]],Tabelle17[Wärmedurchlasswiderstand Rλ,B in '[m²K/W']],Tabelle17[aT],0,-1,1) -> 1.23 | ES9: {=_xlfn.XLOOKUP(Heizflächen!S13&Tabelle14[[#This Row],[Wärmedurchlasswiderstand Bodenbelag]],Tabelle18[T]&Tabelle18[Rλ,B in '[m²K/W']],Tabelle18[au],0,-1,1)} -> 0 | ET9: {=_xlfn.XLOOKUP(Heizflächen!S13&Tabelle14[[#This Row],[Wärmedurchlasswiderstand Bodenbelag]],Tabelle19[T]&Tabelle19[Rλ,B in '[m²K/W']],Tabelle19[aD],0,-1,1)} -> 0 | EU9: =_xlfn.XLOOKUP(Heizflächen!$U$64,Tabelle5[Auswählbare Vor-und Rücklauftemperaturen],Tabelle5[Vorlauf],0,0,1) -> 35 | EV9: =_xlfn.XLOOKUP(Heizflächen!$U$64,Tabelle5[Auswählbare Vor-und Rücklauftemperaturen],Tabelle5[Rücklauf],0,0,1) -> 30 | EW9: =((Tabelle14[[#This Row],[gewünschte Vorlauftemperatur]]-Tabelle14[[#This Row],[gewünschte Rücklauftemperatur]])/LN((Tabelle14[[#This Row],[gewünschte Vorlauftemperatur]]-Heizflächen!G13)/(Tabelle14[[#This Row],[gewünschte Rücklauftemperatur]]-Heizflächen!G13))) -> 32.435796 | EX9: =_xlfn.XLOOKUP(Heizflächen!V13,Tabelle13[Bodenbelagsmaterial],Tabelle13[Wärmedurchlasswiderstand Rλ,B in '[m²K/W']],0,0,1) -> 0 | EY9: =((1/10.8)+(0.045/1))/((1/10.8)+(0.045/1.4)+Tabelle14[[#This Row],[Wärmedurchlasswiderstand Bodenbelag]]) -> 1.1030753 | EZ9: 6.7 | FA9: =Tabelle14[[#This Row],[B '[W/(m²K)']]]*Tabelle14[[#This Row],[aB]]*(Tabelle14[[#This Row],[aT]]^Tabelle14[[#This Row],[mT]])*(Tabelle14[[#This Row],[au]]^Tabelle14[[#This Row],[mu]])*(Tabelle14[[#This Row],[aD]]^Tabelle14[[#This Row],[mD]])*Tabelle14[[#This Row],[gewünschte Übertemperatur Δθm]] -> #DIV/0! | FB9: =IFERROR(Tabelle14[[#This Row],[q '[W/m²']]]*(Heizflächen!E13-Heizflächen!F13),0) -> 0 | FC9: =Heizflächen!H13 -> 2 | FI9: 3
B10: Energieberater | M10: Dieselkraftstoffe | N10: l | O10: 9.96 | P10: 264 | Q10: =Allgemein!C144 -> 0.04 | AO10: C | AP10: 75 | AQ10: 100 | BH10: Typ 33 | BI10: 900 | BJ10: 300 | BN10: 659 | CC10: Auswählbare Vor-und Rücklauftemperaturen | CD10: Vorlauf | CE10: Rücklauf | CH10: Systemtemperatur bei Norm-Wärmeleistungsbestimmung | CI10: Vorlauf | CJ10: Rücklauf | CK10: Norm Innentemperatur | DQ10: =Heizflächen!C14 -> 0 | DR10: =Heizflächen!D14 -> 0 | DS10: =Heizflächen!H14 -> 3 | DT10: =Heizflächen!G14 -> 0 | DU10: =_xlfn.XLOOKUP(Heizflächen!$U$64,Tabelle5[Auswählbare Vor-und Rücklauftemperaturen],Tabelle5[Vorlauf],0,0,1) -> 35 | DV10: =_xlfn.XLOOKUP(Heizflächen!$U$64,Tabelle5[Auswählbare Vor-und Rücklauftemperaturen],Tabelle5[Rücklauf],0,0,1) -> 30 | DW10: =((Tabelle3[[#This Row],[gewünschte Vorlauftemperatur]]-Tabelle3[[#This Row],[gewünschte Rücklauftemperatur]])/LN((Tabelle3[[#This Row],[gewünschte Vorlauftemperatur]]-Tabelle3[[#This Row],[Auslegungsinnentemperatur '[°C']]])/(Tabelle3[[#This Row],[gewünschte Rücklauftemperatur]]-Tabelle3[[#This Row],[Auslegungsinnentemperatur '[°C']]]))) -> 32.435796 | DX10: =_xlfn.XLOOKUP($DZ$3,Tabelle6[Systemtemperatur bei Norm-Wärmeleistungsbestimmung],Tabelle6[Vorlauf],0,0,1) -> 55 | DY10: =_xlfn.XLOOKUP($DZ$3,Tabelle6[Systemtemperatur bei Norm-Wärmeleistungsbestimmung],Tabelle6[Rücklauf],0,0,1) -> 45 | DZ10: =_xlfn.XLOOKUP($DZ$3,Tabelle6[Systemtemperatur bei Norm-Wärmeleistungsbestimmung],Tabelle6[Norm Innentemperatur],0,0,1) -> 20 | EA10: =((Tabelle3[[#This Row],[Norm Vorlauftemperatur]]-Tabelle3[[#This Row],[Norm Rücklauftemperatur]])/LN((Tabelle3[[#This Row],[Norm Vorlauftemperatur]]-Tabelle3[[#This Row],[Norm Innentemperatur]])/(Tabelle3[[#This Row],[Norm Rücklauftemperatur]]-Tabelle3[[#This Row],[Norm Innentemperatur]]))) -> 29.720134 | EB10: =_xlfn.XLOOKUP(Heizflächen!I14,Tabelle2[Typ],Tabelle2[Heizkörperexponent],0,1,1) -> 0 | EC10: =Heizflächen!K14 -> 0 | ED10: =IF(Tabelle3[[#This Row],[Heizkörper in Nische?]]="Nein",1,_xlfn.XLOOKUP(Heizflächen!L14, Tabelle8[Höhe über HK],Tabelle8[Abminderungsfaktor],1,0,1)) -> 1 | EE10: =(DW10/EA10)^Tabelle3[[#This Row],[Heizkörperexponent n]] -> 1 | EF10: {=_xlfn.XLOOKUP(Heizflächen!J14&Heizflächen!M14&Heizflächen!N14&Heizflächen!O14&Heizflächen!P14&Heizflächen!Q14,Tabelle4[Typ]&Tabelle4[Breite '[mm']]&Tabelle4[Höhe '[mm']]&Tabelle4[Bauhöhe Radiator '[mm']]&Tabelle4[Nabenabstand Radiator '[mm']]&Tabelle4[Bautiefe Radiator '[mm']],Tabelle4[Wärmeleistung (Radiatoren je Glied) '[W']],,-1,1)} -> 0 | EG10: =Heizflächen!R14 -> 0 | EH10: =IF(AND(Tabelle3[[#This Row],[Gliederanzahl]]>0,Heizflächen!J14="Radiator"),Tabelle3[[#This Row],[Norm Heizleistung QNorm]]*Tabelle3[[#This Row],[f = (Δθm1/Δθm2)^n]]*Tabelle3[[#This Row],[Abminderungsfaktor]]*Tabelle3[[#This Row],[Gliederanzahl]],Tabelle3[[#This Row],[Abminderungsfaktor]]*Tabelle3[[#This Row],[f = (Δθm1/Δθm2)^n]]*Tabelle3[[#This Row],[Norm Heizleistung QNorm]]) -> 0 | EM10: =Heizflächen!C14 -> 0 | EN10: =Heizflächen!D14 -> 0 | EO10: =1-(Heizflächen!S14/0.075) -> 1 | EP10: =100*(0.045-Heizflächen!T14) -> 4.5 | EQ10: =250*(Heizflächen!U14-0.02) -> -5 | ER10: =_xlfn.XLOOKUP(Tabelle14[[#This Row],[Wärmedurchlasswiderstand Bodenbelag]],Tabelle17[Wärmedurchlasswiderstand Rλ,B in '[m²K/W']],Tabelle17[aT],0,-1,1) -> 1.23 | ES10: {=_xlfn.XLOOKUP(Heizflächen!S14&Tabelle14[[#This Row],[Wärmedurchlasswiderstand Bodenbelag]],Tabelle18[T]&Tabelle18[Rλ,B in '[m²K/W']],Tabelle18[au],0,-1,1)} -> 0 | ET10: {=_xlfn.XLOOKUP(Heizflächen!S14&Tabelle14[[#This Row],[Wärmedurchlasswiderstand Bodenbelag]],Tabelle19[T]&Tabelle19[Rλ,B in '[m²K/W']],Tabelle19[aD],0,-1,1)} -> 0 | EU10: =_xlfn.XLOOKUP(Heizflächen!$U$64,Tabelle5[Auswählbare Vor-und Rücklauftemperaturen],Tabelle5[Vorlauf],0,0,1) -> 35 | EV10: =_xlfn.XLOOKUP(Heizflächen!$U$64,Tabelle5[Auswählbare Vor-und Rücklauftemperaturen],Tabelle5[Rücklauf],0,0,1) -> 30 | EW10: =((Tabelle14[[#This Row],[gewünschte Vorlauftemperatur]]-Tabelle14[[#This Row],[gewünschte Rücklauftemperatur]])/LN((Tabelle14[[#This Row],[gewünschte Vorlauftemperatur]]-Heizflächen!G14)/(Tabelle14[[#This Row],[gewünschte Rücklauftemperatur]]-Heizflächen!G14))) -> 32.435796 | EX10: =_xlfn.XLOOKUP(Heizflächen!V14,Tabelle13[Bodenbelagsmaterial],Tabelle13[Wärmedurchlasswiderstand Rλ,B in '[m²K/W']],0,0,1) -> 0 | EY10: =((1/10.8)+(0.045/1))/((1/10.8)+(0.045/1.4)+Tabelle14[[#This Row],[Wärmedurchlasswiderstand Bodenbelag]]) -> 1.1030753 | EZ10: 6.7 | FA10: =Tabelle14[[#This Row],[B '[W/(m²K)']]]*Tabelle14[[#This Row],[aB]]*(Tabelle14[[#This Row],[aT]]^Tabelle14[[#This Row],[mT]])*(Tabelle14[[#This Row],[au]]^Tabelle14[[#This Row],[mu]])*(Tabelle14[[#This Row],[aD]]^Tabelle14[[#This Row],[mD]])*Tabelle14[[#This Row],[gewünschte Übertemperatur Δθm]] -> #DIV/0! | FB10: =IFERROR(Tabelle14[[#This Row],[q '[W/m²']]]*(Heizflächen!E14-Heizflächen!F14),0) -> 0 | FC10: =Heizflächen!H14 -> 3 | FI10: 4
B11: S. Becher | M11: Holz | N11: kg | O11: 4.07 | P11: 0 | Q11: =Allgemein!C144 -> 0.04 | AO11: D | AP11: 100 | AQ11: 130 | BH11: Typ 33 | BI11: 1000 | BJ11: 300 | BN11: 732 | CC11: 90/70 | CD11: 90 | CE11: 70 | CI11: 75 | CJ11: 65 | CK11: 20 | DQ11: =Heizflächen!C15 -> 0 | DR11: =Heizflächen!D15 -> 0 | DS11: =Heizflächen!H15 -> 4 | DT11: =Heizflächen!G15 -> 0 | DU11: =_xlfn.XLOOKUP(Heizflächen!$U$64,Tabelle5[Auswählbare Vor-und Rücklauftemperaturen],Tabelle5[Vorlauf],0,0,1) -> 35 | DV11: =_xlfn.XLOOKUP(Heizflächen!$U$64,Tabelle5[Auswählbare Vor-und Rücklauftemperaturen],Tabelle5[Rücklauf],0,0,1) -> 30 | DW11: =((Tabelle3[[#This Row],[gewünschte Vorlauftemperatur]]-Tabelle3[[#This Row],[gewünschte Rücklauftemperatur]])/LN((Tabelle3[[#This Row],[gewünschte Vorlauftemperatur]]-Tabelle3[[#This Row],[Auslegungsinnentemperatur '[°C']]])/(Tabelle3[[#This Row],[gewünschte Rücklauftemperatur]]-Tabelle3[[#This Row],[Auslegungsinnentemperatur '[°C']]]))) -> 32.435796 | DX11: =_xlfn.XLOOKUP($DZ$3,Tabelle6[Systemtemperatur bei Norm-Wärmeleistungsbestimmung],Tabelle6[Vorlauf],0,0,1) -> 55 | DY11: =_xlfn.XLOOKUP($DZ$3,Tabelle6[Systemtemperatur bei Norm-Wärmeleistungsbestimmung],Tabelle6[Rücklauf],0,0,1) -> 45 | DZ11: =_xlfn.XLOOKUP($DZ$3,Tabelle6[Systemtemperatur bei Norm-Wärmeleistungsbestimmung],Tabelle6[Norm Innentemperatur],0,0,1) -> 20 | EA11: =((Tabelle3[[#This Row],[Norm Vorlauftemperatur]]-Tabelle3[[#This Row],[Norm Rücklauftemperatur]])/LN((Tabelle3[[#This Row],[Norm Vorlauftemperatur]]-Tabelle3[[#This Row],[Norm Innentemperatur]])/(Tabelle3[[#This Row],[Norm Rücklauftemperatur]]-Tabelle3[[#This Row],[Norm Innentemperatur]]))) -> 29.720134 | EB11: =_xlfn.XLOOKUP(Heizflächen!I15,Tabelle2[Typ],Tabelle2[Heizkörperexponent],0,1,1) -> 0 | EC11: =Heizflächen!K15 -> 0 | ED11: =IF(Tabelle3[[#This Row],[Heizkörper in Nische?]]="Nein",1,_xlfn.XLOOKUP(Heizflächen!L15, Tabelle8[Höhe über HK],Tabelle8[Abminderungsfaktor],1,0,1)) -> 1 | EE11: =(DW11/EA11)^Tabelle3[[#This Row],[Heizkörperexponent n]] -> 1 | EF11: {=_xlfn.XLOOKUP(Heizflächen!J15&Heizflächen!M15&Heizflächen!N15&Heizflächen!O15&Heizflächen!P15&Heizflächen!Q15,Tabelle4[Typ]&Tabelle4[Breite '[mm']]&Tabelle4[Höhe '[mm']]&Tabelle4[Bauhöhe Radiator '[mm']]&Tabelle4[Nabenabstand Radiator '[mm']]&Tabelle4[Bautiefe Radiator '[mm']],Tabelle4[Wärmeleistung (Radiatoren je Glied) '[W']],,-1,1)} -> 0 | EG11: =Heizflächen!R15 -> 0 | EH11: =IF(AND(Tabelle3[[#This Row],[Gliederanzahl]]>0,Heizflächen!J15="Radiator"),Tabelle3[[#This Row],[Norm Heizleistung QNorm]]*Tabelle3[[#This Row],[f = (Δθm1/Δθm2)^n]]*Tabelle3[[#This Row],[Abminderungsfaktor]]*Tabelle3[[#This Row],[Gliederanzahl]],Tabelle3[[#This Row],[Abminderungsfaktor]]*Tabelle3[[#This Row],[f = (Δθm1/Δθm2)^n]]*Tabelle3[[#This Row],[Norm Heizleistung QNorm]]) -> 0 | EM11: =Heizflächen!C15 -> 0 | EN11: =Heizflächen!D15 -> 0 | EO11: =1-(Heizflächen!S15/0.075) -> 1 | EP11: =100*(0.045-Heizflächen!T15) -> 4.5 | EQ11: =250*(Heizflächen!U15-0.02) -> -5 | ER11: =_xlfn.XLOOKUP(Tabelle14[[#This Row],[Wärmedurchlasswiderstand Bodenbelag]],Tabelle17[Wärmedurchlasswiderstand Rλ,B in '[m²K/W']],Tabelle17[aT],0,-1,1) -> 1.23 | ES11: {=_xlfn.XLOOKUP(Heizflächen!S15&Tabelle14[[#This Row],[Wärmedurchlasswiderstand Bodenbelag]],Tabelle18[T]&Tabelle18[Rλ,B in '[m²K/W']],Tabelle18[au],0,-1,1)} -> 0 | ET11: {=_xlfn.XLOOKUP(Heizflächen!S15&Tabelle14[[#This Row],[Wärmedurchlasswiderstand Bodenbelag]],Tabelle19[T]&Tabelle19[Rλ,B in '[m²K/W']],Tabelle19[aD],0,-1,1)} -> 0 | EU11: =_xlfn.XLOOKUP(Heizflächen!$U$64,Tabelle5[Auswählbare Vor-und Rücklauftemperaturen],Tabelle5[Vorlauf],0,0,1) -> 35 | EV11: =_xlfn.XLOOKUP(Heizflächen!$U$64,Tabelle5[Auswählbare Vor-und Rücklauftemperaturen],Tabelle5[Rücklauf],0,0,1) -> 30 | EW11: =((Tabelle14[[#This Row],[gewünschte Vorlauftemperatur]]-Tabelle14[[#This Row],[gewünschte Rücklauftemperatur]])/LN((Tabelle14[[#This Row],[gewünschte Vorlauftemperatur]]-Heizflächen!G15)/(Tabelle14[[#This Row],[gewünschte Rücklauftemperatur]]-Heizflächen!G15))) -> 32.435796 | EX11: =_xlfn.XLOOKUP(Heizflächen!V15,Tabelle13[Bodenbelagsmaterial],Tabelle13[Wärmedurchlasswiderstand Rλ,B in '[m²K/W']],0,0,1) -> 0 | EY11: =((1/10.8)+(0.045/1))/((1/10.8)+(0.045/1.4)+Tabelle14[[#This Row],[Wärmedurchlasswiderstand Bodenbelag]]) -> 1.1030753 | EZ11: 6.7 | FA11: =Tabelle14[[#This Row],[B '[W/(m²K)']]]*Tabelle14[[#This Row],[aB]]*(Tabelle14[[#This Row],[aT]]^Tabelle14[[#This Row],[mT]])*(Tabelle14[[#This Row],[au]]^Tabelle14[[#This Row],[mu]])*(Tabelle14[[#This Row],[aD]]^Tabelle14[[#This Row],[mD]])*Tabelle14[[#This Row],[gewünschte Übertemperatur Δθm]] -> #DIV/0! | FB11: =IFERROR(Tabelle14[[#This Row],[q '[W/m²']]]*(Heizflächen!E15-Heizflächen!F15),0) -> 0 | FC11: =Heizflächen!H15 -> 4 | FI11: 5 | FX11: Außenwand | GA11: Fenster und Türen | GD11: Dach | GG11: Boden (unterer Gebäudeabschluss) | GJ11: Keller | GM11: Heizung
